Workbook

Sheet Cover
B2: Operating Model Assessment Toolkit
B3: CTO Consulting | Business Analysis Practice
B4: ="Client: "&IF(Engagement!C5="","[enter on the Engagement tab]",Engagement!C5)&" | Status: "&Engagement!C14 -> Client: [enter on the Engagement tab] | Status: Mobilising
B6: Purpose
B7: A structured toolkit for an exhaustive assessment of how an organisation delivers value: its strategy, customers, services, processes, capabilities, structure, governance, people, culture, performance management, technology, data, suppliers, locations, risk and compliance, finances and change capability. It combines a 157-question maturity diagnostic across 17 dimensions with the planning tools, current-state inventories, analysis and outputs needed to move from evidence to a prioritised set of recommendations.
B9: How to use this workbook
B10: 1. Mobilise | C10: Complete the Engagement tab: client details, objectives, scope, hypotheses, design principles and assessment settings.
B11: 2. Plan | C11: Register stakeholders, tailor the Interview Guides and issue the Document Requests list.
B12: 3. Discover | C12: Run interviews and workshops, review documents and populate the current-state inventories (Capabilities, Processes, Org Structure, Decision Rights, Applications, Suppliers, Locations, Cost Baseline).
B13: 4. Assess | C13: Score each question on the Assessment tab (current and target maturity, 1–5 or N/A) against the Maturity Model and 'What good looks like'. Record the evidence reviewed and your confidence in it.
B14: 5. Analyse | C14: Log findings and root causes on the Findings tab, validate them with stakeholders and review the Dashboard.
B15: 6. Recommend | C15: Describe the current and target state and key shifts on Current vs Target; log, score and sequence recommendations.
B16: 7. Tailor | C16: Add questions by inserting rows inside a dimension block and copying the formulas down. Dropdown values and span benchmarks are maintained on the Lists tab.
B18: Workbook map
B19: Phase | C19: Tab | D19: Purpose
B20: Set up | C20: Engagement | D20: Client details, objectives, scope, hypotheses, design principles and assessment settings.
B21: Reference | C21: Framework | D21: The 17 dimensions, definitions and mapping to recognised frameworks, plus the assessment approach.
B22: Reference | C22: Maturity Model | D22: Five-level maturity descriptors for each dimension.
B23: Plan | C23: Stakeholders | D23: Stakeholder register, influence and interest, and interview schedule.
B24: Plan | C24: Interview Guides | D24: Interview questions for ten stakeholder groups, mapped to dimensions.
B25: Plan | C25: Document Requests | D25: 69 pre-populated document and data requests with tracking.
B26: Discover & assess | C26: Assessment | D26: 157-question maturity diagnostic with evidence, confidence, gap and RAG.
B27: Discover & assess | C27: Capabilities | D27: Level 1 / Level 2 business capability map with importance, maturity and priority heat map.
B28: Discover & assess | C28: Processes | D28: Value streams and processes with documentation, automation and performance data.
B29: Discover & assess | C29: Org Structure | D29: Workforce mix, spans of control, layers and cost by business unit.
B30: Discover & assess | C30: Decision Rights | D30: RAPID matrix for key decisions with checks for missing or multiple deciders.
... B39: Reference | C39: Lists | D39: Dropdown values, span-of-control benchmarks and importance weights.
B41: Cell legend
B42: Input | C42: Enter or select a value (dropdowns where shown).
B43: Calculated | C43: Formula. Do not overwrite.
B44: Linked | C44: Pulled from another tab (green text).
B45: Example row | C45: Shows the expected format. Overwrite or delete; excluded from totals and the Dashboard.
B46: Reference content | C46: Pre-populated guidance. Tailor to the client where needed.
B48: Maturity scale
B49: 1 – Initial | C49: Ad hoc, undocumented and person-dependent. Outcomes are unpredictable and largely reactive.
B50: 2 – Developing | C50: Some practices are defined but applied inconsistently. Limited measurement; still largely reactive.
B51: 3 – Defined | C51: Practices are documented, standardised and applied consistently across the organisation.
B52: 4 – Managed | C52: Practices are measured and actively managed against targets. Decisions are data-driven.
B53: 5 – Optimised | C53: Continuous improvement is embedded. Leading practice that adapts quickly to change.
B54: N/A – Not applicable | C54: Not relevant to this organisation or outside the agreed scope. Excluded from averages.
B56: RAG ratings compare target and current maturity using the thresholds on the Engagement tab (defaults: Red when the gap is 1.5 or more, Amber from 0.75, otherwise Green).

Sheet Engagement
B1: Engagement Details
B2: Complete this tab first. Settings in the Assessment settings table drive formulas across the workbook.
B4: Engagement details
B5: Client organisation
B6: Industry / sector
B7: Engagement name
B8: Client sponsor
B9: CTO Consulting engagement lead
B10: Assessment team
B11: Start date
B12: Target completion date
B13: Workbook version | C13: 0.1
B14: Engagement status | C14: Mobilising
B16: Engagement objectives
B17: Objective 1
B18: Objective 2
B19: Objective 3
B20: Objective 4
B21: Objective 5
B23: Scope
B24: In-scope business units / functions
B25: In-scope locations / geographies
B26: Dimensions in scope | C26: All 17 dimensions
B27: Out of scope
B28: Key constraints and assumptions
B30: Key hypotheses to test
B31: Hypothesis 1
B32: Hypothesis 2
B33: Hypothesis 3
B34: Hypothesis 4
B35: Hypothesis 5
B37: Assessment settings
B38: Setting | C38: Value | D38: How it is used
B39: Default target maturity (1–5) | C39: 3 | D39: Pre-fills the Target Maturity column on the Assessment tab. Overwrite individual questions where the target differs.
B40: RAG: Red when maturity gap is at least | C40: 1.5 | D40: Gap = target minus current. Applied to questions and dimension averages.
B41: RAG: Amber when maturity gap is at least | C41: 0.75 | D41: Gaps below this threshold are Green.
B42: Prioritisation threshold (Value and Ease, 1–5) | C42: 3 | D42: Recommendations with Value and Ease at or above this score are Quick wins; high Value / low Ease are Strategic initiatives.
B43: Maximum management layers (CEO = layer 1) | C43: 6 | D43: Org Structure flags business units whose deepest reporting line exceeds this.
B44: Contract / lease / support expiry warning (days) | C44: 180 | D44: Flags suppliers, leases and applications approaching expiry.
B45: Application TIME fit threshold (1–5) | C45: 3 | D45: Business and technical fit at or above this are 'high' when classifying applications as Tolerate, Invest, Migrate or Eliminate.
B47: Operating model design principles (agreed with the client)
B48: Principle | C48: Rationale | D48: Implications for operating model design | E48: Status
B49: Example: Standardise unless differentiating | C49: Variation adds cost, risk and complexity without adding customer value. | D49: Common processes and systems across business units; local variation requires a documented case. | E49: Proposed

Sheet Framework
A1: Operating Model Framework
A2: 17 dimensions synthesised from the Operating Model Canvas (POLISM), McKinsey 7S, the Galbraith Star Model and TOGAF / BIZBOK business architecture.
A4: Code | B4: Dimension | C4: Definition | D4: Key sub-components assessed | E4: Key question answered | F4: Operating Model Canvas | G4: McKinsey 7S | H4: Galbraith Star | I4: TOGAF / BIZBOK | J4: Standards & references | K4: Questions (#)
A5: D01 | B5: Strategy & Direction | C5: The organisation's purpose, strategic objectives and the explicit choices the operating model must enable. | D5: Purpose and vision; strategic objectives; strategic choices; external environment; design principles; strategy-to-execution alignment; ESG | E5: Is it clear what the operating model must deliver, and are the strategic choices explicit? | F5: Value proposition (context for all elements) | G5: Strategy; Shared values | H5: Strategy | I5: Business motivation (drivers, goals, objectives) | J5: Balanced Scorecard; PESTLE / SWOT; Playing to Win; ASX Corporate Governance Principles | K5: =COUNTIF(Assessment!$B$6:$B$179,B5) -> 9
A6: D02 | B6: Customers, Channels & Value Proposition | C6: Who the organisation serves, what value it offers each segment, and how customers access and experience its services. | D6: Segments; value proposition; customer journeys; channel strategy; omnichannel consistency; voice of customer; service standards; accessibility | E6: Does the organisation understand and consistently deliver what its customers value, through the right channels? | F6: Value delivery chain (beneficiaries) | G6: Strategy | H6: Strategy | I6: Business architecture (actors, stakeholders, business services) | J6: Service design; NPS / CSAT / CES; WCAG 2.2; BIZBOK stakeholder mapping | K6: =COUNTIF(Assessment!$B$6:$B$179,B6) -> 9
A7: D03 | B7: Products & Services | C7: The portfolio of products and services the organisation delivers, and how that portfolio is owned, managed and evolved. | D7: Service catalogue; portfolio performance; ownership; lifecycle; complexity; innovation pipeline; pricing and funding; product obligations | E7: Is the portfolio of products and services clear, owned and actively managed for value? | F7: Value delivery chain | G7: Strategy | H7: Strategy | I7: Business services / products | J7: Product lifecycle management; ITIL 4 service catalogue; ASIC design and distribution obligations (where applicable) | K7: =COUNTIF(Assessment!$B$6:$B$179,B7) -> 8
A8: D04 | B8: Value Streams & Processes | C8: The end-to-end value streams and business processes through which work flows to deliver outcomes. | D8: Value streams; process architecture; ownership; documentation; standardisation; efficiency; automation; performance; hand-offs; embedded controls | E8: Does work flow efficiently, consistently and under control from trigger to outcome? | F8: Processes (value delivery chain) | G8: Systems | H8: Processes | I8: Business process; BIZBOK value streams | J8: APQC Process Classification Framework; BPMN 2.0; Lean; Six Sigma; process mining | K8: =COUNTIF(Assessment!$B$6:$B$179,B8) -> 10
A9: D05 | B9: Business Capabilities | C9: What the organisation must be able to do (independent of how), and the maturity of those abilities across people, process, technology and information. | D9: Capability map; strategic importance; maturity; ownership; investment alignment; gaps; duplication; sourcing | E9: Does the organisation have the capabilities its strategy needs, and is investment focused on the right ones? | F9: Processes; Organisation | G9: Skills; Systems | H9: Processes | I9: BIZBOK capability map; TOGAF capability-based planning | J9: BIZBOK Guide; TOGAF Standard 10th Edition | K9: =COUNTIF(Assessment!$B$6:$B$179,B9) -> 8
A10: D06 | B10: Organisation Structure & Roles | C10: How people and work are grouped, the reporting lines, spans and layers, and the clarity of roles and accountabilities. | D10: Structural archetype; spans of control; layers; centralisation vs devolution; shared services and CoEs; role clarity; duplication; interfaces; agility | E10: Is the structure aligned to strategy, lean, and clear about who is accountable for what? | F10: Organisation | G10: Structure | H10: Structure | I10: Organisation units; roles and actors | J10: Spans and layers analysis; organisation design archetypes | K10: =COUNTIF(Assessment!$B$6:$B$179,B10) -> 9
A11: D07 | B11: Governance & Decision Rights | C11: The bodies, delegations, policies and decision rights that direct and control the organisation. | D11: Governance framework; committee effectiveness; delegations; decision rights; decision speed; policy framework; oversight; three lines; transparency | E11: Are decisions made by the right people, at the right level, in a timely and accountable way? | F11: Management system | G11: Systems; Structure | H11: Structure; Processes | I11: Governance (architecture and enterprise) | J11: ASX Corporate Governance Principles; PGPA Act 2013 (Commonwealth entities); COBIT 2019; IIA Three Lines Model; RAPID / RACI | K11: =COUNTIF(Assessment!$B$6:$B$179,B11) -> 9
A12: D08 | B12: People, Workforce & Skills | C12: The size, mix, skills, capacity and management of the workforce needed to deliver the operating model. | D12: Workforce planning; workforce mix; capacity; skills; critical roles and succession; attraction and retention; performance; reward; WHS; engagement | E12: Does the organisation have the right people, with the right skills, in the right numbers, at the right cost? | F12: Organisation | G12: Staff; Skills | H12: People; Rewards | I12: Roles and actors | J12: Strategic workforce planning; SFIA (digital skills); Work Health and Safety Act 2011 and psychosocial hazard regulations | K12: =COUNTIF(Assessment!$B$6:$B$179,B12) -> 10
A13: D09 | B13: Culture, Leadership & Behaviours | C13: The shared values, leadership style and everyday behaviours that determine how work actually gets done. | D13: Values and behaviours; culture diagnosis; leadership; accountability; collaboration; customer centricity; psychological safety; risk culture; change readiness | E13: Do culture and leadership enable, or undermine, the intended operating model? | F13: Organisation; Management system | G13: Style; Shared values | H13: People; Rewards | I13: Not explicitly covered | J13: Culture diagnostics; 360-degree feedback; risk culture assessments | K13: =COUNTIF(Assessment!$B$6:$B$179,B13) -> 9
A14: D10 | B14: Performance Management & Planning | C14: How the organisation plans, sets targets, measures performance and uses information to steer. | D14: Planning cycle; KPI framework; cascade; management reporting; performance forums; target setting; incentive alignment; data for performance; external reporting | E14: Does the organisation know how it is performing and act on that information? | F14: Management system | G14: Systems | H14: Processes; Rewards | I14: Business motivation (measures) | J14: Balanced Scorecard; OKRs; integrated planning | K14: =COUNTIF(Assessment!$B$6:$B$179,B14) -> 9
A15: D11 | B15: Technology & Applications | C15: The applications, infrastructure, architecture and technology operating model that enable the business. | D15: Technology strategy; enterprise architecture; application portfolio; technical debt; infrastructure and cloud; integration; IT operating model; ITSM; digital, automation and AI; tech investment; end-user tools | E15: Is technology fit for purpose today, and an enabler rather than a constraint for the future? | F15: Information (systems) | G15: Systems | H15: Processes | I15: Application and technology architecture | J15: TOGAF; ITIL 4; COBIT 2019; Gartner TIME model; FinOps; Technology Business Management (TBM) | K15: =COUNTIF(Assessment!$B$6:$B$179,B15) -> 11
A16: D12 | B16: Data, Information & Analytics | C16: How data and information are governed, managed, protected and used to generate insight. | D16: Data strategy; data governance; data quality; master data; analytics; records management; privacy; classification; AI readiness | E16: Is data trusted, protected and used as an asset for decision making? | F16: Information | G16: Systems | H16: Processes | I16: Data architecture | J16: DAMA-DMBOK; Privacy Act 1988 and Australian Privacy Principles; ISO 15489 records management; ISO/IEC 42001 (AI management) | K16: =COUNTIF(Assessment!$B$6:$B$179,B16) -> 9
... A21: D17 | B21: Change, Transformation & Continuous Improvement | C21: The organisation's ability to prioritise, deliver and embed change and to improve continuously. | D21: Portfolio management; delivery methodology; delivery performance; change capacity; change management; benefits realisation; business analysis; continuous improvement; innovation; lessons learned | E21: Can the organisation move from its current to its target operating model and sustain the change? | F21: Management system | G21: Systems; Skills; Style | H21: Processes; People | I21: Implementation and migration (ADM phases E–G) | J21: PRINCE2; MSP; P3O; Agile / SAFe; Prosci ADKAR; BABOK v3; Lean | K21: =COUNTIF(Assessment!$B$6:$B$179,B21) -> 10
A24: Assessment approach
A25: Phase | C25: Key activities | D25: Workbook tabs | E25: Outputs
A26: 1. Mobilise | C26: Confirm objectives, scope, sponsor and success criteria. Identify stakeholders, issue the document request and schedule interviews. Agree design principles and assessment settings. | D26: Engagement; Stakeholders; Document Requests | E26: Engagement charter; stakeholder map; document request
A27: 2. Discover | C27: Review documents and data; run interviews, workshops and site visits; build the capability, process, organisation, decision rights, application, supplier, location and cost baselines. | D27: Interview Guides; Capabilities; Processes; Org Structure; Decision Rights; Applications; Suppliers; Locations; Cost Baseline | E27: Evidence base; current-state inventories and baselines
A28: 3. Assess & analyse | C28: Score current and target maturity for every question with evidence and confidence ratings. Identify findings and root causes and validate them with stakeholders. | D28: Assessment; Findings; Dashboard | E28: Maturity profile; validated findings; heat maps
A29: 4. Design & recommend | C29: Describe the target state and key shifts for each dimension against the design principles. Develop and prioritise recommendations by value and ease. | D29: Current vs Target; Recommendations | E29: Target operating model directions; prioritised recommendations
A30: 5. Roadmap & mobilise | C30: Sequence recommendations into horizons, confirm dependencies, owners and indicative costs, and present to the sponsor and executive. | D30: Recommendations; Dashboard | E30: Implementation roadmap; executive presentation

Sheet Maturity Model
A1: Maturity Model
A2: Descriptors for each maturity level by dimension. Use these, together with 'What good looks like' on the Assessment tab, to calibrate scores.
A4: Code | B4: Dimension | C4: 1 – Initial | D4: 2 – Developing | E4: 3 – Defined | F4: 4 – Managed | G4: 5 – Optimised
A5: All | B5: Generic scale (applies to every dimension) | C5: Ad hoc, undocumented and person-dependent. Outcomes are unpredictable and largely reactive. | D5: Some practices are defined but applied inconsistently. Limited measurement; still largely reactive. | E5: Practices are documented, standardised and applied consistently across the organisation. | F5: Practices are measured and actively managed against targets. Decisions are data-driven. | G5: Continuous improvement is embedded. Leading practice that adapts quickly to change.
A6: D01 | B6: Strategy & Direction | C6: No articulated strategy, or it exists only in the heads of a few leaders. Priorities shift frequently. | D6: Strategy documented but high level. Objectives are unclear or unprioritised; awareness is limited beyond the executive. | E6: Clear strategy with measurable objectives and agreed design principles, cascaded into business plans. | F6: Strategy drives portfolio, budget and operating model decisions. Progress reviewed quarterly and adjusted. | G6: Adaptive, evidence-led strategy informed by continuous scanning. The whole organisation understands and contributes to it.
A7: D02 | B7: Customers, Channels & Value Proposition | C7: Limited understanding of customers. Services are designed around internal structures. | D7: Basic segmentation. Feedback is collected but rarely acted upon; channels are managed in silos. | E7: Defined segments, value propositions and key journeys. Channel strategy and voice-of-customer program in place. | F7: Journeys owned and measured end to end. Consistent omnichannel experience; insight drives service change. | G7: Customer-centric by design. Predictive insight personalises services and customers co-design improvements.
A8: D03 | B8: Products & Services | C8: No complete view of products and services. Ownership is unclear. | D8: Catalogue exists but is incomplete. Performance data is partial and launches are ad hoc. | E8: Complete catalogue with owners, a defined lifecycle process and tracked performance. | F8: Portfolio actively managed on value and cost, with regular rationalisation and a strategy-linked pipeline. | G8: Portfolio continuously optimised using customer and financial insight; rapid test-and-learn development.
A9: D04 | B9: Value Streams & Processes | C9: Processes are undocumented and person-dependent, with high variation and rework. | D9: Some processes documented. Ownership is functional and measurement is limited. | E9: Process architecture defined. Key processes documented, owned and measured with KPIs. | F9: End-to-end process owners manage performance. Processes are standardised and automation is applied systematically. | G9: Processes continuously optimised using data (e.g. process mining), with intelligent automation at scale.
A10: D05 | B10: Business Capabilities | C10: No capability view. Investment is decided project by project. | D10: A capability map has been drafted but is not used in decision making. | E10: Endorsed capability map with named owners and a maturity assessment. | F10: Capability-based planning drives investment, architecture and sourcing decisions. | G10: The capability model is the common language for strategy, architecture, investment and performance.
A11: D06 | B11: Organisation Structure & Roles | C11: Structure has evolved organically. Roles are unclear and duplication is significant. | D11: Structure documented with some role clarity. Spans and layers have not been analysed. | E11: Structure aligned to strategy with a documented rationale. Roles defined; spans and layers within broad norms. | F11: Structure optimised (spans, layers, shared services) and reviewed regularly, with strong cross-unit interfaces. | G11: Adaptive structure that reconfigures around priorities with minimal disruption.
A12: D07 | B12: Governance & Decision Rights | C12: Governance is informal. Decisions are escalated or made inconsistently; delegations are out of date. | D12: Committees exist but overlap. Decision rights are unclear and delegations are poorly understood. | E12: Governance framework and delegations defined. Committees have terms of reference; key decision rights are defined. | F12: Governance is effective and efficient. Decisions are timely and made at the right level; the three lines operate well. | G12: Governance is continuously reviewed. Decision making is agile, transparent and data-driven.
A13: D08 | B13: People, Workforce & Skills | C13: Workforce management is reactive, with limited workforce data. | D13: Basic workforce reporting. Skills gaps are known anecdotally and development is ad hoc. | E13: Workforce plan and skills framework in place. Performance and development processes are consistent. | F13: Strategic workforce planning is integrated with business planning. Talent is actively managed; engagement is high. | G13: Predictive workforce analytics and agile deployment of talent. Recognised employer of choice.
A14: D09 | B14: Culture, Leadership & Behaviours | C14: Values are not defined or not lived. Trust is low and behaviours are siloed. | D14: Values are defined but inconsistently demonstrated. Culture is not measured. | E14: Culture is measured and the desired shifts are defined. Leadership development is in place. | F14: Leaders role-model desired behaviours. Culture is reinforced through hiring, reward and recognition. | G14: Culture is a source of advantage, with high psychological safety and continuous learning.
A15: D10 | B15: Performance Management & Planning | C15: Few or no KPIs. Reporting is ad hoc and manual. | D15: KPIs exist but are mainly financial or activity-based. Reporting is lagging and manual. | E15: Balanced KPI framework cascaded through the organisation. Integrated planning cycle and regular performance forums. | F15: Automated, trusted reporting. Performance information drives decisions and resource allocation. | G15: Real-time, predictive performance insight. Continuous planning and adaptive targets.
... A22: D17 | B22: Change, Transformation & Continuous Improvement | C22: Change managed project by project with no portfolio view. Delivery track record is poor. | D22: PMO established. Methods defined but inconsistently applied; benefits rarely tracked. | E22: Portfolio prioritised against strategy. Standard delivery and change methods; benefits registers maintained. | F22: Portfolio managed dynamically. Change capacity managed and benefits consistently realised. | G22: Continuous transformation capability. Improvement and innovation embedded; the organisation learns and adapts rapidly.

Sheet Stakeholders
A1: Stakeholder Register & Interview Plan
A2: Register everyone to be interviewed or engaged. Engagement approach is derived from influence and interest.
A3: Legend: yellow cells = inputs | grey cells = calculated (do not overwrite) | green text = linked from another tab | grey italic row = example (overwrite or delete)
A5: ID | B5: Name | C5: Role / title | D5: Business unit | E5: Stakeholder group | F5: Influence | G5: Interest | H5: Engagement approach | I5: Dimensions to cover | J5: Interview date | K5: Interviewer | L5: Status | M5: Key themes / notes
A6: Example | B6: Jane Citizen | C6: Chief Operating Officer | D6: Operations | E6: CEO & Executive Leadership | F6: High | G6: High | H6: =IF(OR(F6="",G6=""),"",IF(AND(F6="High",G6="High"),"Manage closely",IF(F6="High","Keep satisfied",IF(G6="High","Keep informed","Monitor")))) -> Manage closely | I6: D04; D06; D07 | J6: 46309 | K6: Lead consultant | L6: Scheduled | M6: Sees cross-unit hand-offs as the main constraint on service times.
A7: S01 | H7: =IF(OR(F7="",G7=""),"",IF(AND(F7="High",G7="High"),"Manage closely",IF(F7="High","Keep satisfied",IF(G7="High","Keep informed","Monitor"))))
A8: S02 | H8: =IF(OR(F8="",G8=""),"",IF(AND(F8="High",G8="High"),"Manage closely",IF(F8="High","Keep satisfied",IF(G8="High","Keep informed","Monitor"))))
A9: S03 | H9: =IF(OR(F9="",G9=""),"",IF(AND(F9="High",G9="High"),"Manage closely",IF(F9="High","Keep satisfied",IF(G9="High","Keep informed","Monitor"))))
A10: S04 | H10: =IF(OR(F10="",G10=""),"",IF(AND(F10="High",G10="High"),"Manage closely",IF(F10="High","Keep satisfied",IF(G10="High","Keep informed","Monitor"))))
A11: S05 | H11: =IF(OR(F11="",G11=""),"",IF(AND(F11="High",G11="High"),"Manage closely",IF(F11="High","Keep satisfied",IF(G11="High","Keep informed","Monitor"))))
A12: S06 | H12: =IF(OR(F12="",G12=""),"",IF(AND(F12="High",G12="High"),"Manage closely",IF(F12="High","Keep satisfied",IF(G12="High","Keep informed","Monitor"))))
A13: S07 | H13: =IF(OR(F13="",G13=""),"",IF(AND(F13="High",G13="High"),"Manage closely",IF(F13="High","Keep satisfied",IF(G13="High","Keep informed","Monitor"))))
A14: S08 | H14: =IF(OR(F14="",G14=""),"",IF(AND(F14="High",G14="High"),"Manage closely",IF(F14="High","Keep satisfied",IF(G14="High","Keep informed","Monitor"))))
A15: S09 | H15: =IF(OR(F15="",G15=""),"",IF(AND(F15="High",G15="High"),"Manage closely",IF(F15="High","Keep satisfied",IF(G15="High","Keep informed","Monitor"))))
A16: S10 | H16: =IF(OR(F16="",G16=""),"",IF(AND(F16="High",G16="High"),"Manage closely",IF(F16="High","Keep satisfied",IF(G16="High","Keep informed","Monitor"))))
A17: S11 | H17: =IF(OR(F17="",G17=""),"",IF(AND(F17="High",G17="High"),"Manage closely",IF(F17="High","Keep satisfied",IF(G17="High","Keep informed","Monitor"))))
A18: S12 | H18: =IF(OR(F18="",G18=""),"",IF(AND(F18="High",G18="High"),"Manage closely",IF(F18="High","Keep satisfied",IF(G18="High","Keep informed","Monitor"))))
... A66: S60 | H66: =IF(OR(F66="",G66=""),"",IF(AND(F66="High",G66="High"),"Manage closely",IF(F66="High","Keep satisfied",IF(G66="High","Keep informed","Monitor"))))

Sheet Interview Guides
A1: Interview Guides
A2: Core questions by stakeholder group, mapped to dimensions. Tailor before each interview and record notes in the yellow column.
A5: Stakeholder group | B5: # | C5: Interview question | D5: Dimensions | E5: Probe / follow-up | F5: Interview notes
A6: Board / Chair | B6: 1 | C6: What are the organisation's most important priorities over the next three to five years, and how confident are you that it can deliver them? | D6: D01 | E6: Which priorities are most at risk, and why?
A7: Board / Chair | B7: 2 | C7: How well does the information the board receives support decisions on strategy, performance and risk? | D7: D07; D10 | E7: What would you like to see more or less of?
A8: Board / Chair | B8: 3 | C8: How clear are the respective roles of the board, its committees and management? | D8: D07 | E8: Any areas where the board is drawn into operational matters?
A9: Board / Chair | B9: 4 | C9: How would you describe the organisation's risk appetite and risk culture? | D9: D15; D09 | E9: Recent examples where appetite shaped a decision.
A10: Board / Chair | B10: 5 | C10: Where do you see the greatest operational, cyber or regulatory exposures? | D10: D15 | E10: How confident are you in the organisation's resilience?
A11: Board / Chair | B11: 6 | C11: How effectively does the organisation deliver major change and realise the promised benefits? | D11: D17 | E11: Recent programs that succeeded or struggled.
A12: Board / Chair | B12: 7 | C12: What would a successful operating model look like to the board in three years? | D12: D01 | E12: How would you know it had been achieved?
A13: CEO & Executive Leadership | B13: 1 | C13: What is the organisation trying to achieve, and what must the operating model do differently to get there? | D13: D01 | E13: What are the non-negotiables?
A14: CEO & Executive Leadership | B14: 2 | C14: What are the biggest barriers to executing the strategy today? | D14: D01; D06; D07 | E14: Are they structural, process, people, technology or cultural?
A15: CEO & Executive Leadership | B15: 3 | C15: Which capabilities are most critical to success, and where are the largest gaps? | D15: D05 | E15: Which capabilities should be built, bought or partnered?
A16: CEO & Executive Leadership | B16: 4 | C16: How are decisions made at the executive level, and where do decisions get stuck? | D16: D07 | E16: Examples of decisions that took too long or were revisited.
A17: CEO & Executive Leadership | B17: 5 | C17: How well do business units and functions work together to deliver end to end for customers? | D17: D06; D09; D02 | E17: Where do hand-offs break down?
... A76: Customers & External Partners | B76: 5 | C76: How does the organisation compare with others you deal with? | D76: D02 | E76: Who does this well?
A77: Customers & External Partners | B77: 6 | C77: What should the organisation start, stop or continue doing? | D77: All
A79: Opening and closing (use in every interview): explain the purpose and confidentiality of the interview; ask the interviewee to describe their role; close by asking 'What have I not asked that I should have?' and 'Who else should we speak to?'.

Sheet Document Requests
A1: Document & Data Request List
A2: Pre-populated with the artefacts typically needed for an operating model assessment. Remove items that do not apply and add client-specific requests at the bottom.
A3: Legend: yellow cells = inputs | grey cells = calculated (do not overwrite) | green text = linked from another tab | grey italic row = example (overwrite or delete)
A5: Ref | B5: Document / artefact | C5: Dimension(s) | D5: Priority | E5: Likely owner | F5: Requested from | G5: Date requested | H5: Date due | I5: Date received | J5: Status | K5: Days outstanding | L5: Notes
A6: DR01 | B6: Strategic plan / corporate plan (current and previous) | C6: D01 | D6: High | E6: CEO office / Strategy | J6: Not requested | K6: =IF(AND(ISNUMBER(G6),NOT(ISNUMBER(I6))),TODAY()-G6,"")
A7: DR02 | B7: Business unit plans | C7: D01; D10 | D7: High | E7: Business unit heads | J7: Not requested | K7: =IF(AND(ISNUMBER(G7),NOT(ISNUMBER(I7))),TODAY()-G7,"")
A8: DR03 | B8: Board and executive committee papers and minutes (last 12 months) | C8: D07 | D8: High | E8: Company Secretary | J8: Not requested | K8: =IF(AND(ISNUMBER(G8),NOT(ISNUMBER(I8))),TODAY()-G8,"")
A9: DR04 | B9: Previous operating model reviews, restructure proposals or consulting reports | C9: D01; D06 | D9: High | E9: Strategy / CEO office | J9: Not requested | K9: =IF(AND(ISNUMBER(G9),NOT(ISNUMBER(I9))),TODAY()-G9,"")
A10: DR05 | B10: ESG / sustainability strategy and report | C10: D01; D15 | D10: Medium | E10: Sustainability lead | J10: Not requested | K10: =IF(AND(ISNUMBER(G10),NOT(ISNUMBER(I10))),TODAY()-G10,"")
A11: DR06 | B11: Customer research, segmentation and NPS / CSAT reports | C11: D02 | D11: High | E11: CX / Marketing | J11: Not requested | K11: =IF(AND(ISNUMBER(G11),NOT(ISNUMBER(I11))),TODAY()-G11,"")
A12: DR07 | B12: Customer journey maps and service blueprints | C12: D02 | D12: Medium | E12: CX lead | J12: Not requested | K12: =IF(AND(ISNUMBER(G12),NOT(ISNUMBER(I12))),TODAY()-G12,"")
A13: DR08 | B13: Complaints register and complaints analysis | C13: D02 | D13: High | E13: Complaints manager | J13: Not requested | K13: =IF(AND(ISNUMBER(G13),NOT(ISNUMBER(I13))),TODAY()-G13,"")
A14: DR09 | B14: Channel volumes and cost by channel | C14: D02; D16 | D14: Medium | E14: Operations / Finance | J14: Not requested | K14: =IF(AND(ISNUMBER(G14),NOT(ISNUMBER(I14))),TODAY()-G14,"")
A15: DR10 | B15: Service charter and customer SLAs | C15: D02; D03 | D15: Medium | E15: Operations | J15: Not requested | K15: =IF(AND(ISNUMBER(G15),NOT(ISNUMBER(I15))),TODAY()-G15,"")
A16: DR11 | B16: Product / service catalogue | C16: D03 | D16: High | E16: Product owners | J16: Not requested | K16: =IF(AND(ISNUMBER(G16),NOT(ISNUMBER(I16))),TODAY()-G16,"")
A17: DR12 | B17: Product performance and P&L reports | C17: D03; D16 | D17: Medium | E17: Finance | J17: Not requested | K17: =IF(AND(ISNUMBER(G17),NOT(ISNUMBER(I17))),TODAY()-G17,"")
... A74: DR69 | B74: Lessons-learned register and post-implementation reviews | C74: D17 | D74: Low | E74: PMO | J74: Not requested | K74: =IF(AND(ISNUMBER(G74),NOT(ISNUMBER(I74))),TODAY()-G74,"")
A75: DR70 | K75: =IF(AND(ISNUMBER(G75),NOT(ISNUMBER(I75))),TODAY()-G75,"")
A76: DR71 | K76: =IF(AND(ISNUMBER(G76),NOT(ISNUMBER(I76))),TODAY()-G76,"")
A77: DR72 | K77: =IF(AND(ISNUMBER(G77),NOT(ISNUMBER(I77))),TODAY()-G77,"")
A78: DR73 | K78: =IF(AND(ISNUMBER(G78),NOT(ISNUMBER(I78))),TODAY()-G78,"")
A79: DR74 | K79: =IF(AND(ISNUMBER(G79),NOT(ISNUMBER(I79))),TODAY()-G79,"")
A80: DR75 | K80: =IF(AND(ISNUMBER(G80),NOT(ISNUMBER(I80))),TODAY()-G80,"")
A81: DR76 | K81: =IF(AND(ISNUMBER(G81),NOT(ISNUMBER(I81))),TODAY()-G81,"")
A82: DR77 | K82: =IF(AND(ISNUMBER(G82),NOT(ISNUMBER(I82))),TODAY()-G82,"")
A83: DR78 | K83: =IF(AND(ISNUMBER(G83),NOT(ISNUMBER(I83))),TODAY()-G83,"")
A84: DR79 | K84: =IF(AND(ISNUMBER(G84),NOT(ISNUMBER(I84))),TODAY()-G84,"")
A85: DR80 | K85: =IF(AND(ISNUMBER(G85),NOT(ISNUMBER(I85))),TODAY()-G85,"")
A86: DR81 | K86: =IF(AND(ISNUMBER(G86),NOT(ISNUMBER(I86))),TODAY()-G86,"")
... A89: DR84 | K89: =IF(AND(ISNUMBER(G89),NOT(ISNUMBER(I89))),TODAY()-G89,"")

Sheet Assessment
A1: Operating Model Maturity Assessment
A2: Score current and target maturity for each question (1–5, or N/A). Importance: 1 = low, 2 = medium, 3 = high. Gap = target − current; weighted gap = gap × importance (shortfalls only).
A3: Legend: yellow cells = inputs | grey cells = calculated (do not overwrite) | green text = linked from another tab | grey italic row = example (overwrite or delete)
A5: ID | B5: Dimension | C5: Sub-component | D5: Assessment question | E5: What good looks like | F5: Importance (1–3) | G5: Current maturity (1–5 / N/A) | H5: Target maturity (1–5) | I5: Gap | J5: Weighted gap | K5: RAG | L5: Evidence confidence | M5: Evidence reviewed / source | N5: Observations & findings | O5: Linked finding ID(s) | P5: Evidence to request | Q5: Key stakeholders
A6: D01 Strategy & Direction | D6: The organisation's purpose, strategic objectives and the explicit choices the operating model must enable.
A7: D01.01 | B7: Strategy & Direction | C7: Purpose & vision | D7: Is there a clearly articulated purpose, vision and mission that is understood across the organisation? | E7: Purpose and vision are documented and current. Staff at all levels can explain them and how their work contributes. | F7: 2 | H7: =Engagement!$C$39 -> 3 | I7: =IF(AND(ISNUMBER(G7),ISNUMBER(H7)),H7-G7,"") | J7: =IF(AND(ISNUMBER(I7),ISNUMBER(F7)),MAX(0,I7)*F7,"") | K7: =IF(ISNUMBER(I7),IF(I7>=Engagement!$C$40,"Red",IF(I7>=Engagement!$C$41,"Amber","Green")),"") | P7: Strategic plan; vision and mission statements; staff engagement survey results | Q7: CEO; Executive team; Frontline staff
A8: D01.02 | B8: Strategy & Direction | C8: Strategic objectives | D8: Are strategic objectives specific, measurable and time-bound, with clear priorities and trade-offs? | E8: A small number of prioritised objectives with measures, targets and owners, plus explicit statements of what the organisation will not do. | F8: 2 | H8: =Engagement!$C$39 -> 3 | I8: =IF(AND(ISNUMBER(G8),ISNUMBER(H8)),H8-G8,"") | J8: =IF(AND(ISNUMBER(I8),ISNUMBER(F8)),MAX(0,I8)*F8,"") | K8: =IF(ISNUMBER(I8),IF(I8>=Engagement!$C$40,"Red",IF(I8>=Engagement!$C$41,"Amber","Green")),"") | P8: Strategic or corporate plan; board papers | Q8: CEO; Executive team; Board
A9: D01.03 | B9: Strategy & Direction | C9: Strategic choices | D9: Has the organisation made explicit choices about where it operates, whom it serves and how it creates value? | E9: Documented choices on target segments, services, channels and sources of advantage that directly inform operating model design. | F9: 2 | H9: =Engagement!$C$39 -> 3 | I9: =IF(AND(ISNUMBER(G9),ISNUMBER(H9)),H9-G9,"") | J9: =IF(AND(ISNUMBER(I9),ISNUMBER(F9)),MAX(0,I9)*F9,"") | K9: =IF(ISNUMBER(I9),IF(I9>=Engagement!$C$40,"Red",IF(I9>=Engagement!$C$41,"Amber","Green")),"") | P9: Strategy documents; market analysis; business cases | Q9: CEO; Strategy lead
A10: D01.04 | B10: Strategy & Direction | C10: External environment | D10: Does the strategy reflect a current understanding of the external environment (market, regulatory, technology, economic, social)? | E10: Regular environmental scanning (e.g. PESTLE) feeds strategy refresh. Emerging regulatory and technology changes are anticipated. | F10: 2 | H10: =Engagement!$C$39 -> 3 | I10: =IF(AND(ISNUMBER(G10),ISNUMBER(H10)),H10-G10,"") | J10: =IF(AND(ISNUMBER(I10),ISNUMBER(F10)),MAX(0,I10)*F10,"") | K10: =IF(ISNUMBER(I10),IF(I10>=Engagement!$C$40,"Red",IF(I10>=Engagement!$C$41,"Amber","Green")),"") | P10: PESTLE / SWOT analyses; horizon-scanning reports; regulatory change updates | Q10: Strategy lead; Risk & Compliance
A11: D01.05 | B11: Strategy & Direction | C11: Design principles | D11: Are there agreed operating model design principles that guide how the organisation is structured and operates? | E11: Six to ten principles (e.g. 'customer first', 'standardise unless differentiating', 'digital by default') endorsed by the executive and used to test design decisions. | F11: 2 | H11: =Engagement!$C$39 -> 3 | I11: =IF(AND(ISNUMBER(G11),ISNUMBER(H11)),H11-G11,"") | J11: =IF(AND(ISNUMBER(I11),ISNUMBER(F11)),MAX(0,I11)*F11,"") | K11: =IF(ISNUMBER(I11),IF(I11>=Engagement!$C$40,"Red",IF(I11>=Engagement!$C$41,"Amber","Green")),"") | P11: Operating model documentation; design principles; executive decisions | Q11: Executive team; COO
A12: D01.06 | B12: Strategy & Direction | C12: Strategy to execution | D12: Is there a clear line of sight from strategy to portfolios, business plans, budgets and individual objectives? | E12: Strategy cascades into business unit plans, the investment portfolio, budgets and individual performance plans with traceable links. | F12: 2 | H12: =Engagement!$C$39 -> 3 | I12: =IF(AND(ISNUMBER(G12),ISNUMBER(H12)),H12-G12,"") | J12: =IF(AND(ISNUMBER(I12),ISNUMBER(F12)),MAX(0,I12)*F12,"") | K12: =IF(ISNUMBER(I12),IF(I12>=Engagement!$C$40,"Red",IF(I12>=Engagement!$C$41,"Amber","Green")),"") | P12: Business unit plans; portfolio register; budget; performance agreements | Q12: Executive team; PMO; Finance
A13: D01.07 | B13: Strategy & Direction | C13: Strategy communication | D13: How effectively is the strategy communicated to, and understood by, staff, partners and other stakeholders? | E13: Structured communication plan. Staff can articulate strategic priorities; progress is discussed through regular two-way engagement. | F13: 2 | H13: =Engagement!$C$39 -> 3 | I13: =IF(AND(ISNUMBER(G13),ISNUMBER(H13)),H13-G13,"") | J13: =IF(AND(ISNUMBER(I13),ISNUMBER(F13)),MAX(0,I13)*F13,"") | K13: =IF(ISNUMBER(I13),IF(I13>=Engagement!$C$40,"Red",IF(I13>=Engagement!$C$41,"Amber","Green")),"") | P13: Internal communication plans; intranet content; engagement survey | Q13: Communications; Frontline staff
A14: D01.08 | B14: Strategy & Direction | C14: Strategy review | D14: Is progress against the strategy reviewed regularly and the strategy adjusted in response to performance and change? | E14: Quarterly strategy reviews by the executive and board, with documented adjustments and re-prioritisation. | F14: 2 | H14: =Engagement!$C$39 -> 3 | I14: =IF(AND(ISNUMBER(G14),ISNUMBER(H14)),H14-G14,"") | J14: =IF(AND(ISNUMBER(I14),ISNUMBER(F14)),MAX(0,I14)*F14,"") | K14: =IF(ISNUMBER(I14),IF(I14>=Engagement!$C$40,"Red",IF(I14>=Engagement!$C$41,"Amber","Green")),"") | P14: Board and executive minutes; strategy performance reports | Q14: CEO; Board; Strategy lead
A15: D01.09 | B15: Strategy & Direction | C15: Sustainability & ESG | D15: Are sustainability, ESG and social-licence considerations embedded in the strategy? | E15: ESG objectives integrated into the strategy with measures. Climate-related risks and opportunities identified and disclosed where required. | F15: 2 | H15: =Engagement!$C$39 -> 3 | I15: =IF(AND(ISNUMBER(G15),ISNUMBER(H15)),H15-G15,"") | J15: =IF(AND(ISNUMBER(I15),ISNUMBER(F15)),MAX(0,I15)*F15,"") | K15: =IF(ISNUMBER(I15),IF(I15>=Engagement!$C$40,"Red",IF(I15>=Engagement!$C$41,"Amber","Green")),"") | P15: ESG / sustainability strategy; climate risk assessment; annual report | Q15: CEO; CFO; Sustainability lead
A16: D02 Customers, Channels & Value Proposition | D16: Who the organisation serves, what value it offers each segment, and how customers access and experience its services.
A17: D02.01 | B17: Customers, Channels & Value Proposition | C17: Customer segments | D17: Are customer or stakeholder segments clearly defined, with an understanding of their needs and value? | E17: Evidence-based segmentation describing the needs, behaviours, value and cost to serve of each segment. | F17: 2 | H17: =Engagement!$C$39 -> 3 | I17: =IF(AND(ISNUMBER(G17),ISNUMBER(H17)),H17-G17,"") | J17: =IF(AND(ISNUMBER(I17),ISNUMBER(F17)),MAX(0,I17)*F17,"") | K17: =IF(ISNUMBER(I17),IF(I17>=Engagement!$C$40,"Red",IF(I17>=Engagement!$C$41,"Amber","Green")),"") | P17: Segmentation studies; customer research; CRM analysis | Q17: Customer / Marketing lead; Product owners
A18: D02.02 | B18: Customers, Channels & Value Proposition | C18: Value proposition | D18: Is the value proposition for each segment clearly articulated and differentiated? | E18: Documented value propositions per segment, tested with customers and reflected in services and channels. | F18: 2 | H18: =Engagement!$C$39 -> 3 | I18: =IF(AND(ISNUMBER(G18),ISNUMBER(H18)),H18-G18,"") | J18: =IF(AND(ISNUMBER(I18),ISNUMBER(F18)),MAX(0,I18)*F18,"") | K18: =IF(ISNUMBER(I18),IF(I18>=Engagement!$C$40,"Red",IF(I18>=Engagement!$C$41,"Amber","Green")),"") | P18: Value proposition documents; brand strategy; customer research | Q18: Executive team; Marketing
A19: D02.03 | B19: Customers, Channels & Value Proposition | C19: Customer journeys | D19: Have the key end-to-end customer journeys been mapped, including pain points and moments that matter? | E19: Priority journeys mapped from the customer's perspective, with pain points quantified and owners assigned. | F19: 2 | H19: =Engagement!$C$39 -> 3 | I19: =IF(AND(ISNUMBER(G19),ISNUMBER(H19)),H19-G19,"") | J19: =IF(AND(ISNUMBER(I19),ISNUMBER(F19)),MAX(0,I19)*F19,"") | K19: =IF(ISNUMBER(I19),IF(I19>=Engagement!$C$40,"Red",IF(I19>=Engagement!$C$41,"Amber","Green")),"") | P19: Journey maps; service blueprints; complaints analysis | Q19: CX lead; Operations managers
A20: D02.04 | B20: Customers, Channels & Value Proposition | C20: Channel strategy | D20: Is there a deliberate channel strategy (digital, phone, face-to-face, partner) aligned to customer needs and cost to serve? | E20: Channel roles defined by segment and interaction type; digital first where appropriate; consistent experience across channels. | F20: 2 | H20: =Engagement!$C$39 -> 3 | I20: =IF(AND(ISNUMBER(G20),ISNUMBER(H20)),H20-G20,"") | J20: =IF(AND(ISNUMBER(I20),ISNUMBER(F20)),MAX(0,I20)*F20,"") | K20: =IF(ISNUMBER(I20),IF(I20>=Engagement!$C$40,"Red",IF(I20>=Engagement!$C$41,"Amber","Green")),"") | P20: Channel strategy; channel volume and cost data; digital analytics | Q20: CX lead; Digital lead; Contact centre manager
A21: D02.05 | B21: Customers, Channels & Value Proposition | C21: Omnichannel consistency | D21: Do customers receive a consistent experience and consistent information across channels? | E21: Single view of the customer and a shared knowledge base across channels. Customers do not need to repeat themselves. | F21: 2 | H21: =Engagement!$C$39 -> 3 | I21: =IF(AND(ISNUMBER(G21),ISNUMBER(H21)),H21-G21,"") | J21: =IF(AND(ISNUMBER(I21),ISNUMBER(F21)),MAX(0,I21)*F21,"") | K21: =IF(ISNUMBER(I21),IF(I21>=Engagement!$C$40,"Red",IF(I21>=Engagement!$C$41,"Amber","Green")),"") | P21: CRM architecture; knowledge management system; mystery shopping results | Q21: Contact centre; Digital; IT
A22: D02.06 | B22: Customers, Channels & Value Proposition | C22: Voice of customer | D22: Are customer feedback, complaints and satisfaction systematically captured, analysed and acted upon? | E22: Closed-loop voice-of-customer program (NPS / CSAT / CES) with root-cause analysis and evidence of changes made. | F22: 2 | H22: =Engagement!$C$39 -> 3 | I22: =IF(AND(ISNUMBER(G22),ISNUMBER(H22)),H22-G22,"") | J22: =IF(AND(ISNUMBER(I22),ISNUMBER(F22)),MAX(0,I22)*F22,"") | K22: =IF(ISNUMBER(I22),IF(I22>=Engagement!$C$40,"Red",IF(I22>=Engagement!$C$41,"Amber","Green")),"") | P22: VoC reports; complaints register; NPS / CSAT trends | Q22: CX lead; Complaints manager
A23: D02.07 | B23: Customers, Channels & Value Proposition | C23: Service standards | D23: Are customer service standards and commitments defined, published and measured? | E23: Published service charter or SLAs, with performance reported and remediation when targets are missed. | F23: 2 | H23: =Engagement!$C$39 -> 3 | I23: =IF(AND(ISNUMBER(G23),ISNUMBER(H23)),H23-G23,"") | J23: =IF(AND(ISNUMBER(I23),ISNUMBER(F23)),MAX(0,I23)*F23,"") | K23: =IF(ISNUMBER(I23),IF(I23>=Engagement!$C$40,"Red",IF(I23>=Engagement!$C$41,"Amber","Green")),"") | P23: Service charter; SLA performance reports | Q23: Operations managers; CX lead
A24: D02.08 | B24: Customers, Channels & Value Proposition | C24: Customer insight | D24: Does the organisation use customer data and insight to design and improve services? | E24: Customer analytics informs product, service and channel decisions; insights are shared across teams. | F24: 2 | H24: =Engagement!$C$39 -> 3 | I24: =IF(AND(ISNUMBER(G24),ISNUMBER(H24)),H24-G24,"") | J24: =IF(AND(ISNUMBER(I24),ISNUMBER(F24)),MAX(0,I24)*F24,"") | K24: =IF(ISNUMBER(I24),IF(I24>=Engagement!$C$40,"Red",IF(I24>=Engagement!$C$41,"Amber","Green")),"") | P24: Analytics reports; insight packs | Q24: Data & Analytics; Marketing
A25: D02.09 | B25: Customers, Channels & Value Proposition | C25: Accessibility & inclusion | D25: Are services accessible and inclusive for all customer groups, including customers experiencing vulnerability? | E25: Accessibility standards (e.g. WCAG 2.2 AA) met; vulnerable customer policy in place; inclusive design practised. | F25: 2 | H25: =Engagement!$C$39 -> 3 | I25: =IF(AND(ISNUMBER(G25),ISNUMBER(H25)),H25-G25,"") | J25: =IF(AND(ISNUMBER(I25),ISNUMBER(F25)),MAX(0,I25)*F25,"") | K25: =IF(ISNUMBER(I25),IF(I25>=Engagement!$C$40,"Red",IF(I25>=Engagement!$C$41,"Amber","Green")),"") | P25: Accessibility audits; vulnerable customer policy | Q25: CX lead; Digital; Legal
A26: D03 Products & Services | D26: The portfolio of products and services the organisation delivers, and how that portfolio is owned, managed and evolved.
A27: D03.01 | B27: Products & Services | C27: Service catalogue | D27: Is there a complete, current catalogue of the products and services the organisation delivers (external and internal)? | E27: A single authoritative catalogue with owners, descriptions, customers, channels and service levels. | F27: 2 | H27: =Engagement!$C$39 -> 3 | I27: =IF(AND(ISNUMBER(G27),ISNUMBER(H27)),H27-G27,"") | J27: =IF(AND(ISNUMBER(I27),ISNUMBER(F27)),MAX(0,I27)*F27,"") | K27: =IF(ISNUMBER(I27),IF(I27>=Engagement!$C$40,"Red",IF(I27>=Engagement!$C$41,"Amber","Green")),"") | P27: Product / service catalogue; internal service catalogue | Q27: Product owners; Operations
A28: D03.02 | B28: Products & Services | C28: Portfolio performance | D28: Is the performance, value or profitability of each product or service known? | E28: Revenue or value, cost, volumes and customer outcomes tracked for each product or service. | F28: 2 | H28: =Engagement!$C$39 -> 3 | I28: =IF(AND(ISNUMBER(G28),ISNUMBER(H28)),H28-G28,"") | J28: =IF(AND(ISNUMBER(I28),ISNUMBER(F28)),MAX(0,I28)*F28,"") | K28: =IF(ISNUMBER(I28),IF(I28>=Engagement!$C$40,"Red",IF(I28>=Engagement!$C$41,"Amber","Green")),"") | P28: Product P&Ls; product performance reports | Q28: CFO; Product owners
A29: D03.03 | B29: Products & Services | C29: Product ownership | D29: Does every product or service have an accountable owner with end-to-end responsibility? | E29: Named owners accountable for outcomes, lifecycle and performance. | F29: 2 | H29: =Engagement!$C$39 -> 3 | I29: =IF(AND(ISNUMBER(G29),ISNUMBER(H29)),H29-G29,"") | J29: =IF(AND(ISNUMBER(I29),ISNUMBER(F29)),MAX(0,I29)*F29,"") | K29: =IF(ISNUMBER(I29),IF(I29>=Engagement!$C$40,"Red",IF(I29>=Engagement!$C$41,"Amber","Green")),"") | P29: Role descriptions; product governance documents | Q29: Product owners; Executive team
A30: D03.04 | B30: Products & Services | C30: Lifecycle management | D30: Is there a defined lifecycle process for designing, launching, changing and retiring products and services? | E30: Stage-gated lifecycle with criteria for launch, review and retirement, applied consistently. | F30: 2 | H30: =Engagement!$C$39 -> 3 | I30: =IF(AND(ISNUMBER(G30),ISNUMBER(H30)),H30-G30,"") | J30: =IF(AND(ISNUMBER(I30),ISNUMBER(F30)),MAX(0,I30)*F30,"") | K30: =IF(ISNUMBER(I30),IF(I30>=Engagement!$C$40,"Red",IF(I30>=Engagement!$C$41,"Amber","Green")),"") | P30: Product lifecycle process; product committee minutes | Q30: Product owners; Risk
A31: D03.05 | B31: Products & Services | C31: Portfolio complexity | D31: Is portfolio complexity actively managed (e.g. overlapping, legacy or low-value products rationalised)? | E31: Periodic rationalisation reviews. The cost of complexity is understood; legacy products are migrated or retired. | F31: 2 | H31: =Engagement!$C$39 -> 3 | I31: =IF(AND(ISNUMBER(G31),ISNUMBER(H31)),H31-G31,"") | J31: =IF(AND(ISNUMBER(I31),ISNUMBER(F31)),MAX(0,I31)*F31,"") | K31: =IF(ISNUMBER(I31),IF(I31>=Engagement!$C$40,"Red",IF(I31>=Engagement!$C$41,"Amber","Green")),"") | P31: Rationalisation reviews; product counts over time | Q31: Product owners; Finance
A32: D03.06 | B32: Products & Services | C32: Innovation pipeline | D32: Is there a pipeline of new or improved products and services linked to strategy and customer insight? | E32: Managed pipeline with prioritisation criteria, a test-and-learn approach and clear funding. | F32: 2 | H32: =Engagement!$C$39 -> 3 | I32: =IF(AND(ISNUMBER(G32),ISNUMBER(H32)),H32-G32,"") | J32: =IF(AND(ISNUMBER(I32),ISNUMBER(F32)),MAX(0,I32)*F32,"") | K32: =IF(ISNUMBER(I32),IF(I32>=Engagement!$C$40,"Red",IF(I32>=Engagement!$C$41,"Amber","Green")),"") | P32: Innovation pipeline; business cases | Q32: Strategy; Product
A33: D03.07 | B33: Products & Services | C33: Pricing & funding | D33: Are pricing, fees or funding arrangements for services understood, justified and reviewed? | E33: Pricing and funding models linked to cost-to-serve and value, and reviewed at least annually. | F33: 2 | H33: =Engagement!$C$39 -> 3 | I33: =IF(AND(ISNUMBER(G33),ISNUMBER(H33)),H33-G33,"") | J33: =IF(AND(ISNUMBER(I33),ISNUMBER(F33)),MAX(0,I33)*F33,"") | K33: =IF(ISNUMBER(I33),IF(I33>=Engagement!$C$40,"Red",IF(I33>=Engagement!$C$41,"Amber","Green")),"") | P33: Pricing policy; funding agreements | Q33: CFO; Product owners
A34: D03.08 | B34: Products & Services | C34: Product obligations | D34: Are product-related regulatory obligations (e.g. consumer law, design and distribution) identified and met? | E34: Obligations mapped to each product with controls and monitoring (e.g. target market determinations where applicable). | F34: 2 | H34: =Engagement!$C$39 -> 3 | I34: =IF(AND(ISNUMBER(G34),ISNUMBER(H34)),H34-G34,"") | J34: =IF(AND(ISNUMBER(I34),ISNUMBER(F34)),MAX(0,I34)*F34,"") | K34: =IF(ISNUMBER(I34),IF(I34>=Engagement!$C$40,"Red",IF(I34>=Engagement!$C$41,"Amber","Green")),"") | P34: Obligations register; product compliance reviews | Q34: Risk & Compliance; Legal
A35: D04 Value Streams & Processes | D35: The end-to-end value streams and business processes through which work flows to deliver outcomes.
A36: D04.01 | B36: Value Streams & Processes | C36: Value streams | D36: Have the organisation's end-to-end value streams been identified (e.g. request-to-resolve, procure-to-pay, hire-to-retire)? | E36: Value streams defined from trigger to outcome, with stages, stakeholders and value items. | F36: 2 | H36: =Engagement!$C$39 -> 3 | I36: =IF(AND(ISNUMBER(G36),ISNUMBER(H36)),H36-G36,"") | J36: =IF(AND(ISNUMBER(I36),ISNUMBER(F36)),MAX(0,I36)*F36,"") | K36: =IF(ISNUMBER(I36),IF(I36>=Engagement!$C$40,"Red",IF(I36>=Engagement!$C$41,"Amber","Green")),"") | P36: Value stream maps; business architecture artefacts | Q36: COO; Business architect
A37: D04.02 | B37: Value Streams & Processes | C37: Process architecture | D37: Is there a structured process architecture (Level 0 to Level 3) covering core and supporting processes? | E37: Documented process hierarchy aligned to a reference model (e.g. APQC PCF) and actively maintained. | F37: 2 | H37: =Engagement!$C$39 -> 3 | I37: =IF(AND(ISNUMBER(G37),ISNUMBER(H37)),H37-G37,"") | J37: =IF(AND(ISNUMBER(I37),ISNUMBER(F37)),MAX(0,I37)*F37,"") | K37: =IF(ISNUMBER(I37),IF(I37>=Engagement!$C$40,"Red",IF(I37>=Engagement!$C$41,"Amber","Green")),"") | P37: Process architecture; process repository | Q37: Process owners; BA / process team
A38: D04.03 | B38: Value Streams & Processes | C38: Process ownership | D38: Do end-to-end processes have accountable owners with authority across organisational boundaries? | E38: Named end-to-end process owners with a mandate, performance measures and improvement responsibility. | F38: 2 | H38: =Engagement!$C$39 -> 3 | I38: =IF(AND(ISNUMBER(G38),ISNUMBER(H38)),H38-G38,"") | J38: =IF(AND(ISNUMBER(I38),ISNUMBER(F38)),MAX(0,I38)*F38,"") | K38: =IF(ISNUMBER(I38),IF(I38>=Engagement!$C$40,"Red",IF(I38>=Engagement!$C$41,"Amber","Green")),"") | P38: RACI; role descriptions | Q38: COO; Process owners
A39: D04.04 | B39: Value Streams & Processes | C39: Documentation | D39: Are key processes documented, current and accessible to the people who perform them? | E39: Processes documented in a common notation (e.g. BPMN 2.0) in a central repository with version control and review dates. | F39: 2 | H39: =Engagement!$C$39 -> 3 | I39: =IF(AND(ISNUMBER(G39),ISNUMBER(H39)),H39-G39,"") | J39: =IF(AND(ISNUMBER(I39),ISNUMBER(F39)),MAX(0,I39)*F39,"") | K39: =IF(ISNUMBER(I39),IF(I39>=Engagement!$C$40,"Red",IF(I39>=Engagement!$C$41,"Amber","Green")),"") | P39: Process maps; standard operating procedures; work instructions | Q39: Process owners; Frontline staff
A40: D04.05 | B40: Value Streams & Processes | C40: Standardisation | D40: Are processes standardised across business units and locations where there is no reason for variation? | E40: Common processes adopted by default. Variations are deliberate, justified and documented. | F40: 2 | H40: =Engagement!$C$39 -> 3 | I40: =IF(AND(ISNUMBER(G40),ISNUMBER(H40)),H40-G40,"") | J40: =IF(AND(ISNUMBER(I40),ISNUMBER(F40)),MAX(0,I40)*F40,"") | K40: =IF(ISNUMBER(I40),IF(I40>=Engagement!$C$40,"Red",IF(I40>=Engagement!$C$41,"Amber","Green")),"") | P40: Process comparisons across units; audit findings | Q40: Operations managers
A41: D04.06 | B41: Value Streams & Processes | C41: Efficiency & waste | D41: Are processes efficient, with minimal rework, hand-offs, delays and manual workarounds? | E41: Process performance analysed (cycle time, rework, touchpoints) and waste systematically removed using Lean methods. | F41: 2 | H41: =Engagement!$C$39 -> 3 | I41: =IF(AND(ISNUMBER(G41),ISNUMBER(H41)),H41-G41,"") | J41: =IF(AND(ISNUMBER(I41),ISNUMBER(F41)),MAX(0,I41)*F41,"") | K41: =IF(ISNUMBER(I41),IF(I41>=Engagement!$C$40,"Red",IF(I41>=Engagement!$C$41,"Amber","Green")),"") | P41: Process metrics; time-and-motion studies; workaround inventory | Q41: Operations managers; Frontline staff
A42: D04.07 | B42: Value Streams & Processes | C42: Automation | D42: What level of automation is applied, and are automation opportunities (including RPA and AI) identified and prioritised? | E42: Automation pipeline with business cases. High-volume, rules-based work is automated, with controls over bots and AI. | F42: 2 | H42: =Engagement!$C$39 -> 3 | I42: =IF(AND(ISNUMBER(G42),ISNUMBER(H42)),H42-G42,"") | J42: =IF(AND(ISNUMBER(I42),ISNUMBER(F42)),MAX(0,I42)*F42,"") | K42: =IF(ISNUMBER(I42),IF(I42>=Engagement!$C$40,"Red",IF(I42>=Engagement!$C$41,"Amber","Green")),"") | P42: Automation register; RPA / AI use-case inventory | Q42: IT; Operations; Digital
A43: D04.08 | B43: Value Streams & Processes | C43: Process performance | D43: Are process KPIs (volume, cycle time, cost, quality, compliance) defined and monitored? | E43: Process dashboards reviewed regularly by owners, with targets and corrective action. | F43: 2 | H43: =Engagement!$C$39 -> 3 | I43: =IF(AND(ISNUMBER(G43),ISNUMBER(H43)),H43-G43,"") | J43: =IF(AND(ISNUMBER(I43),ISNUMBER(F43)),MAX(0,I43)*F43,"") | K43: =IF(ISNUMBER(I43),IF(I43>=Engagement!$C$40,"Red",IF(I43>=Engagement!$C$41,"Amber","Green")),"") | P43: Process dashboards; operational reports | Q43: Process owners; Operations managers
A44: D04.09 | B44: Value Streams & Processes | C44: Hand-offs & interfaces | D44: Are hand-offs between teams, functions and third parties clearly defined and managed? | E44: Clear hand-off points, internal service agreements (OLAs) between teams, and minimal queues between steps. | F44: 2 | H44: =Engagement!$C$39 -> 3 | I44: =IF(AND(ISNUMBER(G44),ISNUMBER(H44)),H44-G44,"") | J44: =IF(AND(ISNUMBER(I44),ISNUMBER(F44)),MAX(0,I44)*F44,"") | K44: =IF(ISNUMBER(I44),IF(I44>=Engagement!$C$40,"Red",IF(I44>=Engagement!$C$41,"Amber","Green")),"") | P44: Swimlane maps; internal SLAs / OLAs | Q44: Operations managers; Team leaders
A45: D04.10 | B45: Value Streams & Processes | C45: Embedded controls | D45: Are key risk and compliance controls embedded in processes rather than applied after the fact? | E45: Controls designed into processes, mapped to risks and obligations, and tested. | F45: 2 | H45: =Engagement!$C$39 -> 3 | I45: =IF(AND(ISNUMBER(G45),ISNUMBER(H45)),H45-G45,"") | J45: =IF(AND(ISNUMBER(I45),ISNUMBER(F45)),MAX(0,I45)*F45,"") | K45: =IF(ISNUMBER(I45),IF(I45>=Engagement!$C$40,"Red",IF(I45>=Engagement!$C$41,"Amber","Green")),"") | P45: Control library; risk and control matrix (RCM) | Q45: Risk & Compliance; Process owners
A46: D05 Business Capabilities | D46: What the organisation must be able to do (independent of how), and the maturity of those abilities across people, process, technology and information.
A47: D05.01 | B47: Business Capabilities | C47: Capability map | D47: Does the organisation have a current business capability map describing what it does, independent of how? | E47: Levelled capability map (L1 to L3) endorsed by executives and used in planning and investment decisions. | F47: 2 | H47: =Engagement!$C$39 -> 3 | I47: =IF(AND(ISNUMBER(G47),ISNUMBER(H47)),H47-G47,"") | J47: =IF(AND(ISNUMBER(I47),ISNUMBER(F47)),MAX(0,I47)*F47,"") | K47: =IF(ISNUMBER(I47),IF(I47>=Engagement!$C$40,"Red",IF(I47>=Engagement!$C$41,"Amber","Green")),"") | P47: Capability map; business architecture artefacts | Q47: Enterprise / business architect; Strategy
A48: D05.02 | B48: Business Capabilities | C48: Strategic importance | D48: Have capabilities been classified by strategic importance and differentiation (differentiating vs commodity)? | E48: Each capability rated for strategic importance and differentiation, informing sourcing and investment. | F48: 2 | H48: =Engagement!$C$39 -> 3 | I48: =IF(AND(ISNUMBER(G48),ISNUMBER(H48)),H48-G48,"") | J48: =IF(AND(ISNUMBER(I48),ISNUMBER(F48)),MAX(0,I48)*F48,"") | K48: =IF(ISNUMBER(I48),IF(I48>=Engagement!$C$40,"Red",IF(I48>=Engagement!$C$41,"Amber","Green")),"") | P48: Capability heat maps; strategy documents | Q48: Executive team; Architecture
A49: D05.03 | B49: Business Capabilities | C49: Capability maturity | D49: Has capability maturity been assessed across people, process, technology and information? | E49: Periodic, evidence-based maturity assessment with a target maturity for each capability. | F49: 2 | H49: =Engagement!$C$39 -> 3 | I49: =IF(AND(ISNUMBER(G49),ISNUMBER(H49)),H49-G49,"") | J49: =IF(AND(ISNUMBER(I49),ISNUMBER(F49)),MAX(0,I49)*F49,"") | K49: =IF(ISNUMBER(I49),IF(I49>=Engagement!$C$40,"Red",IF(I49>=Engagement!$C$41,"Amber","Green")),"") | P49: Capability assessments; maturity reports | Q49: Capability owners; Architecture
A50: D05.04 | B50: Business Capabilities | C50: Capability ownership | D50: Is there a named owner for each capability, accountable for its performance and uplift? | E50: Capability owners identified with clear accountability and uplift plans. | F50: 2 | H50: =Engagement!$C$39 -> 3 | I50: =IF(AND(ISNUMBER(G50),ISNUMBER(H50)),H50-G50,"") | J50: =IF(AND(ISNUMBER(I50),ISNUMBER(F50)),MAX(0,I50)*F50,"") | K50: =IF(ISNUMBER(I50),IF(I50>=Engagement!$C$40,"Red",IF(I50>=Engagement!$C$41,"Amber","Green")),"") | P50: Capability ownership register | Q50: Executive team
A51: D05.05 | B51: Business Capabilities | C51: Investment alignment | D51: Is investment directed to the capabilities that matter most to the strategy? | E51: Portfolio investment mapped to capabilities, with spend weighted towards strategic gaps. | F51: 2 | H51: =Engagement!$C$39 -> 3 | I51: =IF(AND(ISNUMBER(G51),ISNUMBER(H51)),H51-G51,"") | J51: =IF(AND(ISNUMBER(I51),ISNUMBER(F51)),MAX(0,I51)*F51,"") | K51: =IF(ISNUMBER(I51),IF(I51>=Engagement!$C$40,"Red",IF(I51>=Engagement!$C$41,"Amber","Green")),"") | P51: Investment portfolio mapped to capabilities; budget | Q51: PMO; CFO; Architecture
A52: D05.06 | B52: Business Capabilities | C52: Capability gaps | D52: Are gaps between current and required capabilities identified, with plans to close them? | E52: Gap analysis linked to roadmap initiatives with timeframes and funding. | F52: 2 | H52: =Engagement!$C$39 -> 3 | I52: =IF(AND(ISNUMBER(G52),ISNUMBER(H52)),H52-G52,"") | J52: =IF(AND(ISNUMBER(I52),ISNUMBER(F52)),MAX(0,I52)*F52,"") | K52: =IF(ISNUMBER(I52),IF(I52>=Engagement!$C$40,"Red",IF(I52>=Engagement!$C$41,"Amber","Green")),"") | P52: Gap analyses; roadmaps | Q52: Architecture; Strategy
A53: D05.07 | B53: Business Capabilities | C53: Capability duplication | D53: Are capabilities duplicated across business units, and is any duplication deliberate? | E53: Duplication identified; consolidation or shared services considered where appropriate. | F53: 2 | H53: =Engagement!$C$39 -> 3 | I53: =IF(AND(ISNUMBER(G53),ISNUMBER(H53)),H53-G53,"") | J53: =IF(AND(ISNUMBER(I53),ISNUMBER(F53)),MAX(0,I53)*F53,"") | K53: =IF(ISNUMBER(I53),IF(I53>=Engagement!$C$40,"Red",IF(I53>=Engagement!$C$41,"Amber","Green")),"") | P53: Capability-to-organisation mapping | Q53: COO; Architecture
A54: D05.08 | B54: Business Capabilities | C54: Capability sourcing | D54: Is there a deliberate decision on which capabilities are delivered in-house, shared, outsourced or partnered? | E54: Sourcing decisions follow a documented framework linked to differentiation, cost and risk. | F54: 2 | H54: =Engagement!$C$39 -> 3 | I54: =IF(AND(ISNUMBER(G54),ISNUMBER(H54)),H54-G54,"") | J54: =IF(AND(ISNUMBER(I54),ISNUMBER(F54)),MAX(0,I54)*F54,"") | K54: =IF(ISNUMBER(I54),IF(I54>=Engagement!$C$40,"Red",IF(I54>=Engagement!$C$41,"Amber","Green")),"") | P54: Sourcing strategy; outsourcing contracts | Q54: COO; Procurement
A55: D06 Organisation Structure & Roles | D55: How people and work are grouped, the reporting lines, spans and layers, and the clarity of roles and accountabilities.
A56: D06.01 | B56: Organisation Structure & Roles | C56: Structural archetype | D56: Is the organisational structure (functional, divisional, matrix, product / platform, network) aligned to the strategy and design principles? | E56: Structure explicitly linked to strategy with a documented rationale. Trade-offs are understood and managed. | F56: 2 | H56: =Engagement!$C$39 -> 3 | I56: =IF(AND(ISNUMBER(G56),ISNUMBER(H56)),H56-G56,"") | J56: =IF(AND(ISNUMBER(I56),ISNUMBER(F56)),MAX(0,I56)*F56,"") | K56: =IF(ISNUMBER(I56),IF(I56>=Engagement!$C$40,"Red",IF(I56>=Engagement!$C$41,"Amber","Green")),"") | P56: Organisation charts; restructure business cases | Q56: CEO; CHRO; Executive team
A57: D06.02 | B57: Organisation Structure & Roles | C57: Spans of control | D57: Are spans of control appropriate for the nature of the work? | E57: Spans within agreed benchmarks (see Lists tab); outliers are justified. | F57: 2 | H57: =Engagement!$C$39 -> 3 | I57: =IF(AND(ISNUMBER(G57),ISNUMBER(H57)),H57-G57,"") | J57: =IF(AND(ISNUMBER(I57),ISNUMBER(F57)),MAX(0,I57)*F57,"") | K57: =IF(ISNUMBER(I57),IF(I57>=Engagement!$C$40,"Red",IF(I57>=Engagement!$C$41,"Amber","Green")),"") | P57: HR system extract (reporting lines); organisation charts | Q57: CHRO; HR analytics
A58: D06.03 | B58: Organisation Structure & Roles | C58: Layers | D58: Is the number of management layers appropriate for the organisation's size and complexity? | E58: Minimal layers between the CEO and the frontline (commonly 5 to 7 for large organisations); decisions are not slowed by hierarchy. | F58: 2 | H58: =Engagement!$C$39 -> 3 | I58: =IF(AND(ISNUMBER(G58),ISNUMBER(H58)),H58-G58,"") | J58: =IF(AND(ISNUMBER(I58),ISNUMBER(F58)),MAX(0,I58)*F58,"") | K58: =IF(ISNUMBER(I58),IF(I58>=Engagement!$C$40,"Red",IF(I58>=Engagement!$C$41,"Amber","Green")),"") | P58: HR system extract; organisation charts | Q58: CHRO; HR analytics
A59: D06.04 | B59: Organisation Structure & Roles | C59: Centralisation vs devolution | D59: Is there a clear, deliberate balance between centralised, shared and devolved functions? | E59: The rationale for what is centralised versus local is documented; there are minimal shadow functions. | F59: 2 | H59: =Engagement!$C$39 -> 3 | I59: =IF(AND(ISNUMBER(G59),ISNUMBER(H59)),H59-G59,"") | J59: =IF(AND(ISNUMBER(I59),ISNUMBER(F59)),MAX(0,I59)*F59,"") | K59: =IF(ISNUMBER(I59),IF(I59>=Engagement!$C$40,"Red",IF(I59>=Engagement!$C$41,"Amber","Green")),"") | P59: Functional model documentation; cost data | Q59: COO; CFO; CHRO
A60: D06.05 | B60: Organisation Structure & Roles | C60: Shared services & CoEs | D60: Are shared services and centres of excellence used where they add value, with clear service agreements? | E60: Shared services operate with service catalogues, SLAs and customer satisfaction measures. | F60: 2 | H60: =Engagement!$C$39 -> 3 | I60: =IF(AND(ISNUMBER(G60),ISNUMBER(H60)),H60-G60,"") | J60: =IF(AND(ISNUMBER(I60),ISNUMBER(F60)),MAX(0,I60)*F60,"") | K60: =IF(ISNUMBER(I60),IF(I60>=Engagement!$C$40,"Red",IF(I60>=Engagement!$C$41,"Amber","Green")),"") | P60: Shared services catalogue; SLAs; satisfaction surveys | Q60: Shared services leads; Business unit heads
A61: D06.06 | B61: Organisation Structure & Roles | C61: Role clarity | D61: Are roles, accountabilities and responsibilities clearly defined and understood? | E61: Current role descriptions and documented accountabilities, with little overlap or gaps between roles. | F61: 2 | H61: =Engagement!$C$39 -> 3 | I61: =IF(AND(ISNUMBER(G61),ISNUMBER(H61)),H61-G61,"") | J61: =IF(AND(ISNUMBER(I61),ISNUMBER(F61)),MAX(0,I61)*F61,"") | K61: =IF(ISNUMBER(I61),IF(I61>=Engagement!$C$40,"Red",IF(I61>=Engagement!$C$41,"Amber","Green")),"") | P61: Position descriptions; RACIs; engagement survey | Q61: CHRO; Managers; Staff
A62: D06.07 | B62: Organisation Structure & Roles | C62: Duplication & shadow functions | D62: Is there duplication of roles or activities across units (e.g. shadow finance, HR or IT teams)? | E62: Duplicated activity identified and deliberately resolved. | F62: 2 | H62: =Engagement!$C$39 -> 3 | I62: =IF(AND(ISNUMBER(G62),ISNUMBER(H62)),H62-G62,"") | J62: =IF(AND(ISNUMBER(I62),ISNUMBER(F62)),MAX(0,I62)*F62,"") | K62: =IF(ISNUMBER(I62),IF(I62>=Engagement!$C$40,"Red",IF(I62>=Engagement!$C$41,"Amber","Green")),"") | P62: Activity analysis; organisation charts; cost centre data | Q62: CFO; CHRO; COO
A63: D06.08 | B63: Organisation Structure & Roles | C63: Interfaces & collaboration | D63: Are interfaces between organisational units clearly defined, with effective mechanisms for cross-unit work? | E63: Cross-functional teams, forums and operating agreements support end-to-end delivery. | F63: 2 | H63: =Engagement!$C$39 -> 3 | I63: =IF(AND(ISNUMBER(G63),ISNUMBER(H63)),H63-G63,"") | J63: =IF(AND(ISNUMBER(I63),ISNUMBER(F63)),MAX(0,I63)*F63,"") | K63: =IF(ISNUMBER(I63),IF(I63>=Engagement!$C$40,"Red",IF(I63>=Engagement!$C$41,"Amber","Green")),"") | P63: Operating agreements; forum terms of reference | Q63: Executive team; Managers
A64: D06.09 | B64: Organisation Structure & Roles | C64: Structural agility | D64: Can the structure adapt quickly to changing priorities (e.g. through cross-functional or agile teams)? | E64: Mechanisms exist to form and re-form teams around priorities without full restructures. | F64: 2 | H64: =Engagement!$C$39 -> 3 | I64: =IF(AND(ISNUMBER(G64),ISNUMBER(H64)),H64-G64,"") | J64: =IF(AND(ISNUMBER(I64),ISNUMBER(F64)),MAX(0,I64)*F64,"") | K64: =IF(ISNUMBER(I64),IF(I64>=Engagement!$C$40,"Red",IF(I64>=Engagement!$C$41,"Amber","Green")),"") | P64: Team models; resourcing processes | Q64: COO; CHRO
A65: D07 Governance & Decision Rights | D65: The bodies, delegations, policies and decision rights that direct and control the organisation.
A66: D07.01 | B66: Governance & Decision Rights | C66: Governance framework | D66: Is there a documented governance framework showing the governing bodies and committees and how they relate? | E66: Governance map with a clear hierarchy, purpose, membership and reporting lines for each body. | F66: 2 | H66: =Engagement!$C$39 -> 3 | I66: =IF(AND(ISNUMBER(G66),ISNUMBER(H66)),H66-G66,"") | J66: =IF(AND(ISNUMBER(I66),ISNUMBER(F66)),MAX(0,I66)*F66,"") | K66: =IF(ISNUMBER(I66),IF(I66>=Engagement!$C$40,"Red",IF(I66>=Engagement!$C$41,"Amber","Green")),"") | P66: Governance framework; committee charters | Q66: Company Secretary / Board Secretariat; CEO
A67: D07.02 | B67: Governance & Decision Rights | C67: Committee effectiveness | D67: Do governance forums have clear terms of reference, the right membership and effective agendas? | E67: Current terms of reference. Forums focus on decisions rather than information; effectiveness is reviewed periodically. | F67: 2 | H67: =Engagement!$C$39 -> 3 | I67: =IF(AND(ISNUMBER(G67),ISNUMBER(H67)),H67-G67,"") | J67: =IF(AND(ISNUMBER(I67),ISNUMBER(F67)),MAX(0,I67)*F67,"") | K67: =IF(ISNUMBER(I67),IF(I67>=Engagement!$C$40,"Red",IF(I67>=Engagement!$C$41,"Amber","Green")),"") | P67: Terms of reference; agendas; minutes; effectiveness reviews | Q67: Committee chairs; Secretariat
A68: D07.03 | B68: Governance & Decision Rights | C68: Delegations of authority | D68: Are financial and non-financial delegations documented, current and understood? | E68: Delegations instrument aligned to structure and risk appetite, reviewed annually and system-enforced where possible. | F68: 2 | H68: =Engagement!$C$39 -> 3 | I68: =IF(AND(ISNUMBER(G68),ISNUMBER(H68)),H68-G68,"") | J68: =IF(AND(ISNUMBER(I68),ISNUMBER(F68)),MAX(0,I68)*F68,"") | K68: =IF(ISNUMBER(I68),IF(I68>=Engagement!$C$40,"Red",IF(I68>=Engagement!$C$41,"Amber","Green")),"") | P68: Delegations of authority schedule; system workflow rules | Q68: CFO; Legal
A69: D07.04 | B69: Governance & Decision Rights | C69: Decision rights | D69: Is it clear who recommends, agrees, decides and provides input on key decisions? | E69: Decision rights (e.g. RAPID or RACI) defined for key decisions, which are made at the lowest appropriate level. | F69: 2 | H69: =Engagement!$C$39 -> 3 | I69: =IF(AND(ISNUMBER(G69),ISNUMBER(H69)),H69-G69,"") | J69: =IF(AND(ISNUMBER(I69),ISNUMBER(F69)),MAX(0,I69)*F69,"") | K69: =IF(ISNUMBER(I69),IF(I69>=Engagement!$C$40,"Red",IF(I69>=Engagement!$C$41,"Amber","Green")),"") | P69: Decision rights matrix; RACI | Q69: Executive team; Managers
A70: D07.05 | B70: Governance & Decision Rights | C70: Decision speed | D70: Are decisions made in a timely way, without excessive escalation or duplication of forums? | E70: Reasonable decision cycle times, little re-litigation of decisions and clear escalation thresholds. | F70: 2 | H70: =Engagement!$C$39 -> 3 | I70: =IF(AND(ISNUMBER(G70),ISNUMBER(H70)),H70-G70,"") | J70: =IF(AND(ISNUMBER(I70),ISNUMBER(F70)),MAX(0,I70)*F70,"") | K70: =IF(ISNUMBER(I70),IF(I70>=Engagement!$C$40,"Red",IF(I70>=Engagement!$C$41,"Amber","Green")),"") | P70: Decision logs; minutes; interview evidence | Q70: Executive team; Managers
A71: D07.06 | B71: Governance & Decision Rights | C71: Policy framework | D71: Is there a structured policy framework with ownership, review cycles and alignment to obligations? | E71: Policy hierarchy (policy, standard, procedure) with owners, review dates and attestation. | F71: 2 | H71: =Engagement!$C$39 -> 3 | I71: =IF(AND(ISNUMBER(G71),ISNUMBER(H71)),H71-G71,"") | J71: =IF(AND(ISNUMBER(I71),ISNUMBER(F71)),MAX(0,I71)*F71,"") | K71: =IF(ISNUMBER(I71),IF(I71>=Engagement!$C$40,"Red",IF(I71>=Engagement!$C$41,"Amber","Green")),"") | P71: Policy register; policy framework | Q71: Risk & Compliance; Policy owners
A72: D07.07 | B72: Governance & Decision Rights | C72: Board & executive oversight | D72: Does the board and executive receive timely, decision-useful information on performance, risk and change? | E72: Integrated reporting to the board covering strategy, performance, risk and major programs. | F72: 2 | H72: =Engagement!$C$39 -> 3 | I72: =IF(AND(ISNUMBER(G72),ISNUMBER(H72)),H72-G72,"") | J72: =IF(AND(ISNUMBER(I72),ISNUMBER(F72)),MAX(0,I72)*F72,"") | K72: =IF(ISNUMBER(I72),IF(I72>=Engagement!$C$40,"Red",IF(I72>=Engagement!$C$41,"Amber","Green")),"") | P72: Board packs; executive reports | Q72: Board; CEO; Company Secretary
A73: D07.08 | B73: Governance & Decision Rights | C73: Three lines | D73: Are roles across the three lines (management, risk and compliance oversight, independent assurance) clear and effective? | E73: Clear separation of accountabilities between the first, second and third lines, with a coordinated assurance map. | F73: 2 | H73: =Engagement!$C$39 -> 3 | I73: =IF(AND(ISNUMBER(G73),ISNUMBER(H73)),H73-G73,"") | J73: =IF(AND(ISNUMBER(I73),ISNUMBER(F73)),MAX(0,I73)*F73,"") | K73: =IF(ISNUMBER(I73),IF(I73>=Engagement!$C$40,"Red",IF(I73>=Engagement!$C$41,"Amber","Green")),"") | P73: Assurance map; risk framework; internal audit charter | Q73: CRO; Head of Internal Audit
A74: D07.09 | B74: Governance & Decision Rights | C74: Transparency & accountability | D74: Are decisions, rationale and accountabilities recorded and traceable? | E74: Decision registers, minutes and action logs maintained and followed up. | F74: 2 | H74: =Engagement!$C$39 -> 3 | I74: =IF(AND(ISNUMBER(G74),ISNUMBER(H74)),H74-G74,"") | J74: =IF(AND(ISNUMBER(I74),ISNUMBER(F74)),MAX(0,I74)*F74,"") | K74: =IF(ISNUMBER(I74),IF(I74>=Engagement!$C$40,"Red",IF(I74>=Engagement!$C$41,"Amber","Green")),"") | P74: Decision and action registers | Q74: Secretariat; PMO
A75: D08 People, Workforce & Skills | D75: The size, mix, skills, capacity and management of the workforce needed to deliver the operating model.
A76: D08.01 | B76: People, Workforce & Skills | C76: Workforce planning | D76: Is there a strategic workforce plan linking future capability needs to the strategy? | E76: Three-to-five-year workforce plan with supply and demand analysis, critical roles and actions. | F76: 2 | H76: =Engagement!$C$39 -> 3 | I76: =IF(AND(ISNUMBER(G76),ISNUMBER(H76)),H76-G76,"") | J76: =IF(AND(ISNUMBER(I76),ISNUMBER(F76)),MAX(0,I76)*F76,"") | K76: =IF(ISNUMBER(I76),IF(I76>=Engagement!$C$40,"Red",IF(I76>=Engagement!$C$41,"Amber","Green")),"") | P76: Strategic workforce plan; workforce analytics | Q76: CHRO; Executive team
A77: D08.02 | B77: People, Workforce & Skills | C77: Workforce mix | D77: Is the workforce mix (permanent, fixed-term, contractor, outsourced, offshore) deliberate and cost-effective? | E77: Target workforce mix defined by capability; contractor reliance monitored and justified. | F77: 2 | H77: =Engagement!$C$39 -> 3 | I77: =IF(AND(ISNUMBER(G77),ISNUMBER(H77)),H77-G77,"") | J77: =IF(AND(ISNUMBER(I77),ISNUMBER(F77)),MAX(0,I77)*F77,"") | K77: =IF(ISNUMBER(I77),IF(I77>=Engagement!$C$40,"Red",IF(I77>=Engagement!$C$41,"Amber","Green")),"") | P77: Headcount / FTE by employment type; contractor spend | Q77: CHRO; CFO; Procurement
A78: D08.03 | B78: People, Workforce & Skills | C78: Capacity & demand | D78: Is workforce capacity matched to demand, with visibility of utilisation and backlogs? | E78: Demand forecasting and capacity planning used; resources rebalanced as demand changes. | F78: 2 | H78: =Engagement!$C$39 -> 3 | I78: =IF(AND(ISNUMBER(G78),ISNUMBER(H78)),H78-G78,"") | J78: =IF(AND(ISNUMBER(I78),ISNUMBER(F78)),MAX(0,I78)*F78,"") | K78: =IF(ISNUMBER(I78),IF(I78>=Engagement!$C$40,"Red",IF(I78>=Engagement!$C$41,"Amber","Green")),"") | P78: Capacity models; rosters; backlog data | Q78: Operations managers; Workforce planning
A79: D08.04 | B79: People, Workforce & Skills | C79: Skills & capability | D79: Are current skills known, and are gaps against future needs identified? | E79: Skills framework and inventory in place; gaps quantified and addressed through development plans. | F79: 2 | H79: =Engagement!$C$39 -> 3 | I79: =IF(AND(ISNUMBER(G79),ISNUMBER(H79)),H79-G79,"") | J79: =IF(AND(ISNUMBER(I79),ISNUMBER(F79)),MAX(0,I79)*F79,"") | K79: =IF(ISNUMBER(I79),IF(I79>=Engagement!$C$40,"Red",IF(I79>=Engagement!$C$41,"Amber","Green")),"") | P79: Skills framework; capability assessments; training records | Q79: CHRO; Learning & Development
A80: D08.05 | B80: People, Workforce & Skills | C80: Critical roles & succession | D80: Are critical roles and key-person dependencies identified, with succession plans? | E80: Critical roles identified, with ready-now successors and captured knowledge. | F80: 2 | H80: =Engagement!$C$39 -> 3 | I80: =IF(AND(ISNUMBER(G80),ISNUMBER(H80)),H80-G80,"") | J80: =IF(AND(ISNUMBER(I80),ISNUMBER(F80)),MAX(0,I80)*F80,"") | K80: =IF(ISNUMBER(I80),IF(I80>=Engagement!$C$40,"Red",IF(I80>=Engagement!$C$41,"Amber","Green")),"") | P80: Succession plans; key-person risk register | Q80: CHRO; Executive team
A81: D08.06 | B81: People, Workforce & Skills | C81: Attraction & retention | D81: Can the organisation attract and retain the talent it needs? | E81: Competitive employee value proposition; turnover, time-to-fill and regretted losses within targets. | F81: 2 | H81: =Engagement!$C$39 -> 3 | I81: =IF(AND(ISNUMBER(G81),ISNUMBER(H81)),H81-G81,"") | J81: =IF(AND(ISNUMBER(I81),ISNUMBER(F81)),MAX(0,I81)*F81,"") | K81: =IF(ISNUMBER(I81),IF(I81>=Engagement!$C$40,"Red",IF(I81>=Engagement!$C$41,"Amber","Green")),"") | P81: Turnover data; recruitment metrics; exit interview themes | Q81: CHRO; Talent acquisition
A82: D08.07 | B82: People, Workforce & Skills | C82: Performance & development | D82: Is there an effective performance and development framework linked to objectives and behaviours? | E82: Regular performance conversations; objectives cascaded from strategy; development plans in place. | F82: 2 | H82: =Engagement!$C$39 -> 3 | I82: =IF(AND(ISNUMBER(G82),ISNUMBER(H82)),H82-G82,"") | J82: =IF(AND(ISNUMBER(I82),ISNUMBER(F82)),MAX(0,I82)*F82,"") | K82: =IF(ISNUMBER(I82),IF(I82>=Engagement!$C$40,"Red",IF(I82>=Engagement!$C$41,"Amber","Green")),"") | P82: Performance framework; completion rates | Q82: CHRO; Managers
A83: D08.08 | B83: People, Workforce & Skills | C83: Reward & recognition | D83: Do reward and recognition mechanisms reinforce the desired outcomes and behaviours? | E83: Remuneration and incentives aligned to strategy, risk and behaviours; pay equity monitored. | F83: 2 | H83: =Engagement!$C$39 -> 3 | I83: =IF(AND(ISNUMBER(G83),ISNUMBER(H83)),H83-G83,"") | J83: =IF(AND(ISNUMBER(I83),ISNUMBER(F83)),MAX(0,I83)*F83,"") | K83: =IF(ISNUMBER(I83),IF(I83>=Engagement!$C$40,"Red",IF(I83>=Engagement!$C$41,"Amber","Green")),"") | P83: Remuneration framework; incentive plans; pay equity analysis | Q83: CHRO; Remuneration committee
A84: D08.09 | B84: People, Workforce & Skills | C84: WHS & wellbeing | D84: Are work health and safety risks, including psychosocial hazards, managed effectively? | E84: WHS management system in place; psychosocial risks identified and controlled in line with WHS regulations. | F84: 2 | H84: =Engagement!$C$39 -> 3 | I84: =IF(AND(ISNUMBER(G84),ISNUMBER(H84)),H84-G84,"") | J84: =IF(AND(ISNUMBER(I84),ISNUMBER(F84)),MAX(0,I84)*F84,"") | K84: =IF(ISNUMBER(I84),IF(I84>=Engagement!$C$40,"Red",IF(I84>=Engagement!$C$41,"Amber","Green")),"") | P84: WHS reports; psychosocial risk assessments; incident data | Q84: WHS lead; CHRO
A85: D08.10 | B85: People, Workforce & Skills | C85: Employee engagement | D85: Is employee engagement measured and acted upon? | E85: Regular engagement surveys with action plans and visible follow-through. | F85: 2 | H85: =Engagement!$C$39 -> 3 | I85: =IF(AND(ISNUMBER(G85),ISNUMBER(H85)),H85-G85,"") | J85: =IF(AND(ISNUMBER(I85),ISNUMBER(F85)),MAX(0,I85)*F85,"") | K85: =IF(ISNUMBER(I85),IF(I85>=Engagement!$C$40,"Red",IF(I85>=Engagement!$C$41,"Amber","Green")),"") | P85: Engagement survey results and action plans | Q85: CHRO; Managers
A86: D09 Culture, Leadership & Behaviours | D86: The shared values, leadership style and everyday behaviours that determine how work actually gets done.
A87: D09.01 | B87: Culture, Leadership & Behaviours | C87: Values & behaviours | D87: Are organisational values defined and translated into observable behaviours? | E87: Values embedded in recruitment, performance and recognition; behaviours are observable in practice. | F87: 2 | H87: =Engagement!$C$39 -> 3 | I87: =IF(AND(ISNUMBER(G87),ISNUMBER(H87)),H87-G87,"") | J87: =IF(AND(ISNUMBER(I87),ISNUMBER(F87)),MAX(0,I87)*F87,"") | K87: =IF(ISNUMBER(I87),IF(I87>=Engagement!$C$40,"Red",IF(I87>=Engagement!$C$41,"Amber","Green")),"") | P87: Values framework; behavioural competencies | Q87: CEO; CHRO; Staff
A88: D09.02 | B88: Culture, Leadership & Behaviours | C88: Culture diagnosis | D88: Has the current culture been diagnosed and compared with the culture needed to deliver the strategy? | E88: Culture diagnostic completed; priority culture shifts defined and tracked. | F88: 2 | H88: =Engagement!$C$39 -> 3 | I88: =IF(AND(ISNUMBER(G88),ISNUMBER(H88)),H88-G88,"") | J88: =IF(AND(ISNUMBER(I88),ISNUMBER(F88)),MAX(0,I88)*F88,"") | K88: =IF(ISNUMBER(I88),IF(I88>=Engagement!$C$40,"Red",IF(I88>=Engagement!$C$41,"Amber","Green")),"") | P88: Culture surveys; diagnostics | Q88: CHRO; Executive team
A89: D09.03 | B89: Culture, Leadership & Behaviours | C89: Leadership capability | D89: Do leaders have the capability to lead through change and deliver the strategy? | E89: Leadership framework, development programs and 360-degree feedback; leaders role-model desired behaviours. | F89: 2 | H89: =Engagement!$C$39 -> 3 | I89: =IF(AND(ISNUMBER(G89),ISNUMBER(H89)),H89-G89,"") | J89: =IF(AND(ISNUMBER(I89),ISNUMBER(F89)),MAX(0,I89)*F89,"") | K89: =IF(ISNUMBER(I89),IF(I89>=Engagement!$C$40,"Red",IF(I89>=Engagement!$C$41,"Amber","Green")),"") | P89: Leadership framework; 360 results; development programs | Q89: CEO; CHRO
A90: D09.04 | B90: Culture, Leadership & Behaviours | C90: Accountability | D90: Do people take ownership of outcomes, and are they held to account constructively? | E90: Clear expectations, consequences and recognition; issues raised and resolved without blame. | F90: 2 | H90: =Engagement!$C$39 -> 3 | I90: =IF(AND(ISNUMBER(G90),ISNUMBER(H90)),H90-G90,"") | J90: =IF(AND(ISNUMBER(I90),ISNUMBER(F90)),MAX(0,I90)*F90,"") | K90: =IF(ISNUMBER(I90),IF(I90>=Engagement!$C$40,"Red",IF(I90>=Engagement!$C$41,"Amber","Green")),"") | P90: Engagement survey; performance data; interviews | Q90: Managers; Staff
A91: D09.05 | B91: Culture, Leadership & Behaviours | C91: Collaboration | D91: Is there effective collaboration across teams and functions, or are silos evident? | E91: Cross-functional collaboration is the norm, with shared goals across units and little siloed behaviour. | F91: 2 | H91: =Engagement!$C$39 -> 3 | I91: =IF(AND(ISNUMBER(G91),ISNUMBER(H91)),H91-G91,"") | J91: =IF(AND(ISNUMBER(I91),ISNUMBER(F91)),MAX(0,I91)*F91,"") | K91: =IF(ISNUMBER(I91),IF(I91>=Engagement!$C$40,"Red",IF(I91>=Engagement!$C$41,"Amber","Green")),"") | P91: Engagement survey; organisational network analysis; interviews | Q91: Managers; Staff
A92: D09.06 | B92: Culture, Leadership & Behaviours | C92: Customer centricity | D92: Do staff make decisions with the customer or beneficiary outcome in mind? | E92: Customer outcomes feature in everyday decision making and in measures. | F92: 2 | H92: =Engagement!$C$39 -> 3 | I92: =IF(AND(ISNUMBER(G92),ISNUMBER(H92)),H92-G92,"") | J92: =IF(AND(ISNUMBER(I92),ISNUMBER(F92)),MAX(0,I92)*F92,"") | K92: =IF(ISNUMBER(I92),IF(I92>=Engagement!$C$40,"Red",IF(I92>=Engagement!$C$41,"Amber","Green")),"") | P92: Interviews; CX metrics; decision examples | Q92: Frontline staff; Managers
A93: D09.07 | B93: Culture, Leadership & Behaviours | C93: Psychological safety | D93: Do staff feel safe to raise concerns, challenge ideas and report issues? | E93: High psychological safety scores; effective speak-up and whistleblower mechanisms. | F93: 2 | H93: =Engagement!$C$39 -> 3 | I93: =IF(AND(ISNUMBER(G93),ISNUMBER(H93)),H93-G93,"") | J93: =IF(AND(ISNUMBER(I93),ISNUMBER(F93)),MAX(0,I93)*F93,"") | K93: =IF(ISNUMBER(I93),IF(I93>=Engagement!$C$40,"Red",IF(I93>=Engagement!$C$41,"Amber","Green")),"") | P93: Engagement survey; whistleblower reports | Q93: CHRO; Staff; Risk
A94: D09.08 | B94: Culture, Leadership & Behaviours | C94: Risk culture | D94: Is there a healthy risk culture in which risks are identified, escalated and managed openly? | E94: Risk culture assessed; risks and incidents reported promptly; lessons learned applied. | F94: 2 | H94: =Engagement!$C$39 -> 3 | I94: =IF(AND(ISNUMBER(G94),ISNUMBER(H94)),H94-G94,"") | J94: =IF(AND(ISNUMBER(I94),ISNUMBER(F94)),MAX(0,I94)*F94,"") | K94: =IF(ISNUMBER(I94),IF(I94>=Engagement!$C$40,"Red",IF(I94>=Engagement!$C$41,"Amber","Green")),"") | P94: Risk culture survey; incident reporting trends | Q94: CRO; Managers
A95: D09.09 | B95: Culture, Leadership & Behaviours | C95: Change readiness | D95: How ready and able is the organisation to adopt change? | E95: Change fatigue understood, change capacity managed and a history of successful adoption. | F95: 2 | H95: =Engagement!$C$39 -> 3 | I95: =IF(AND(ISNUMBER(G95),ISNUMBER(H95)),H95-G95,"") | J95: =IF(AND(ISNUMBER(I95),ISNUMBER(F95)),MAX(0,I95)*F95,"") | K95: =IF(ISNUMBER(I95),IF(I95>=Engagement!$C$40,"Red",IF(I95>=Engagement!$C$41,"Amber","Green")),"") | P95: Change readiness assessments; post-implementation reviews | Q95: Change lead; Managers
A96: D10 Performance Management & Planning | D96: How the organisation plans, sets targets, measures performance and uses information to steer.
A97: D10.01 | B97: Performance Management & Planning | C97: Planning cycle | D97: Is there an integrated planning cycle linking strategic, business, workforce and financial planning? | E97: Annual integrated planning calendar with clear inputs, outputs and decision points. | F97: 2 | H97: =Engagement!$C$39 -> 3 | I97: =IF(AND(ISNUMBER(G97),ISNUMBER(H97)),H97-G97,"") | J97: =IF(AND(ISNUMBER(I97),ISNUMBER(F97)),MAX(0,I97)*F97,"") | K97: =IF(ISNUMBER(I97),IF(I97>=Engagement!$C$40,"Red",IF(I97>=Engagement!$C$41,"Amber","Green")),"") | P97: Planning calendar; business plans; budget process | Q97: CFO; Strategy; PMO
A98: D10.02 | B98: Performance Management & Planning | C98: KPI framework | D98: Is there a balanced set of KPIs (financial, customer, process, people, risk) aligned to the strategy? | E98: Balanced scorecard or equivalent with defined measures, targets, owners and data sources. | F98: 2 | H98: =Engagement!$C$39 -> 3 | I98: =IF(AND(ISNUMBER(G98),ISNUMBER(H98)),H98-G98,"") | J98: =IF(AND(ISNUMBER(I98),ISNUMBER(F98)),MAX(0,I98)*F98,"") | K98: =IF(ISNUMBER(I98),IF(I98>=Engagement!$C$40,"Red",IF(I98>=Engagement!$C$41,"Amber","Green")),"") | P98: KPI framework; scorecards; metric definitions | Q98: Executive team; Performance team
A99: D10.03 | B99: Performance Management & Planning | C99: Cascade & line of sight | D99: Do KPIs and objectives cascade from enterprise to business unit, team and individual levels? | E99: Clear line of sight from enterprise goals to team and individual objectives (e.g. OKRs). | F99: 2 | H99: =Engagement!$C$39 -> 3 | I99: =IF(AND(ISNUMBER(G99),ISNUMBER(H99)),H99-G99,"") | J99: =IF(AND(ISNUMBER(I99),ISNUMBER(F99)),MAX(0,I99)*F99,"") | K99: =IF(ISNUMBER(I99),IF(I99>=Engagement!$C$40,"Red",IF(I99>=Engagement!$C$41,"Amber","Green")),"") | P99: Cascaded scorecards; OKRs; performance agreements | Q99: Managers; CHRO
A100: D10.04 | B100: Performance Management & Planning | C100: Management reporting | D100: Is management reporting timely, accurate, insightful and trusted? | E100: Automated, single-source reporting focused on insight and exceptions, with little manual effort. | F100: 2 | H100: =Engagement!$C$39 -> 3 | I100: =IF(AND(ISNUMBER(G100),ISNUMBER(H100)),H100-G100,"") | J100: =IF(AND(ISNUMBER(I100),ISNUMBER(F100)),MAX(0,I100)*F100,"") | K100: =IF(ISNUMBER(I100),IF(I100>=Engagement!$C$40,"Red",IF(I100>=Engagement!$C$41,"Amber","Green")),"") | P100: Management reports; report inventory; production effort | Q100: CFO; Data & Analytics
A101: D10.05 | B101: Performance Management & Planning | C101: Performance forums | D101: Are there regular forums where performance is reviewed and actions agreed? | E101: A rhythm of performance reviews at each level, with actions tracked to closure. | F101: 2 | H101: =Engagement!$C$39 -> 3 | I101: =IF(AND(ISNUMBER(G101),ISNUMBER(H101)),H101-G101,"") | J101: =IF(AND(ISNUMBER(I101),ISNUMBER(F101)),MAX(0,I101)*F101,"") | K101: =IF(ISNUMBER(I101),IF(I101>=Engagement!$C$40,"Red",IF(I101>=Engagement!$C$41,"Amber","Green")),"") | P101: Performance review agendas; action logs | Q101: Executive team; Managers
...

Sheet Capabilities
A1: Business Capability Assessment
A2: Generic Level 1 / Level 2 capability model — rename, add or remove capabilities to reflect the client. Priority score = importance weight (High 3, Medium 2, Low 1) × maturity shortfall.
A3: Legend: yellow cells = inputs | grey cells = calculated (do not overwrite) | green text = linked from another tab | grey italic row = example (overwrite or delete)
A5: ID | B5: Tier | C5: Level 1 capability | D5: Level 2 capability | E5: Description | F5: Strategic importance | G5: Differentiation | H5: Current maturity (1–5) | I5: Target maturity (1–5) | J5: Gap | K5: Priority score | L5: Capability owner | M5: Key supporting systems | N5: Sourcing model | O5: Observations
A6: C01 | B6: Strategic | C6: Strategy & Planning | D6: Strategy development | E6: Set direction, strategic objectives and choices. | J6: =IF(AND(ISNUMBER(H6),ISNUMBER(I6)),I6-H6,"") | K6: =IFERROR(IF(AND(ISNUMBER(J6),F6<>""),MAX(0,J6)*INDEX(Lists!$AJ$2:$AJ$4,MATCH(F6,Lists!$AI$2:$AI$4,0)),""),"")
A7: C02 | B7: Strategic | C7: Strategy & Planning | D7: Business planning | E7: Translate strategy into business unit plans and targets. | J7: =IF(AND(ISNUMBER(H7),ISNUMBER(I7)),I7-H7,"") | K7: =IFERROR(IF(AND(ISNUMBER(J7),F7<>""),MAX(0,J7)*INDEX(Lists!$AJ$2:$AJ$4,MATCH(F7,Lists!$AI$2:$AI$4,0)),""),"")
A8: C03 | B8: Strategic | C8: Strategy & Planning | D8: Performance management | E8: Measure, report and steer performance against plans. | J8: =IF(AND(ISNUMBER(H8),ISNUMBER(I8)),I8-H8,"") | K8: =IFERROR(IF(AND(ISNUMBER(J8),F8<>""),MAX(0,J8)*INDEX(Lists!$AJ$2:$AJ$4,MATCH(F8,Lists!$AI$2:$AI$4,0)),""),"")
A9: C04 | B9: Strategic | C9: Strategy & Planning | D9: Enterprise architecture & design | E9: Design and govern the business and technology architecture. | J9: =IF(AND(ISNUMBER(H9),ISNUMBER(I9)),I9-H9,"") | K9: =IFERROR(IF(AND(ISNUMBER(J9),F9<>""),MAX(0,J9)*INDEX(Lists!$AJ$2:$AJ$4,MATCH(F9,Lists!$AI$2:$AI$4,0)),""),"")
A10: C05 | B10: Strategic | C10: Governance & Assurance | D10: Corporate governance | E10: Operate the board, committees and delegations. | J10: =IF(AND(ISNUMBER(H10),ISNUMBER(I10)),I10-H10,"") | K10: =IFERROR(IF(AND(ISNUMBER(J10),F10<>""),MAX(0,J10)*INDEX(Lists!$AJ$2:$AJ$4,MATCH(F10,Lists!$AI$2:$AI$4,0)),""),"")
A11: C06 | B11: Strategic | C11: Governance & Assurance | D11: Enterprise risk management | E11: Identify, assess and treat risks within appetite. | J11: =IF(AND(ISNUMBER(H11),ISNUMBER(I11)),I11-H11,"") | K11: =IFERROR(IF(AND(ISNUMBER(J11),F11<>""),MAX(0,J11)*INDEX(Lists!$AJ$2:$AJ$4,MATCH(F11,Lists!$AI$2:$AI$4,0)),""),"")
A12: C07 | B12: Strategic | C12: Governance & Assurance | D12: Compliance management | E12: Identify obligations and monitor compliance. | J12: =IF(AND(ISNUMBER(H12),ISNUMBER(I12)),I12-H12,"") | K12: =IFERROR(IF(AND(ISNUMBER(J12),F12<>""),MAX(0,J12)*INDEX(Lists!$AJ$2:$AJ$4,MATCH(F12,Lists!$AI$2:$AI$4,0)),""),"")
A13: C08 | B13: Strategic | C13: Governance & Assurance | D13: Internal audit & assurance | E13: Provide independent assurance over controls. | J13: =IF(AND(ISNUMBER(H13),ISNUMBER(I13)),I13-H13,"") | K13: =IFERROR(IF(AND(ISNUMBER(J13),F13<>""),MAX(0,J13)*INDEX(Lists!$AJ$2:$AJ$4,MATCH(F13,Lists!$AI$2:$AI$4,0)),""),"")
A14: C09 | B14: Strategic | C14: Portfolio & Change | D14: Portfolio management | E14: Prioritise, fund and oversee the change portfolio. | J14: =IF(AND(ISNUMBER(H14),ISNUMBER(I14)),I14-H14,"") | K14: =IFERROR(IF(AND(ISNUMBER(J14),F14<>""),MAX(0,J14)*INDEX(Lists!$AJ$2:$AJ$4,MATCH(F14,Lists!$AI$2:$AI$4,0)),""),"")
A15: C10 | B15: Strategic | C15: Portfolio & Change | D15: Program & project delivery | E15: Deliver change initiatives to scope, time and budget. | J15: =IF(AND(ISNUMBER(H15),ISNUMBER(I15)),I15-H15,"") | K15: =IFERROR(IF(AND(ISNUMBER(J15),F15<>""),MAX(0,J15)*INDEX(Lists!$AJ$2:$AJ$4,MATCH(F15,Lists!$AI$2:$AI$4,0)),""),"")
A16: C11 | B16: Strategic | C16: Portfolio & Change | D16: Business analysis & design | E16: Define needs, requirements and solution designs. | J16: =IF(AND(ISNUMBER(H16),ISNUMBER(I16)),I16-H16,"") | K16: =IFERROR(IF(AND(ISNUMBER(J16),F16<>""),MAX(0,J16)*INDEX(Lists!$AJ$2:$AJ$4,MATCH(F16,Lists!$AI$2:$AI$4,0)),""),"")
A17: C12 | B17: Strategic | C17: Portfolio & Change | D17: Change management | E17: Drive adoption and embed change. | J17: =IF(AND(ISNUMBER(H17),ISNUMBER(I17)),I17-H17,"") | K17: =IFERROR(IF(AND(ISNUMBER(J17),F17<>""),MAX(0,J17)*INDEX(Lists!$AJ$2:$AJ$4,MATCH(F17,Lists!$AI$2:$AI$4,0)),""),"")
... A61: C56 | B61: Enabling | C61: Legal & Corporate Services | D61: Business continuity management | E61: Plan for and respond to disruption. | J61: =IF(AND(ISNUMBER(H61),ISNUMBER(I61)),I61-H61,"") | K61: =IFERROR(IF(AND(ISNUMBER(J61),F61<>""),MAX(0,J61)*INDEX(Lists!$AJ$2:$AJ$4,MATCH(F61,Lists!$AI$2:$AI$4,0)),""),"")
A62: C57 | J62: =IF(AND(ISNUMBER(H62),ISNUMBER(I62)),I62-H62,"") | K62: =IFERROR(IF(AND(ISNUMBER(J62),F62<>""),MAX(0,J62)*INDEX(Lists!$AJ$2:$AJ$4,MATCH(F62,Lists!$AI$2:$AI$4,0)),""),"")
A63: C58 | J63: =IF(AND(ISNUMBER(H63),ISNUMBER(I63)),I63-H63,"") | K63: =IFERROR(IF(AND(ISNUMBER(J63),F63<>""),MAX(0,J63)*INDEX(Lists!$AJ$2:$AJ$4,MATCH(F63,Lists!$AI$2:$AI$4,0)),""),"")
A64: C59 | J64: =IF(AND(ISNUMBER(H64),ISNUMBER(I64)),I64-H64,"") | K64: =IFERROR(IF(AND(ISNUMBER(J64),F64<>""),MAX(0,J64)*INDEX(Lists!$AJ$2:$AJ$4,MATCH(F64,Lists!$AI$2:$AI$4,0)),""),"")
A65: C60 | J65: =IF(AND(ISNUMBER(H65),ISNUMBER(I65)),I65-H65,"") | K65: =IFERROR(IF(AND(ISNUMBER(J65),F65<>""),MAX(0,J65)*INDEX(Lists!$AJ$2:$AJ$4,MATCH(F65,Lists!$AI$2:$AI$4,0)),""),"")
A66: C61 | J66: =IF(AND(ISNUMBER(H66),ISNUMBER(I66)),I66-H66,"") | K66: =IFERROR(IF(AND(ISNUMBER(J66),F66<>""),MAX(0,J66)*INDEX(Lists!$AJ$2:$AJ$4,MATCH(F66,Lists!$AI$2:$AI$4,0)),""),"")
A67: C62 | J67: =IF(AND(ISNUMBER(H67),ISNUMBER(I67)),I67-H67,"") | K67: =IFERROR(IF(AND(ISNUMBER(J67),F67<>""),MAX(0,J67)*INDEX(Lists!$AJ$2:$AJ$4,MATCH(F67,Lists!$AI$2:$AI$4,0)),""),"")
A68: C63 | J68: =IF(AND(ISNUMBER(H68),ISNUMBER(I68)),I68-H68,"") | K68: =IFERROR(IF(AND(ISNUMBER(J68),F68<>""),MAX(0,J68)*INDEX(Lists!$AJ$2:$AJ$4,MATCH(F68,Lists!$AI$2:$AI$4,0)),""),"")
A69: C64 | J69: =IF(AND(ISNUMBER(H69),ISNUMBER(I69)),I69-H69,"") | K69: =IFERROR(IF(AND(ISNUMBER(J69),F69<>""),MAX(0,J69)*INDEX(Lists!$AJ$2:$AJ$4,MATCH(F69,Lists!$AI$2:$AI$4,0)),""),"")
A70: C65 | J70: =IF(AND(ISNUMBER(H70),ISNUMBER(I70)),I70-H70,"") | K70: =IFERROR(IF(AND(ISNUMBER(J70),F70<>""),MAX(0,J70)*INDEX(Lists!$AJ$2:$AJ$4,MATCH(F70,Lists!$AI$2:$AI$4,0)),""),"")
A71: C66 | J71: =IF(AND(ISNUMBER(H71),ISNUMBER(I71)),I71-H71,"") | K71: =IFERROR(IF(AND(ISNUMBER(J71),F71<>""),MAX(0,J71)*INDEX(Lists!$AJ$2:$AJ$4,MATCH(F71,Lists!$AI$2:$AI$4,0)),""),"")
A72: C67 | J72: =IF(AND(ISNUMBER(H72),ISNUMBER(I72)),I72-H72,"") | K72: =IFERROR(IF(AND(ISNUMBER(J72),F72<>""),MAX(0,J72)*INDEX(Lists!$AJ$2:$AJ$4,MATCH(F72,Lists!$AI$2:$AI$4,0)),""),"")
A73: C68 | J73: =IF(AND(ISNUMBER(H73),ISNUMBER(I73)),I73-H73,"") | K73: =IFERROR(IF(AND(ISNUMBER(J73),F73<>""),MAX(0,J73)*INDEX(Lists!$AJ$2:$AJ$4,MATCH(F73,Lists!$AI$2:$AI$4,0)),""),"")
... A76: C71 | J76: =IF(AND(ISNUMBER(H76),ISNUMBER(I76)),I76-H76,"") | K76: =IFERROR(IF(AND(ISNUMBER(J76),F76<>""),MAX(0,J76)*INDEX(Lists!$AJ$2:$AJ$4,MATCH(F76,Lists!$AI$2:$AI$4,0)),""),"")

Sheet Processes
A1: Value Stream & Process Inventory
A2: Generic end-to-end value streams and Level 1 processes. Add Level 2 sub-processes as rows and record performance data where available.
A3: Legend: yellow cells = inputs | grey cells = calculated (do not overwrite) | green text = linked from another tab | grey italic row = example (overwrite or delete)
A5: ID | B5: Value stream | C5: Level 1 process | D5: Level 2 process / sub-process | E5: Process owner | F5: Business units involved | G5: Documented? | H5: Standardised across units? | I5: Automation level | J5: Key systems | K5: Monthly volume | L5: Average cycle time (days) | M5: FTE effort | N5: FTE per 1,000 transactions | O5: Hand-offs (#) | P5: Pain points | Q5: Maturity (1–5) | R5: Improvement opportunity | S5: Priority
A6: P01 | B6: Strategy-to-Execution | C6: Develop and refresh strategy | N6: =IF(AND(ISNUMBER(K6),ISNUMBER(M6),K6>0),M6/K6*1000,"")
A7: P02 | B7: Strategy-to-Execution | C7: Plan and budget | N7: =IF(AND(ISNUMBER(K7),ISNUMBER(M7),K7>0),M7/K7*1000,"")
A8: P03 | B8: Strategy-to-Execution | C8: Manage the change portfolio | N8: =IF(AND(ISNUMBER(K8),ISNUMBER(M8),K8>0),M8/K8*1000,"")
A9: P04 | B9: Strategy-to-Execution | C9: Monitor and report performance | N9: =IF(AND(ISNUMBER(K9),ISNUMBER(M9),K9>0),M9/K9*1000,"")
A10: P05 | B10: Market-to-Customer | C10: Understand customer needs | N10: =IF(AND(ISNUMBER(K10),ISNUMBER(M10),K10>0),M10/K10*1000,"")
A11: P06 | B11: Market-to-Customer | C11: Market and promote services | N11: =IF(AND(ISNUMBER(K11),ISNUMBER(M11),K11>0),M11/K11*1000,"")
A12: P07 | B12: Market-to-Customer | C12: Acquire and onboard customers | N12: =IF(AND(ISNUMBER(K12),ISNUMBER(M12),K12>0),M12/K12*1000,"")
A13: P08 | B13: Request-to-Fulfil | C13: Receive and triage requests | N13: =IF(AND(ISNUMBER(K13),ISNUMBER(M13),K13>0),M13/K13*1000,"")
A14: P09 | B14: Request-to-Fulfil | C14: Assess eligibility and requirements | N14: =IF(AND(ISNUMBER(K14),ISNUMBER(M14),K14>0),M14/K14*1000,"")
A15: P10 | B15: Request-to-Fulfil | C15: Deliver the product or service | N15: =IF(AND(ISNUMBER(K15),ISNUMBER(M15),K15>0),M15/K15*1000,"")
A16: P11 | B16: Request-to-Fulfil | C16: Confirm completion and close | N16: =IF(AND(ISNUMBER(K16),ISNUMBER(M16),K16>0),M16/K16*1000,"")
A17: P12 | B17: Issue-to-Resolution | C17: Receive enquiries and complaints | N17: =IF(AND(ISNUMBER(K17),ISNUMBER(M17),K17>0),M17/K17*1000,"")
... A45: P40 | B45: Request-to-Service (IT) | C45: Resolve incidents and problems | N45: =IF(AND(ISNUMBER(K45),ISNUMBER(M45),K45>0),M45/K45*1000,"")
A46: P41 | N46: =IF(AND(ISNUMBER(K46),ISNUMBER(M46),K46>0),M46/K46*1000,"")
A47: P42 | N47: =IF(AND(ISNUMBER(K47),ISNUMBER(M47),K47>0),M47/K47*1000,"")
A48: P43 | N48: =IF(AND(ISNUMBER(K48),ISNUMBER(M48),K48>0),M48/K48*1000,"")
A49: P44 | N49: =IF(AND(ISNUMBER(K49),ISNUMBER(M49),K49>0),M49/K49*1000,"")
A50: P45 | N50: =IF(AND(ISNUMBER(K50),ISNUMBER(M50),K50>0),M50/K50*1000,"")
A51: P46 | N51: =IF(AND(ISNUMBER(K51),ISNUMBER(M51),K51>0),M51/K51*1000,"")
A52: P47 | N52: =IF(AND(ISNUMBER(K52),ISNUMBER(M52),K52>0),M52/K52*1000,"")
A53: P48 | N53: =IF(AND(ISNUMBER(K53),ISNUMBER(M53),K53>0),M53/K53*1000,"")
A54: P49 | N54: =IF(AND(ISNUMBER(K54),ISNUMBER(M54),K54>0),M54/K54*1000,"")
A55: P50 | N55: =IF(AND(ISNUMBER(K55),ISNUMBER(M55),K55>0),M55/K55*1000,"")
A56: P51 | N56: =IF(AND(ISNUMBER(K56),ISNUMBER(M56),K56>0),M56/K56*1000,"")
A57: P52 | N57: =IF(AND(ISNUMBER(K57),ISNUMBER(M57),K57>0),M57/K57*1000,"")
... A65: P60 | N65: =IF(AND(ISNUMBER(K65),ISNUMBER(M65),K65>0),M65/K65*1000,"")

Sheet Org Structure
A1: Organisation Structure: Spans, Layers & Workforce Mix
A2: One row per business unit or function, using the HR system extract. Average span is approximated as (employee + contractor FTE − 1) ÷ people managers; replace with direct-report counts where available. Span benchmarks are on the Lists tab.
A3: Legend: yellow cells = inputs | grey cells = calculated (do not overwrite) | green text = linked from another tab | grey italic row = example (overwrite or delete)
A5: ID | B5: Business unit / function | C5: Head of unit | D5: Nature of work | E5: Permanent FTE | F5: Fixed-term FTE | G5: Contractor FTE | H5: Outsourced FTE | I5: Total FTE | J5: Contractor & outsourced % | K5: People managers (#) | L5: Management layers (CEO = 1) | M5: Average span of control | N5: Target span | O5: Span assessment | P5: Layers assessment | Q5: Annual employee cost ($) | R5: Cost per employee FTE ($) | S5: Vacancies (#) | T5: Observations
A6: Example | B6: Customer Operations | C6: GM Customer Operations | D6: Standardised / operational | E6: 182 | F6: 12 | G6: 9 | H6: 25 | I6: =IF(COUNT(E6:H6)=0,"",SUM(E6:H6)) -> 228 | J6: =IF(AND(ISNUMBER(I6),I6>0),(G6+H6)/I6,"") -> 0.14912281 | K6: 14 | L6: 5 | M6: =IF(AND(ISNUMBER(K6),K6>0),(E6+F6+G6-1)/K6,"") -> 14.428571 | N6: =IFERROR(INDEX(Lists!$AF$2:$AF$5,MATCH(D6,Lists!$AE$2:$AE$5,0))&"–"&INDEX(Lists!$AG$2:$AG$5,MATCH(D6,Lists!$AE$2:$AE$5,0)),"") -> 11–15 | O6: =IFERROR(IF(OR(M6="",D6=""),"",IF(M6<INDEX(Lists!$AF$2:$AF$5,MATCH(D6,Lists!$AE$2:$AE$5,0)),"Below range",IF(M6>INDEX(Lists!$AG$2:$AG$5,MATCH(D6,Lists!$AE$2:$AE$5,0)),"Above range","Within range"))),"") -> Within range | P6: =IF(ISNUMBER(L6),IF(L6>Engagement!$C$43,"Exceeds maximum","Within maximum"),"") -> Within maximum | Q6: 21450000 | R6: =IF(AND(ISNUMBER(Q6),(E6+F6)>0),Q6/(E6+F6),"") -> 110567.01 | S6: 8 | T6: Two team leaders manage 25+ staff each.
A7: O01 | I7: =IF(COUNT(E7:H7)=0,"",SUM(E7:H7)) | J7: =IF(AND(ISNUMBER(I7),I7>0),(G7+H7)/I7,"") | M7: =IF(AND(ISNUMBER(K7),K7>0),(E7+F7+G7-1)/K7,"") | N7: =IFERROR(INDEX(Lists!$AF$2:$AF$5,MATCH(D7,Lists!$AE$2:$AE$5,0))&"–"&INDEX(Lists!$AG$2:$AG$5,MATCH(D7,Lists!$AE$2:$AE$5,0)),"") | O7: =IFERROR(IF(OR(M7="",D7=""),"",IF(M7<INDEX(Lists!$AF$2:$AF$5,MATCH(D7,Lists!$AE$2:$AE$5,0)),"Below range",IF(M7>INDEX(Lists!$AG$2:$AG$5,MATCH(D7,Lists!$AE$2:$AE$5,0)),"Above range","Within range"))),"") | P7: =IF(ISNUMBER(L7),IF(L7>Engagement!$C$43,"Exceeds maximum","Within maximum"),"") | R7: =IF(AND(ISNUMBER(Q7),(E7+F7)>0),Q7/(E7+F7),"")
A8: O02 | I8: =IF(COUNT(E8:H8)=0,"",SUM(E8:H8)) | J8: =IF(AND(ISNUMBER(I8),I8>0),(G8+H8)/I8,"") | M8: =IF(AND(ISNUMBER(K8),K8>0),(E8+F8+G8-1)/K8,"") | N8: =IFERROR(INDEX(Lists!$AF$2:$AF$5,MATCH(D8,Lists!$AE$2:$AE$5,0))&"–"&INDEX(Lists!$AG$2:$AG$5,MATCH(D8,Lists!$AE$2:$AE$5,0)),"") | O8: =IFERROR(IF(OR(M8="",D8=""),"",IF(M8<INDEX(Lists!$AF$2:$AF$5,MATCH(D8,Lists!$AE$2:$AE$5,0)),"Below range",IF(M8>INDEX(Lists!$AG$2:$AG$5,MATCH(D8,Lists!$AE$2:$AE$5,0)),"Above range","Within range"))),"") | P8: =IF(ISNUMBER(L8),IF(L8>Engagement!$C$43,"Exceeds maximum","Within maximum"),"") | R8: =IF(AND(ISNUMBER(Q8),(E8+F8)>0),Q8/(E8+F8),"")
A9: O03 | I9: =IF(COUNT(E9:H9)=0,"",SUM(E9:H9)) | J9: =IF(AND(ISNUMBER(I9),I9>0),(G9+H9)/I9,"") | M9: =IF(AND(ISNUMBER(K9),K9>0),(E9+F9+G9-1)/K9,"") | N9: =IFERROR(INDEX(Lists!$AF$2:$AF$5,MATCH(D9,Lists!$AE$2:$AE$5,0))&"–"&INDEX(Lists!$AG$2:$AG$5,MATCH(D9,Lists!$AE$2:$AE$5,0)),"") | O9: =IFERROR(IF(OR(M9="",D9=""),"",IF(M9<INDEX(Lists!$AF$2:$AF$5,MATCH(D9,Lists!$AE$2:$AE$5,0)),"Below range",IF(M9>INDEX(Lists!$AG$2:$AG$5,MATCH(D9,Lists!$AE$2:$AE$5,0)),"Above range","Within range"))),"") | P9: =IF(ISNUMBER(L9),IF(L9>Engagement!$C$43,"Exceeds maximum","Within maximum"),"") | R9: =IF(AND(ISNUMBER(Q9),(E9+F9)>0),Q9/(E9+F9),"")
A10: O04 | I10: =IF(COUNT(E10:H10)=0,"",SUM(E10:H10)) | J10: =IF(AND(ISNUMBER(I10),I10>0),(G10+H10)/I10,"") | M10: =IF(AND(ISNUMBER(K10),K10>0),(E10+F10+G10-1)/K10,"") | N10: =IFERROR(INDEX(Lists!$AF$2:$AF$5,MATCH(D10,Lists!$AE$2:$AE$5,0))&"–"&INDEX(Lists!$AG$2:$AG$5,MATCH(D10,Lists!$AE$2:$AE$5,0)),"") | O10: =IFERROR(IF(OR(M10="",D10=""),"",IF(M10<INDEX(Lists!$AF$2:$AF$5,MATCH(D10,Lists!$AE$2:$AE$5,0)),"Below range",IF(M10>INDEX(Lists!$AG$2:$AG$5,MATCH(D10,Lists!$AE$2:$AE$5,0)),"Above range","Within range"))),"") | P10: =IF(ISNUMBER(L10),IF(L10>Engagement!$C$43,"Exceeds maximum","Within maximum"),"") | R10: =IF(AND(ISNUMBER(Q10),(E10+F10)>0),Q10/(E10+F10),"")
A11: O05 | I11: =IF(COUNT(E11:H11)=0,"",SUM(E11:H11)) | J11: =IF(AND(ISNUMBER(I11),I11>0),(G11+H11)/I11,"") | M11: =IF(AND(ISNUMBER(K11),K11>0),(E11+F11+G11-1)/K11,"") | N11: =IFERROR(INDEX(Lists!$AF$2:$AF$5,MATCH(D11,Lists!$AE$2:$AE$5,0))&"–"&INDEX(Lists!$AG$2:$AG$5,MATCH(D11,Lists!$AE$2:$AE$5,0)),"") | O11: =IFERROR(IF(OR(M11="",D11=""),"",IF(M11<INDEX(Lists!$AF$2:$AF$5,MATCH(D11,Lists!$AE$2:$AE$5,0)),"Below range",IF(M11>INDEX(Lists!$AG$2:$AG$5,MATCH(D11,Lists!$AE$2:$AE$5,0)),"Above range","Within range"))),"") | P11: =IF(ISNUMBER(L11),IF(L11>Engagement!$C$43,"Exceeds maximum","Within maximum"),"") | R11: =IF(AND(ISNUMBER(Q11),(E11+F11)>0),Q11/(E11+F11),"")
A12: O06 | I12: =IF(COUNT(E12:H12)=0,"",SUM(E12:H12)) | J12: =IF(AND(ISNUMBER(I12),I12>0),(G12+H12)/I12,"") | M12: =IF(AND(ISNUMBER(K12),K12>0),(E12+F12+G12-1)/K12,"") | N12: =IFERROR(INDEX(Lists!$AF$2:$AF$5,MATCH(D12,Lists!$AE$2:$AE$5,0))&"–"&INDEX(Lists!$AG$2:$AG$5,MATCH(D12,Lists!$AE$2:$AE$5,0)),"") | O12: =IFERROR(IF(OR(M12="",D12=""),"",IF(M12<INDEX(Lists!$AF$2:$AF$5,MATCH(D12,Lists!$AE$2:$AE$5,0)),"Below range",IF(M12>INDEX(Lists!$AG$2:$AG$5,MATCH(D12,Lists!$AE$2:$AE$5,0)),"Above range","Within range"))),"") | P12: =IF(ISNUMBER(L12),IF(L12>Engagement!$C$43,"Exceeds maximum","Within maximum"),"") | R12: =IF(AND(ISNUMBER(Q12),(E12+F12)>0),Q12/(E12+F12),"")
A13: O07 | I13: =IF(COUNT(E13:H13)=0,"",SUM(E13:H13)) | J13: =IF(AND(ISNUMBER(I13),I13>0),(G13+H13)/I13,"") | M13: =IF(AND(ISNUMBER(K13),K13>0),(E13+F13+G13-1)/K13,"") | N13: =IFERROR(INDEX(Lists!$AF$2:$AF$5,MATCH(D13,Lists!$AE$2:$AE$5,0))&"–"&INDEX(Lists!$AG$2:$AG$5,MATCH(D13,Lists!$AE$2:$AE$5,0)),"") | O13: =IFERROR(IF(OR(M13="",D13=""),"",IF(M13<INDEX(Lists!$AF$2:$AF$5,MATCH(D13,Lists!$AE$2:$AE$5,0)),"Below range",IF(M13>INDEX(Lists!$AG$2:$AG$5,MATCH(D13,Lists!$AE$2:$AE$5,0)),"Above range","Within range"))),"") | P13: =IF(ISNUMBER(L13),IF(L13>Engagement!$C$43,"Exceeds maximum","Within maximum"),"") | R13: =IF(AND(ISNUMBER(Q13),(E13+F13)>0),Q13/(E13+F13),"")
A14: O08 | I14: =IF(COUNT(E14:H14)=0,"",SUM(E14:H14)) | J14: =IF(AND(ISNUMBER(I14),I14>0),(G14+H14)/I14,"") | M14: =IF(AND(ISNUMBER(K14),K14>0),(E14+F14+G14-1)/K14,"") | N14: =IFERROR(INDEX(Lists!$AF$2:$AF$5,MATCH(D14,Lists!$AE$2:$AE$5,0))&"–"&INDEX(Lists!$AG$2:$AG$5,MATCH(D14,Lists!$AE$2:$AE$5,0)),"") | O14: =IFERROR(IF(OR(M14="",D14=""),"",IF(M14<INDEX(Lists!$AF$2:$AF$5,MATCH(D14,Lists!$AE$2:$AE$5,0)),"Below range",IF(M14>INDEX(Lists!$AG$2:$AG$5,MATCH(D14,Lists!$AE$2:$AE$5,0)),"Above range","Within range"))),"") | P14: =IF(ISNUMBER(L14),IF(L14>Engagement!$C$43,"Exceeds maximum","Within maximum"),"") | R14: =IF(AND(ISNUMBER(Q14),(E14+F14)>0),Q14/(E14+F14),"")
A15: O09 | I15: =IF(COUNT(E15:H15)=0,"",SUM(E15:H15)) | J15: =IF(AND(ISNUMBER(I15),I15>0),(G15+H15)/I15,"") | M15: =IF(AND(ISNUMBER(K15),K15>0),(E15+F15+G15-1)/K15,"") | N15: =IFERROR(INDEX(Lists!$AF$2:$AF$5,MATCH(D15,Lists!$AE$2:$AE$5,0))&"–"&INDEX(Lists!$AG$2:$AG$5,MATCH(D15,Lists!$AE$2:$AE$5,0)),"") | O15: =IFERROR(IF(OR(M15="",D15=""),"",IF(M15<INDEX(Lists!$AF$2:$AF$5,MATCH(D15,Lists!$AE$2:$AE$5,0)),"Below range",IF(M15>INDEX(Lists!$AG$2:$AG$5,MATCH(D15,Lists!$AE$2:$AE$5,0)),"Above range","Within range"))),"") | P15: =IF(ISNUMBER(L15),IF(L15>Engagement!$C$43,"Exceeds maximum","Within maximum"),"") | R15: =IF(AND(ISNUMBER(Q15),(E15+F15)>0),Q15/(E15+F15),"")
A16: O10 | I16: =IF(COUNT(E16:H16)=0,"",SUM(E16:H16)) | J16: =IF(AND(ISNUMBER(I16),I16>0),(G16+H16)/I16,"") | M16: =IF(AND(ISNUMBER(K16),K16>0),(E16+F16+G16-1)/K16,"") | N16: =IFERROR(INDEX(Lists!$AF$2:$AF$5,MATCH(D16,Lists!$AE$2:$AE$5,0))&"–"&INDEX(Lists!$AG$2:$AG$5,MATCH(D16,Lists!$AE$2:$AE$5,0)),"") | O16: =IFERROR(IF(OR(M16="",D16=""),"",IF(M16<INDEX(Lists!$AF$2:$AF$5,MATCH(D16,Lists!$AE$2:$AE$5,0)),"Below range",IF(M16>INDEX(Lists!$AG$2:$AG$5,MATCH(D16,Lists!$AE$2:$AE$5,0)),"Above range","Within range"))),"") | P16: =IF(ISNUMBER(L16),IF(L16>Engagement!$C$43,"Exceeds maximum","Within maximum"),"") | R16: =IF(AND(ISNUMBER(Q16),(E16+F16)>0),Q16/(E16+F16),"")
A17: O11 | I17: =IF(COUNT(E17:H17)=0,"",SUM(E17:H17)) | J17: =IF(AND(ISNUMBER(I17),I17>0),(G17+H17)/I17,"") | M17: =IF(AND(ISNUMBER(K17),K17>0),(E17+F17+G17-1)/K17,"") | N17: =IFERROR(INDEX(Lists!$AF$2:$AF$5,MATCH(D17,Lists!$AE$2:$AE$5,0))&"–"&INDEX(Lists!$AG$2:$AG$5,MATCH(D17,Lists!$AE$2:$AE$5,0)),"") | O17: =IFERROR(IF(OR(M17="",D17=""),"",IF(M17<INDEX(Lists!$AF$2:$AF$5,MATCH(D17,Lists!$AE$2:$AE$5,0)),"Below range",IF(M17>INDEX(Lists!$AG$2:$AG$5,MATCH(D17,Lists!$AE$2:$AE$5,0)),"Above range","Within range"))),"") | P17: =IF(ISNUMBER(L17),IF(L17>Engagement!$C$43,"Exceeds maximum","Within maximum"),"") | R17: =IF(AND(ISNUMBER(Q17),(E17+F17)>0),Q17/(E17+F17),"")
A18: O12 | I18: =IF(COUNT(E18:H18)=0,"",SUM(E18:H18)) | J18: =IF(AND(ISNUMBER(I18),I18>0),(G18+H18)/I18,"") | M18: =IF(AND(ISNUMBER(K18),K18>0),(E18+F18+G18-1)/K18,"") | N18: =IFERROR(INDEX(Lists!$AF$2:$AF$5,MATCH(D18,Lists!$AE$2:$AE$5,0))&"–"&INDEX(Lists!$AG$2:$AG$5,MATCH(D18,Lists!$AE$2:$AE$5,0)),"") | O18: =IFERROR(IF(OR(M18="",D18=""),"",IF(M18<INDEX(Lists!$AF$2:$AF$5,MATCH(D18,Lists!$AE$2:$AE$5,0)),"Below range",IF(M18>INDEX(Lists!$AG$2:$AG$5,MATCH(D18,Lists!$AE$2:$AE$5,0)),"Above range","Within range"))),"") | P18: =IF(ISNUMBER(L18),IF(L18>Engagement!$C$43,"Exceeds maximum","Within maximum"),"") | R18: =IF(AND(ISNUMBER(Q18),(E18+F18)>0),Q18/(E18+F18),"")
... A36: O30 | I36: =IF(COUNT(E36:H36)=0,"",SUM(E36:H36)) | J36: =IF(AND(ISNUMBER(I36),I36>0),(G36+H36)/I36,"") | M36: =IF(AND(ISNUMBER(K36),K36>0),(E36+F36+G36-1)/K36,"") | N36: =IFERROR(INDEX(Lists!$AF$2:$AF$5,MATCH(D36,Lists!$AE$2:$AE$5,0))&"–"&INDEX(Lists!$AG$2:$AG$5,MATCH(D36,Lists!$AE$2:$AE$5,0)),"") | O36: =IFERROR(IF(OR(M36="",D36=""),"",IF(M36<INDEX(Lists!$AF$2:$AF$5,MATCH(D36,Lists!$AE$2:$AE$5,0)),"Below range",IF(M36>INDEX(Lists!$AG$2:$AG$5,MATCH(D36,Lists!$AE$2:$AE$5,0)),"Above range","Within range"))),"") | P36: =IF(ISNUMBER(L36),IF(L36>Engagement!$C$43,"Exceeds maximum","Within maximum"),"") | R36: =IF(AND(ISNUMBER(Q36),(E36+F36)>0),Q36/(E36+F36),"")
B37: Total (excluding example) | E37: =SUMIF($A$6:$A$36,"<>Example",E6:E36) -> 0 | F37: =SUMIF($A$6:$A$36,"<>Example",F6:F36) -> 0 | G37: =SUMIF($A$6:$A$36,"<>Example",G6:G36) -> 0 | H37: =SUMIF($A$6:$A$36,"<>Example",H6:H36) -> 0 | I37: =SUMIF($A$6:$A$36,"<>Example",I6:I36) -> 0 | J37: =IF(I37>0,(G37+H37)/I37,"") | K37: =SUMIF($A$6:$A$36,"<>Example",K6:K36) -> 0 | L37: =_xlfn.MAXIFS(L6:L36,$A$6:$A$36,"<>Example") -> 0 | M37: =IF(K37>0,(E37+F37+G37-1)/K37,"") | Q37: =SUMIF($A$6:$A$36,"<>Example",Q6:Q36) -> 0 | R37: =IF((E37+F37)>0,Q37/(E37+F37),"") | S37: =SUMIF($A$6:$A$36,"<>Example",S6:S36) -> 0

Sheet Decision Rights
A1: Decision Rights Matrix (RAPID)
A2: R = Recommend | A = Agree (must sign off) | P = Perform (implements) | I = Input (consulted) | D = Decide (exactly one per decision). Record the current state as observed; role headings (yellow) can be renamed.
A3: Legend: yellow cells = inputs | grey cells = calculated (do not overwrite) | green text = linked from another tab | grey italic row = example (overwrite or delete)
A5: ID | B5: Key decision | C5: Board | D5: Audit & Risk Committee | E5: CEO | F5: Executive Committee | G5: Investment Committee | H5: CFO | I5: COO | J5: CIO | K5: CHRO | L5: CRO | M5: BU Head | N5: Decide roles (#) | O5: Check | P5: Documented in delegations? | Q5: Typical decision time (days) | R5: Observations
A6: DEC01 | B6: Approve organisational strategy | N6: =IF(COUNTA(C6:M6)=0,"",COUNTIF(C6:M6,"D")) | O6: =IF(COUNTA(C6:M6)=0,"",IF(N6=1,"OK",IF(N6=0,"No decider","Multiple deciders")))
A7: DEC02 | B7: Approve annual budget | N7: =IF(COUNTA(C7:M7)=0,"",COUNTIF(C7:M7,"D")) | O7: =IF(COUNTA(C7:M7)=0,"",IF(N7=1,"OK",IF(N7=0,"No decider","Multiple deciders")))
A8: DEC03 | B8: Approve risk appetite statement | N8: =IF(COUNTA(C8:M8)=0,"",COUNTIF(C8:M8,"D")) | O8: =IF(COUNTA(C8:M8)=0,"",IF(N8=1,"OK",IF(N8=0,"No decider","Multiple deciders")))
A9: DEC04 | B9: Approve launch of a new product or service | N9: =IF(COUNTA(C9:M9)=0,"",COUNTIF(C9:M9,"D")) | O9: =IF(COUNTA(C9:M9)=0,"",IF(N9=1,"OK",IF(N9=0,"No decider","Multiple deciders")))
A10: DEC05 | B10: Approve investment above delegated threshold | N10: =IF(COUNTA(C10:M10)=0,"",COUNTIF(C10:M10,"D")) | O10: =IF(COUNTA(C10:M10)=0,"",IF(N10=1,"OK",IF(N10=0,"No decider","Multiple deciders")))
A11: DEC06 | B11: Prioritise the change portfolio | N11: =IF(COUNTA(C11:M11)=0,"",COUNTIF(C11:M11,"D")) | O11: =IF(COUNTA(C11:M11)=0,"",IF(N11=1,"OK",IF(N11=0,"No decider","Multiple deciders")))
A12: DEC07 | B12: Approve organisational restructure | N12: =IF(COUNTA(C12:M12)=0,"",COUNTIF(C12:M12,"D")) | O12: =IF(COUNTA(C12:M12)=0,"",IF(N12=1,"OK",IF(N12=0,"No decider","Multiple deciders")))
A13: DEC08 | B13: Appoint executive roles | N13: =IF(COUNTA(C13:M13)=0,"",COUNTIF(C13:M13,"D")) | O13: =IF(COUNTA(C13:M13)=0,"",IF(N13=1,"OK",IF(N13=0,"No decider","Multiple deciders")))
A14: DEC09 | B14: Approve headcount increases | N14: =IF(COUNTA(C14:M14)=0,"",COUNTIF(C14:M14,"D")) | O14: =IF(COUNTA(C14:M14)=0,"",IF(N14=1,"OK",IF(N14=0,"No decider","Multiple deciders")))
A15: DEC10 | B15: Approve enterprise-level policies | N15: =IF(COUNTA(C15:M15)=0,"",COUNTIF(C15:M15,"D")) | O15: =IF(COUNTA(C15:M15)=0,"",IF(N15=1,"OK",IF(N15=0,"No decider","Multiple deciders")))
A16: DEC11 | B16: Award a major contract / select strategic supplier | N16: =IF(COUNTA(C16:M16)=0,"",COUNTIF(C16:M16,"D")) | O16: =IF(COUNTA(C16:M16)=0,"",IF(N16=1,"OK",IF(N16=0,"No decider","Multiple deciders")))
A17: DEC12 | B17: Approve technology architecture standards | N17: =IF(COUNTA(C17:M17)=0,"",COUNTIF(C17:M17,"D")) | O17: =IF(COUNTA(C17:M17)=0,"",IF(N17=1,"OK",IF(N17=0,"No decider","Multiple deciders")))
... A26: DEC21 | B26: Approve deployment of an AI use case | N26: =IF(COUNTA(C26:M26)=0,"",COUNTIF(C26:M26,"D")) | O26: =IF(COUNTA(C26:M26)=0,"",IF(N26=1,"OK",IF(N26=0,"No decider","Multiple deciders")))
A27: DEC22 | N27: =IF(COUNTA(C27:M27)=0,"",COUNTIF(C27:M27,"D")) | O27: =IF(COUNTA(C27:M27)=0,"",IF(N27=1,"OK",IF(N27=0,"No decider","Multiple deciders")))
A28: DEC23 | N28: =IF(COUNTA(C28:M28)=0,"",COUNTIF(C28:M28,"D")) | O28: =IF(COUNTA(C28:M28)=0,"",IF(N28=1,"OK",IF(N28=0,"No decider","Multiple deciders")))
A29: DEC24 | N29: =IF(COUNTA(C29:M29)=0,"",COUNTIF(C29:M29,"D")) | O29: =IF(COUNTA(C29:M29)=0,"",IF(N29=1,"OK",IF(N29=0,"No decider","Multiple deciders")))
A30: DEC25 | N30: =IF(COUNTA(C30:M30)=0,"",COUNTIF(C30:M30,"D")) | O30: =IF(COUNTA(C30:M30)=0,"",IF(N30=1,"OK",IF(N30=0,"No decider","Multiple deciders")))
A31: DEC26 | N31: =IF(COUNTA(C31:M31)=0,"",COUNTIF(C31:M31,"D")) | O31: =IF(COUNTA(C31:M31)=0,"",IF(N31=1,"OK",IF(N31=0,"No decider","Multiple deciders")))
A32: DEC27 | N32: =IF(COUNTA(C32:M32)=0,"",COUNTIF(C32:M32,"D")) | O32: =IF(COUNTA(C32:M32)=0,"",IF(N32=1,"OK",IF(N32=0,"No decider","Multiple deciders")))
A33: DEC28 | N33: =IF(COUNTA(C33:M33)=0,"",COUNTIF(C33:M33,"D")) | O33: =IF(COUNTA(C33:M33)=0,"",IF(N33=1,"OK",IF(N33=0,"No decider","Multiple deciders")))
A34: DEC29 | N34: =IF(COUNTA(C34:M34)=0,"",COUNTIF(C34:M34,"D")) | O34: =IF(COUNTA(C34:M34)=0,"",IF(N34=1,"OK",IF(N34=0,"No decider","Multiple deciders")))
A35: DEC30 | N35: =IF(COUNTA(C35:M35)=0,"",COUNTIF(C35:M35,"D")) | O35: =IF(COUNTA(C35:M35)=0,"",IF(N35=1,"OK",IF(N35=0,"No decider","Multiple deciders")))
A36: DEC31 | N36: =IF(COUNTA(C36:M36)=0,"",COUNTIF(C36:M36,"D")) | O36: =IF(COUNTA(C36:M36)=0,"",IF(N36=1,"OK",IF(N36=0,"No decider","Multiple deciders")))

Sheet Applications
A1: Application Portfolio
A2: TIME classification from business and technical fit (threshold on the Engagement tab): Invest = high / high, Migrate = high business / low technical, Tolerate = low business / high technical, Eliminate = low / low.
A3: Legend: yellow cells = inputs | grey cells = calculated (do not overwrite) | green text = linked from another tab | grey italic row = example (overwrite or delete)
A5: ID | B5: Application name | C5: Description / purpose | D5: Capabilities supported | E5: Business owner | F5: Technical owner | G5: Vendor / product (version) | H5: Hosting model | I5: Users (#) | J5: Business criticality | K5: Annual cost ($) | L5: Support / contract end | M5: Support status | N5: Business fit (1–5) | O5: Technical fit (1–5) | P5: TIME classification | Q5: Days to support end | R5: Data classification | S5: Interfaces (#) | T5: Overlap / duplication | U5: Observations
A6: Example | B6: Case Management System | C6: Manages client cases from intake to closure | D6: Case management; Customer support | E6: GM Operations | F6: Applications Manager | G6: Vendor product (v9.2) | H6: Private cloud | I6: 850 | J6: Critical | K6: 420000 | L6: 46568 | M6: Extended support | N6: 4 | O6: 2 | P6: =IF(AND(ISNUMBER(N6),ISNUMBER(O6)),IF(N6>=Engagement!$C$45,IF(O6>=Engagement!$C$45,"Invest","Migrate"),IF(O6>=Engagement!$C$45,"Tolerate","Eliminate")),"") -> Migrate | Q6: =IF(ISNUMBER(L6),L6-TODAY(),"") -> 274 | R6: Confidential | S6: 12 | T6: Contact history duplicated in legacy CRM | U6: Heavy customisation is blocking upgrades.
A7: A001 | P7: =IF(AND(ISNUMBER(N7),ISNUMBER(O7)),IF(N7>=Engagement!$C$45,IF(O7>=Engagement!$C$45,"Invest","Migrate"),IF(O7>=Engagement!$C$45,"Tolerate","Eliminate")),"") | Q7: =IF(ISNUMBER(L7),L7-TODAY(),"")
A8: A002 | P8: =IF(AND(ISNUMBER(N8),ISNUMBER(O8)),IF(N8>=Engagement!$C$45,IF(O8>=Engagement!$C$45,"Invest","Migrate"),IF(O8>=Engagement!$C$45,"Tolerate","Eliminate")),"") | Q8: =IF(ISNUMBER(L8),L8-TODAY(),"")
A9: A003 | P9: =IF(AND(ISNUMBER(N9),ISNUMBER(O9)),IF(N9>=Engagement!$C$45,IF(O9>=Engagement!$C$45,"Invest","Migrate"),IF(O9>=Engagement!$C$45,"Tolerate","Eliminate")),"") | Q9: =IF(ISNUMBER(L9),L9-TODAY(),"")
A10: A004 | P10: =IF(AND(ISNUMBER(N10),ISNUMBER(O10)),IF(N10>=Engagement!$C$45,IF(O10>=Engagement!$C$45,"Invest","Migrate"),IF(O10>=Engagement!$C$45,"Tolerate","Eliminate")),"") | Q10: =IF(ISNUMBER(L10),L10-TODAY(),"")
A11: A005 | P11: =IF(AND(ISNUMBER(N11),ISNUMBER(O11)),IF(N11>=Engagement!$C$45,IF(O11>=Engagement!$C$45,"Invest","Migrate"),IF(O11>=Engagement!$C$45,"Tolerate","Eliminate")),"") | Q11: =IF(ISNUMBER(L11),L11-TODAY(),"")
A12: A006 | P12: =IF(AND(ISNUMBER(N12),ISNUMBER(O12)),IF(N12>=Engagement!$C$45,IF(O12>=Engagement!$C$45,"Invest","Migrate"),IF(O12>=Engagement!$C$45,"Tolerate","Eliminate")),"") | Q12: =IF(ISNUMBER(L12),L12-TODAY(),"")
A13: A007 | P13: =IF(AND(ISNUMBER(N13),ISNUMBER(O13)),IF(N13>=Engagement!$C$45,IF(O13>=Engagement!$C$45,"Invest","Migrate"),IF(O13>=Engagement!$C$45,"Tolerate","Eliminate")),"") | Q13: =IF(ISNUMBER(L13),L13-TODAY(),"")
A14: A008 | P14: =IF(AND(ISNUMBER(N14),ISNUMBER(O14)),IF(N14>=Engagement!$C$45,IF(O14>=Engagement!$C$45,"Invest","Migrate"),IF(O14>=Engagement!$C$45,"Tolerate","Eliminate")),"") | Q14: =IF(ISNUMBER(L14),L14-TODAY(),"")
A15: A009 | P15: =IF(AND(ISNUMBER(N15),ISNUMBER(O15)),IF(N15>=Engagement!$C$45,IF(O15>=Engagement!$C$45,"Invest","Migrate"),IF(O15>=Engagement!$C$45,"Tolerate","Eliminate")),"") | Q15: =IF(ISNUMBER(L15),L15-TODAY(),"")
A16: A010 | P16: =IF(AND(ISNUMBER(N16),ISNUMBER(O16)),IF(N16>=Engagement!$C$45,IF(O16>=Engagement!$C$45,"Invest","Migrate"),IF(O16>=Engagement!$C$45,"Tolerate","Eliminate")),"") | Q16: =IF(ISNUMBER(L16),L16-TODAY(),"")
A17: A011 | P17: =IF(AND(ISNUMBER(N17),ISNUMBER(O17)),IF(N17>=Engagement!$C$45,IF(O17>=Engagement!$C$45,"Invest","Migrate"),IF(O17>=Engagement!$C$45,"Tolerate","Eliminate")),"") | Q17: =IF(ISNUMBER(L17),L17-TODAY(),"")
A18: A012 | P18: =IF(AND(ISNUMBER(N18),ISNUMBER(O18)),IF(N18>=Engagement!$C$45,IF(O18>=Engagement!$C$45,"Invest","Migrate"),IF(O18>=Engagement!$C$45,"Tolerate","Eliminate")),"") | Q18: =IF(ISNUMBER(L18),L18-TODAY(),"")
... A156: A150 | P156: =IF(AND(ISNUMBER(N156),ISNUMBER(O156)),IF(N156>=Engagement!$C$45,IF(O156>=Engagement!$C$45,"Invest","Migrate"),IF(O156>=Engagement!$C$45,"Tolerate","Eliminate")),"") | Q156: =IF(ISNUMBER(L156),L156-TODAY(),"")

Sheet Suppliers
A1: Supplier & Sourcing Register
A2: Focus on suppliers that deliver or enable in-scope capabilities. Dependency risk: High = single source with no complete exit plan; Medium = single source with an exit plan, or a material service provider without a complete exit plan.
A3: Legend: yellow cells = inputs | grey cells = calculated (do not overwrite) | green text = linked from another tab | grey italic row = example (overwrite or delete)
A5: ID | B5: Supplier | C5: Services provided | D5: Capability / process supported | E5: Segment | F5: Annual spend ($) | G5: % of total spend | H5: Contract start | I5: Contract end | J5: Days to expiry | K5: Renewal flag | L5: Material service provider? | M5: Single source? | N5: Exit plan in place? | O5: Dependency risk | P5: Performance rating (1–5) | Q5: Security assurance | R5: Contract owner | S5: Observations
A6: Example | B6: Managed IT services provider | C6: Service desk, end-user support and infrastructure operations | D6: IT service management; Infrastructure | E6: Strategic | F6: 3200000 | G6: =IF(AND(ISNUMBER(F6),A6<>"Example"),IFERROR(F6/SUMIF($A$6:$A$106,"<>Example",$F$6:$F$106),""),"") | H6: 45108 | I6: 46568 | J6: =IF(ISNUMBER(I6),I6-TODAY(),"") -> 274 | K6: =IF(ISNUMBER(J6),IF(J6<0,"Expired",IF(J6<=Engagement!$C$44,"Decision due","")),"") | L6: Yes | M6: Yes | N6: Partial | O6: =IF(AND(L6="",M6="",N6=""),"",IF(AND(M6="Yes",N6<>"Yes"),"High",IF(OR(M6="Yes",AND(L6="Yes",N6<>"Yes")),"Medium","Low"))) -> High | P6: 3 | Q6: ISO/IEC 27001 certified | R6: Head of IT Operations | S6: No tested exit plan; knowledge concentrated in the provider.
A7: SUP001 | G7: =IF(AND(ISNUMBER(F7),A7<>"Example"),IFERROR(F7/SUMIF($A$6:$A$106,"<>Example",$F$6:$F$106),""),"") | J7: =IF(ISNUMBER(I7),I7-TODAY(),"") | K7: =IF(ISNUMBER(J7),IF(J7<0,"Expired",IF(J7<=Engagement!$C$44,"Decision due","")),"") | O7: =IF(AND(L7="",M7="",N7=""),"",IF(AND(M7="Yes",N7<>"Yes"),"High",IF(OR(M7="Yes",AND(L7="Yes",N7<>"Yes")),"Medium","Low")))
A8: SUP002 | G8: =IF(AND(ISNUMBER(F8),A8<>"Example"),IFERROR(F8/SUMIF($A$6:$A$106,"<>Example",$F$6:$F$106),""),"") | J8: =IF(ISNUMBER(I8),I8-TODAY(),"") | K8: =IF(ISNUMBER(J8),IF(J8<0,"Expired",IF(J8<=Engagement!$C$44,"Decision due","")),"") | O8: =IF(AND(L8="",M8="",N8=""),"",IF(AND(M8="Yes",N8<>"Yes"),"High",IF(OR(M8="Yes",AND(L8="Yes",N8<>"Yes")),"Medium","Low")))
A9: SUP003 | G9: =IF(AND(ISNUMBER(F9),A9<>"Example"),IFERROR(F9/SUMIF($A$6:$A$106,"<>Example",$F$6:$F$106),""),"") | J9: =IF(ISNUMBER(I9),I9-TODAY(),"") | K9: =IF(ISNUMBER(J9),IF(J9<0,"Expired",IF(J9<=Engagement!$C$44,"Decision due","")),"") | O9: =IF(AND(L9="",M9="",N9=""),"",IF(AND(M9="Yes",N9<>"Yes"),"High",IF(OR(M9="Yes",AND(L9="Yes",N9<>"Yes")),"Medium","Low")))
A10: SUP004 | G10: =IF(AND(ISNUMBER(F10),A10<>"Example"),IFERROR(F10/SUMIF($A$6:$A$106,"<>Example",$F$6:$F$106),""),"") | J10: =IF(ISNUMBER(I10),I10-TODAY(),"") | K10: =IF(ISNUMBER(J10),IF(J10<0,"Expired",IF(J10<=Engagement!$C$44,"Decision due","")),"") | O10: =IF(AND(L10="",M10="",N10=""),"",IF(AND(M10="Yes",N10<>"Yes"),"High",IF(OR(M10="Yes",AND(L10="Yes",N10<>"Yes")),"Medium","Low")))
A11: SUP005 | G11: =IF(AND(ISNUMBER(F11),A11<>"Example"),IFERROR(F11/SUMIF($A$6:$A$106,"<>Example",$F$6:$F$106),""),"") | J11: =IF(ISNUMBER(I11),I11-TODAY(),"") | K11: =IF(ISNUMBER(J11),IF(J11<0,"Expired",IF(J11<=Engagement!$C$44,"Decision due","")),"") | O11: =IF(AND(L11="",M11="",N11=""),"",IF(AND(M11="Yes",N11<>"Yes"),"High",IF(OR(M11="Yes",AND(L11="Yes",N11<>"Yes")),"Medium","Low")))
A12: SUP006 | G12: =IF(AND(ISNUMBER(F12),A12<>"Example"),IFERROR(F12/SUMIF($A$6:$A$106,"<>Example",$F$6:$F$106),""),"") | J12: =IF(ISNUMBER(I12),I12-TODAY(),"") | K12: =IF(ISNUMBER(J12),IF(J12<0,"Expired",IF(J12<=Engagement!$C$44,"Decision due","")),"") | O12: =IF(AND(L12="",M12="",N12=""),"",IF(AND(M12="Yes",N12<>"Yes"),"High",IF(OR(M12="Yes",AND(L12="Yes",N12<>"Yes")),"Medium","Low")))
A13: SUP007 | G13: =IF(AND(ISNUMBER(F13),A13<>"Example"),IFERROR(F13/SUMIF($A$6:$A$106,"<>Example",$F$6:$F$106),""),"") | J13: =IF(ISNUMBER(I13),I13-TODAY(),"") | K13: =IF(ISNUMBER(J13),IF(J13<0,"Expired",IF(J13<=Engagement!$C$44,"Decision due","")),"") | O13: =IF(AND(L13="",M13="",N13=""),"",IF(AND(M13="Yes",N13<>"Yes"),"High",IF(OR(M13="Yes",AND(L13="Yes",N13<>"Yes")),"Medium","Low")))
A14: SUP008 | G14: =IF(AND(ISNUMBER(F14),A14<>"Example"),IFERROR(F14/SUMIF($A$6:$A$106,"<>Example",$F$6:$F$106),""),"") | J14: =IF(ISNUMBER(I14),I14-TODAY(),"") | K14: =IF(ISNUMBER(J14),IF(J14<0,"Expired",IF(J14<=Engagement!$C$44,"Decision due","")),"") | O14: =IF(AND(L14="",M14="",N14=""),"",IF(AND(M14="Yes",N14<>"Yes"),"High",IF(OR(M14="Yes",AND(L14="Yes",N14<>"Yes")),"Medium","Low")))
A15: SUP009 | G15: =IF(AND(ISNUMBER(F15),A15<>"Example"),IFERROR(F15/SUMIF($A$6:$A$106,"<>Example",$F$6:$F$106),""),"") | J15: =IF(ISNUMBER(I15),I15-TODAY(),"") | K15: =IF(ISNUMBER(J15),IF(J15<0,"Expired",IF(J15<=Engagement!$C$44,"Decision due","")),"") | O15: =IF(AND(L15="",M15="",N15=""),"",IF(AND(M15="Yes",N15<>"Yes"),"High",IF(OR(M15="Yes",AND(L15="Yes",N15<>"Yes")),"Medium","Low")))
A16: SUP010 | G16: =IF(AND(ISNUMBER(F16),A16<>"Example"),IFERROR(F16/SUMIF($A$6:$A$106,"<>Example",$F$6:$F$106),""),"") | J16: =IF(ISNUMBER(I16),I16-TODAY(),"") | K16: =IF(ISNUMBER(J16),IF(J16<0,"Expired",IF(J16<=Engagement!$C$44,"Decision due","")),"") | O16: =IF(AND(L16="",M16="",N16=""),"",IF(AND(M16="Yes",N16<>"Yes"),"High",IF(OR(M16="Yes",AND(L16="Yes",N16<>"Yes")),"Medium","Low")))
A17: SUP011 | G17: =IF(AND(ISNUMBER(F17),A17<>"Example"),IFERROR(F17/SUMIF($A$6:$A$106,"<>Example",$F$6:$F$106),""),"") | J17: =IF(ISNUMBER(I17),I17-TODAY(),"") | K17: =IF(ISNUMBER(J17),IF(J17<0,"Expired",IF(J17<=Engagement!$C$44,"Decision due","")),"") | O17: =IF(AND(L17="",M17="",N17=""),"",IF(AND(M17="Yes",N17<>"Yes"),"High",IF(OR(M17="Yes",AND(L17="Yes",N17<>"Yes")),"Medium","Low")))
A18: SUP012 | G18: =IF(AND(ISNUMBER(F18),A18<>"Example"),IFERROR(F18/SUMIF($A$6:$A$106,"<>Example",$F$6:$F$106),""),"") | J18: =IF(ISNUMBER(I18),I18-TODAY(),"") | K18: =IF(ISNUMBER(J18),IF(J18<0,"Expired",IF(J18<=Engagement!$C$44,"Decision due","")),"") | O18: =IF(AND(L18="",M18="",N18=""),"",IF(AND(M18="Yes",N18<>"Yes"),"High",IF(OR(M18="Yes",AND(L18="Yes",N18<>"Yes")),"Medium","Low")))
... A106: SUP100 | G106: =IF(AND(ISNUMBER(F106),A106<>"Example"),IFERROR(F106/SUMIF($A$6:$A$106,"<>Example",$F$6:$F$106),""),"") | J106: =IF(ISNUMBER(I106),I106-TODAY(),"") | K106: =IF(ISNUMBER(J106),IF(J106<0,"Expired",IF(J106<=Engagement!$C$44,"Decision due","")),"") | O106: =IF(AND(L106="",M106="",N106=""),"",IF(AND(M106="Yes",N106<>"Yes"),"High",IF(OR(M106="Yes",AND(L106="Yes",N106<>"Yes")),"Medium","Low")))
B107: Total annual spend (excluding example) | F107: =SUMIF($A$6:$A$106,"<>Example",$F$6:$F$106) -> 0

Sheet Locations
A1: Locations & Property Register
A2: One row per site. Utilisation is average occupied workstations ÷ capacity, entered as a percentage.
A3: Legend: yellow cells = inputs | grey cells = calculated (do not overwrite) | green text = linked from another tab | grey italic row = example (overwrite or delete)
A5: ID | B5: Site name | C5: City / state | D5: Site type | E5: Functions performed | F5: FTE based at site | G5: Workstations / capacity | H5: Average utilisation (%) | I5: Tenure | J5: Lease expiry | K5: Days to lease expiry | L5: Annual property cost ($) | M5: Cost per FTE ($) | N5: Cost per workstation ($) | O5: Critical site? | P5: Alternate / BCP site | Q5: Observations
A6: Example | B6: Parramatta Service Centre | C6: Parramatta, NSW | D6: Service centre | E6: Claims processing; contact centre | F6: 220 | G6: 180 | H6: 0.62 | I6: Leased | J6: 46843 | K6: =IF(ISNUMBER(J6),J6-TODAY(),"") -> 549 | L6: 2150000 | M6: =IF(AND(ISNUMBER(L6),ISNUMBER(F6),F6>0),L6/F6,"") -> 9772.7273 | N6: =IF(AND(ISNUMBER(L6),ISNUMBER(G6),G6>0),L6/G6,"") -> 11944.444 | O6: Yes | P6: Work from home; Sydney CBD office | Q6: Lease expiry aligns with footprint review.
A7: L01 | K7: =IF(ISNUMBER(J7),J7-TODAY(),"") | M7: =IF(AND(ISNUMBER(L7),ISNUMBER(F7),F7>0),L7/F7,"") | N7: =IF(AND(ISNUMBER(L7),ISNUMBER(G7),G7>0),L7/G7,"")
A8: L02 | K8: =IF(ISNUMBER(J8),J8-TODAY(),"") | M8: =IF(AND(ISNUMBER(L8),ISNUMBER(F8),F8>0),L8/F8,"") | N8: =IF(AND(ISNUMBER(L8),ISNUMBER(G8),G8>0),L8/G8,"")
A9: L03 | K9: =IF(ISNUMBER(J9),J9-TODAY(),"") | M9: =IF(AND(ISNUMBER(L9),ISNUMBER(F9),F9>0),L9/F9,"") | N9: =IF(AND(ISNUMBER(L9),ISNUMBER(G9),G9>0),L9/G9,"")
A10: L04 | K10: =IF(ISNUMBER(J10),J10-TODAY(),"") | M10: =IF(AND(ISNUMBER(L10),ISNUMBER(F10),F10>0),L10/F10,"") | N10: =IF(AND(ISNUMBER(L10),ISNUMBER(G10),G10>0),L10/G10,"")
A11: L05 | K11: =IF(ISNUMBER(J11),J11-TODAY(),"") | M11: =IF(AND(ISNUMBER(L11),ISNUMBER(F11),F11>0),L11/F11,"") | N11: =IF(AND(ISNUMBER(L11),ISNUMBER(G11),G11>0),L11/G11,"")
A12: L06 | K12: =IF(ISNUMBER(J12),J12-TODAY(),"") | M12: =IF(AND(ISNUMBER(L12),ISNUMBER(F12),F12>0),L12/F12,"") | N12: =IF(AND(ISNUMBER(L12),ISNUMBER(G12),G12>0),L12/G12,"")
A13: L07 | K13: =IF(ISNUMBER(J13),J13-TODAY(),"") | M13: =IF(AND(ISNUMBER(L13),ISNUMBER(F13),F13>0),L13/F13,"") | N13: =IF(AND(ISNUMBER(L13),ISNUMBER(G13),G13>0),L13/G13,"")
A14: L08 | K14: =IF(ISNUMBER(J14),J14-TODAY(),"") | M14: =IF(AND(ISNUMBER(L14),ISNUMBER(F14),F14>0),L14/F14,"") | N14: =IF(AND(ISNUMBER(L14),ISNUMBER(G14),G14>0),L14/G14,"")
A15: L09 | K15: =IF(ISNUMBER(J15),J15-TODAY(),"") | M15: =IF(AND(ISNUMBER(L15),ISNUMBER(F15),F15>0),L15/F15,"") | N15: =IF(AND(ISNUMBER(L15),ISNUMBER(G15),G15>0),L15/G15,"")
A16: L10 | K16: =IF(ISNUMBER(J16),J16-TODAY(),"") | M16: =IF(AND(ISNUMBER(L16),ISNUMBER(F16),F16>0),L16/F16,"") | N16: =IF(AND(ISNUMBER(L16),ISNUMBER(G16),G16>0),L16/G16,"")
A17: L11 | K17: =IF(ISNUMBER(J17),J17-TODAY(),"") | M17: =IF(AND(ISNUMBER(L17),ISNUMBER(F17),F17>0),L17/F17,"") | N17: =IF(AND(ISNUMBER(L17),ISNUMBER(G17),G17>0),L17/G17,"")
A18: L12 | K18: =IF(ISNUMBER(J18),J18-TODAY(),"") | M18: =IF(AND(ISNUMBER(L18),ISNUMBER(F18),F18>0),L18/F18,"") | N18: =IF(AND(ISNUMBER(L18),ISNUMBER(G18),G18>0),L18/G18,"")
... A46: L40 | K46: =IF(ISNUMBER(J46),J46-TODAY(),"") | M46: =IF(AND(ISNUMBER(L46),ISNUMBER(F46),F46>0),L46/F46,"") | N46: =IF(AND(ISNUMBER(L46),ISNUMBER(G46),G46>0),L46/G46,"")
B47: Total (excluding example) | F47: =SUMIF($A$6:$A$46,"<>Example",F6:F46) -> 0 | G47: =SUMIF($A$6:$A$46,"<>Example",G6:G46) -> 0 | L47: =SUMIF($A$6:$A$46,"<>Example",L6:L46) -> 0 | M47: =IF(F47>0,L47/F47,"") | N47: =IF(G47>0,L47/G47,"")

Sheet Cost Baseline
A1: Cost Baseline
A2: Annual operating cost by business unit / function and cost type (AUD, latest full financial year), reconciled to the general ledger.
A3: Legend: yellow cells = inputs | grey cells = calculated (do not overwrite) | green text = linked from another tab | grey italic row = example (overwrite or delete)
A5: ID | B5: Business unit / function | C5: Employee costs ($) | D5: Contractor costs ($) | E5: Technology costs ($) | F5: Property costs ($) | G5: Outsourced / third-party ($) | H5: Other operating ($) | I5: Total cost ($) | J5: % of total | K5: FTE | L5: Cost per FTE ($) | M5: Of which change / project spend ($) | N5: Change spend % | O5: Observations
A6: Example | B6: Customer Operations | C6: 21450000 | D6: 1850000 | E6: 2600000 | F6: 2150000 | G6: 3200000 | H6: 900000 | I6: =IF(COUNT(C6:H6)=0,"",SUM(C6:H6)) -> 32150000 | J6: =IF(AND(ISNUMBER(I6),A6<>"Example",$I$37>0),I6/$I$37,"") | K6: 228 | L6: =IF(AND(ISNUMBER(I6),ISNUMBER(K6),K6>0),I6/K6,"") -> 141008.77 | M6: 1200000 | N6: =IF(AND(ISNUMBER(M6),ISNUMBER(I6),I6>0),M6/I6,"") -> 0.037325039 | O6: Includes allocated contact-centre technology.
A7: CB01 | I7: =IF(COUNT(C7:H7)=0,"",SUM(C7:H7)) | J7: =IF(AND(ISNUMBER(I7),A7<>"Example",$I$37>0),I7/$I$37,"") | L7: =IF(AND(ISNUMBER(I7),ISNUMBER(K7),K7>0),I7/K7,"") | N7: =IF(AND(ISNUMBER(M7),ISNUMBER(I7),I7>0),M7/I7,"")
A8: CB02 | I8: =IF(COUNT(C8:H8)=0,"",SUM(C8:H8)) | J8: =IF(AND(ISNUMBER(I8),A8<>"Example",$I$37>0),I8/$I$37,"") | L8: =IF(AND(ISNUMBER(I8),ISNUMBER(K8),K8>0),I8/K8,"") | N8: =IF(AND(ISNUMBER(M8),ISNUMBER(I8),I8>0),M8/I8,"")
A9: CB03 | I9: =IF(COUNT(C9:H9)=0,"",SUM(C9:H9)) | J9: =IF(AND(ISNUMBER(I9),A9<>"Example",$I$37>0),I9/$I$37,"") | L9: =IF(AND(ISNUMBER(I9),ISNUMBER(K9),K9>0),I9/K9,"") | N9: =IF(AND(ISNUMBER(M9),ISNUMBER(I9),I9>0),M9/I9,"")
A10: CB04 | I10: =IF(COUNT(C10:H10)=0,"",SUM(C10:H10)) | J10: =IF(AND(ISNUMBER(I10),A10<>"Example",$I$37>0),I10/$I$37,"") | L10: =IF(AND(ISNUMBER(I10),ISNUMBER(K10),K10>0),I10/K10,"") | N10: =IF(AND(ISNUMBER(M10),ISNUMBER(I10),I10>0),M10/I10,"")
A11: CB05 | I11: =IF(COUNT(C11:H11)=0,"",SUM(C11:H11)) | J11: =IF(AND(ISNUMBER(I11),A11<>"Example",$I$37>0),I11/$I$37,"") | L11: =IF(AND(ISNUMBER(I11),ISNUMBER(K11),K11>0),I11/K11,"") | N11: =IF(AND(ISNUMBER(M11),ISNUMBER(I11),I11>0),M11/I11,"")
A12: CB06 | I12: =IF(COUNT(C12:H12)=0,"",SUM(C12:H12)) | J12: =IF(AND(ISNUMBER(I12),A12<>"Example",$I$37>0),I12/$I$37,"") | L12: =IF(AND(ISNUMBER(I12),ISNUMBER(K12),K12>0),I12/K12,"") | N12: =IF(AND(ISNUMBER(M12),ISNUMBER(I12),I12>0),M12/I12,"")
A13: CB07 | I13: =IF(COUNT(C13:H13)=0,"",SUM(C13:H13)) | J13: =IF(AND(ISNUMBER(I13),A13<>"Example",$I$37>0),I13/$I$37,"") | L13: =IF(AND(ISNUMBER(I13),ISNUMBER(K13),K13>0),I13/K13,"") | N13: =IF(AND(ISNUMBER(M13),ISNUMBER(I13),I13>0),M13/I13,"")
A14: CB08 | I14: =IF(COUNT(C14:H14)=0,"",SUM(C14:H14)) | J14: =IF(AND(ISNUMBER(I14),A14<>"Example",$I$37>0),I14/$I$37,"") | L14: =IF(AND(ISNUMBER(I14),ISNUMBER(K14),K14>0),I14/K14,"") | N14: =IF(AND(ISNUMBER(M14),ISNUMBER(I14),I14>0),M14/I14,"")
A15: CB09 | I15: =IF(COUNT(C15:H15)=0,"",SUM(C15:H15)) | J15: =IF(AND(ISNUMBER(I15),A15<>"Example",$I$37>0),I15/$I$37,"") | L15: =IF(AND(ISNUMBER(I15),ISNUMBER(K15),K15>0),I15/K15,"") | N15: =IF(AND(ISNUMBER(M15),ISNUMBER(I15),I15>0),M15/I15,"")
A16: CB10 | I16: =IF(COUNT(C16:H16)=0,"",SUM(C16:H16)) | J16: =IF(AND(ISNUMBER(I16),A16<>"Example",$I$37>0),I16/$I$37,"") | L16: =IF(AND(ISNUMBER(I16),ISNUMBER(K16),K16>0),I16/K16,"") | N16: =IF(AND(ISNUMBER(M16),ISNUMBER(I16),I16>0),M16/I16,"")
A17: CB11 | I17: =IF(COUNT(C17:H17)=0,"",SUM(C17:H17)) | J17: =IF(AND(ISNUMBER(I17),A17<>"Example",$I$37>0),I17/$I$37,"") | L17: =IF(AND(ISNUMBER(I17),ISNUMBER(K17),K17>0),I17/K17,"") | N17: =IF(AND(ISNUMBER(M17),ISNUMBER(I17),I17>0),M17/I17,"")
A18: CB12 | I18: =IF(COUNT(C18:H18)=0,"",SUM(C18:H18)) | J18: =IF(AND(ISNUMBER(I18),A18<>"Example",$I$37>0),I18/$I$37,"") | L18: =IF(AND(ISNUMBER(I18),ISNUMBER(K18),K18>0),I18/K18,"") | N18: =IF(AND(ISNUMBER(M18),ISNUMBER(I18),I18>0),M18/I18,"")
... A36: CB30 | I36: =IF(COUNT(C36:H36)=0,"",SUM(C36:H36)) | J36: =IF(AND(ISNUMBER(I36),A36<>"Example",$I$37>0),I36/$I$37,"") | L36: =IF(AND(ISNUMBER(I36),ISNUMBER(K36),K36>0),I36/K36,"") | N36: =IF(AND(ISNUMBER(M36),ISNUMBER(I36),I36>0),M36/I36,"")
B37: Total (excluding example) | C37: =SUMIF($A$6:$A$36,"<>Example",C6:C36) -> 0 | D37: =SUMIF($A$6:$A$36,"<>Example",D6:D36) -> 0 | E37: =SUMIF($A$6:$A$36,"<>Example",E6:E36) -> 0 | F37: =SUMIF($A$6:$A$36,"<>Example",F6:F36) -> 0 | G37: =SUMIF($A$6:$A$36,"<>Example",G6:G36) -> 0 | H37: =SUMIF($A$6:$A$36,"<>Example",H6:H36) -> 0 | I37: =SUMIF($A$6:$A$36,"<>Example",I6:I36) -> 0 | J37: =IF(I37>0,1,"") | K37: =SUMIF($A$6:$A$36,"<>Example",K6:K36) -> 0 | L37: =IF(K37>0,I37/K37,"") | M37: =SUMIF($A$6:$A$36,"<>Example",M6:M36) -> 0 | N37: =IF(I37>0,M37/I37,"")
B38: Cost mix (% of total) | C38: =IF($I$37>0,C37/$I$37,"") | D38: =IF($I$37>0,D37/$I$37,"") | E38: =IF($I$37>0,E37/$I$37,"") | F38: =IF($I$37>0,F37/$I$37,"") | G38: =IF($I$37>0,G37/$I$37,"") | H38: =IF($I$37>0,H37/$I$37,"") | I38: =IF($I$37>0,I37/$I$37,"")

Sheet Findings
A1: Findings Log
A2: Record each finding with its evidence, root cause and impact. Link findings to Assessment question IDs and to recommendations.
A3: Legend: yellow cells = inputs | grey cells = calculated (do not overwrite) | green text = linked from another tab | grey italic row = example (overwrite or delete)
A5: ID | B5: Date raised | C5: Dimension | D5: Sub-component | E5: Finding / observation | F5: Evidence source(s) | G5: Root cause | H5: Business impact | I5: Severity | J5: Linked question ID(s) | K5: Stakeholder validated? | L5: Finding owner | M5: Linked recommendation(s) | N5: Status
A6: Example | B6: 46315 | C6: Governance & Decision Rights | D6: Delegations of authority | E6: Investment decisions below $250k are escalated to the Executive Committee, adding four to six weeks to minor change. | F6: Executive Committee minutes (Jan–Jun 2026); six interviews | G6: Delegations not updated since the 2019 restructure | H6: Slower delivery of minor change; executive time spent on low-value decisions | I6: High | J6: D07.03; D07.05 | K6: Yes | L6: CFO | M6: See example on Recommendations tab | N6: Validated
A7: F001
A8: F002
A9: F003
A10: F004
A11: F005
A12: F006
A13: F007
A14: F008
A15: F009
A16: F010
A17: F011
A18: F012
... A156: F150

Sheet Dashboard
B1: Operating Model Assessment Dashboard
B2: ="Client: "&IF(Engagement!C5="","[enter on Engagement tab]",Engagement!C5)&" | Status: "&Engagement!C14&" | Version: "&Engagement!C13 -> Client: [enter on Engagement tab] | Status: Mobilising | Version: 0.1
B3: All figures update automatically from the Assessment, Findings, Recommendations, Stakeholders and Document Requests tabs. Averages exclude unscored and N/A questions.
B5: Headline metrics | F5: Recommendation profile (excluding example)
B6: Overall current maturity (1–5) | D6: =IFERROR(AVERAGE(Assessment!$G$6:$G$179),"") | F6: Category | H6: 0–3 months | I6: 3–12 months | J6: 12–24 months | K6: 24+ months | L6: Total
B7: Overall target maturity (assessed questions) | D7: =IFERROR(AVERAGEIFS(Assessment!$H$6:$H$179,Assessment!$G$6:$G$179,">=1"),"") | F7: Quick win | H7: =COUNTIFS(Recommendations!$I$6:$I$86,$F7,Recommendations!$J$6:$J$86,H$6,Recommendations!$A$6:$A$86,"<>Example") -> 0 | I7: =COUNTIFS(Recommendations!$I$6:$I$86,$F7,Recommendations!$J$6:$J$86,I$6,Recommendations!$A$6:$A$86,"<>Example") -> 0 | J7: =COUNTIFS(Recommendations!$I$6:$I$86,$F7,Recommendations!$J$6:$J$86,J$6,Recommendations!$A$6:$A$86,"<>Example") -> 0 | K7: =COUNTIFS(Recommendations!$I$6:$I$86,$F7,Recommendations!$J$6:$J$86,K$6,Recommendations!$A$6:$A$86,"<>Example") -> 0 | L7: =SUM(H7:K7) -> 0
B8: Average maturity gap | D8: =IFERROR(AVERAGE(Assessment!$I$6:$I$179),"") | F8: Strategic initiative | H8: =COUNTIFS(Recommendations!$I$6:$I$86,$F8,Recommendations!$J$6:$J$86,H$6,Recommendations!$A$6:$A$86,"<>Example") -> 0 | I8: =COUNTIFS(Recommendations!$I$6:$I$86,$F8,Recommendations!$J$6:$J$86,I$6,Recommendations!$A$6:$A$86,"<>Example") -> 0 | J8: =COUNTIFS(Recommendations!$I$6:$I$86,$F8,Recommendations!$J$6:$J$86,J$6,Recommendations!$A$6:$A$86,"<>Example") -> 0 | K8: =COUNTIFS(Recommendations!$I$6:$I$86,$F8,Recommendations!$J$6:$J$86,K$6,Recommendations!$A$6:$A$86,"<>Example") -> 0 | L8: =SUM(H8:K8) -> 0
B9: Overall RAG | D9: =IF(ISNUMBER(D8),IF(D8>=Engagement!$C$40,"Red",IF(D8>=Engagement!$C$41,"Amber","Green")),"") | F9: Fill-in | H9: =COUNTIFS(Recommendations!$I$6:$I$86,$F9,Recommendations!$J$6:$J$86,H$6,Recommendations!$A$6:$A$86,"<>Example") -> 0 | I9: =COUNTIFS(Recommendations!$I$6:$I$86,$F9,Recommendations!$J$6:$J$86,I$6,Recommendations!$A$6:$A$86,"<>Example") -> 0 | J9: =COUNTIFS(Recommendations!$I$6:$I$86,$F9,Recommendations!$J$6:$J$86,J$6,Recommendations!$A$6:$A$86,"<>Example") -> 0 | K9: =COUNTIFS(Recommendations!$I$6:$I$86,$F9,Recommendations!$J$6:$J$86,K$6,Recommendations!$A$6:$A$86,"<>Example") -> 0 | L9: =SUM(H9:K9) -> 0
B10: Assessment questions scored | D10: =(COUNT(Assessment!$G$6:$G$179)+COUNTIF(Assessment!$G$6:$G$179,"N/A"))/COUNTA(Assessment!$B$6:$B$179) -> 0 | F10: Deprioritise | H10: =COUNTIFS(Recommendations!$I$6:$I$86,$F10,Recommendations!$J$6:$J$86,H$6,Recommendations!$A$6:$A$86,"<>Example") -> 0 | I10: =COUNTIFS(Recommendations!$I$6:$I$86,$F10,Recommendations!$J$6:$J$86,I$6,Recommendations!$A$6:$A$86,"<>Example") -> 0 | J10: =COUNTIFS(Recommendations!$I$6:$I$86,$F10,Recommendations!$J$6:$J$86,J$6,Recommendations!$A$6:$A$86,"<>Example") -> 0 | K10: =COUNTIFS(Recommendations!$I$6:$I$86,$F10,Recommendations!$J$6:$J$86,K$6,Recommendations!$A$6:$A$86,"<>Example") -> 0 | L10: =SUM(H10:K10) -> 0
B11: Stakeholder interviews completed | D11: =COUNTIFS(Stakeholders!$L$6:$L$66,"Completed",Stakeholders!$A$6:$A$66,"<>Example")&" of "&COUNTIFS(Stakeholders!$B$6:$B$66,"<>",Stakeholders!$A$6:$A$66,"<>Example") -> 0 of 0 | F11: Total | H11: =SUM(H7:H10) -> 0 | I11: =SUM(I7:I10) -> 0 | J11: =SUM(J7:J10) -> 0 | K11: =SUM(K7:K10) -> 0 | L11: =SUM(L7:L10) -> 0
B12: Documents received | D12: =COUNTIF('Document Requests'!$J$6:$J$89,"Received")&" of "&COUNTA('Document Requests'!$B$6:$B$89) -> 0 of 69 | F12: ="Recommendations without a category or horizon: "&(COUNTIFS(Recommendations!$A$6:$A$86,"<>Example",Recommendations!$C$6:$C$86,"<>")-L11) -> Recommendations without a category or horizon: 0
B13: Open critical and high findings | D13: =COUNTIFS(Findings!$I$6:$I$156,"Critical",Findings!$N$6:$N$156,"<>Closed",Findings!$A$6:$A$156,"<>Example")+COUNTIFS(Findings!$I$6:$I$156,"High",Findings!$N$6:$N$156,"<>Closed",Findings!$A$6:$A$156,"<>Example") -> 0
B15: Maturity and findings by dimension
B16: Code | C16: Dimension | D16: Short name | E16: Questions (#) | F16: Scored (#) | G16: % complete | H16: Avg current | I16: Avg target | J16: Avg gap | K16: Priority index | L16: RAG | M16: Critical | N16: High | O16: Medium | P16: Low | Q16: Recs (#)
B17: D01 | C17: Strategy & Direction | D17: Strategy | E17: =COUNTIFS(Assessment!$B$6:$B$179,$C17) -> 9 | F17: =COUNTIFS(Assessment!$B$6:$B$179,$C17,Assessment!$G$6:$G$179,">=1")+COUNTIFS(Assessment!$B$6:$B$179,$C17,Assessment!$G$6:$G$179,"N/A") -> 0 | G17: =IFERROR(F17/E17,0) -> 0 | H17: =IFERROR(AVERAGEIFS(Assessment!$G$6:$G$179,Assessment!$B$6:$B$179,$C17),"") | I17: =IFERROR(AVERAGEIFS(Assessment!$H$6:$H$179,Assessment!$B$6:$B$179,$C17,Assessment!$G$6:$G$179,">=1"),"") | J17: =IFERROR(AVERAGEIFS(Assessment!$I$6:$I$179,Assessment!$B$6:$B$179,$C17),"") | K17: =IFERROR(AVERAGEIFS(Assessment!$J$6:$J$179,Assessment!$B$6:$B$179,$C17),"") | L17: =IF(ISNUMBER(J17),IF(J17>=Engagement!$C$40,"Red",IF(J17>=Engagement!$C$41,"Amber","Green")),"") | M17: =COUNTIFS(Findings!$C$6:$C$156,$C17,Findings!$I$6:$I$156,M$16,Findings!$A$6:$A$156,"<>Example") -> 0 | N17: =COUNTIFS(Findings!$C$6:$C$156,$C17,Findings!$I$6:$I$156,N$16,Findings!$A$6:$A$156,"<>Example") -> 0 | O17: =COUNTIFS(Findings!$C$6:$C$156,$C17,Findings!$I$6:$I$156,O$16,Findings!$A$6:$A$156,"<>Example") -> 0 | P17: =COUNTIFS(Findings!$C$6:$C$156,$C17,Findings!$I$6:$I$156,P$16,Findings!$A$6:$A$156,"<>Example") -> 0 | Q17: =COUNTIFS(Recommendations!$B$6:$B$86,$C17,Recommendations!$A$6:$A$86,"<>Example") -> 0
B18: D02 | C18: Customers, Channels & Value Proposition | D18: Customers & Channels | E18: =COUNTIFS(Assessment!$B$6:$B$179,$C18) -> 9 | F18: =COUNTIFS(Assessment!$B$6:$B$179,$C18,Assessment!$G$6:$G$179,">=1")+COUNTIFS(Assessment!$B$6:$B$179,$C18,Assessment!$G$6:$G$179,"N/A") -> 0 | G18: =IFERROR(F18/E18,0) -> 0 | H18: =IFERROR(AVERAGEIFS(Assessment!$G$6:$G$179,Assessment!$B$6:$B$179,$C18),"") | I18: =IFERROR(AVERAGEIFS(Assessment!$H$6:$H$179,Assessment!$B$6:$B$179,$C18,Assessment!$G$6:$G$179,">=1"),"") | J18: =IFERROR(AVERAGEIFS(Assessment!$I$6:$I$179,Assessment!$B$6:$B$179,$C18),"") | K18: =IFERROR(AVERAGEIFS(Assessment!$J$6:$J$179,Assessment!$B$6:$B$179,$C18),"") | L18: =IF(ISNUMBER(J18),IF(J18>=Engagement!$C$40,"Red",IF(J18>=Engagement!$C$41,"Amber","Green")),"") | M18: =COUNTIFS(Findings!$C$6:$C$156,$C18,Findings!$I$6:$I$156,M$16,Findings!$A$6:$A$156,"<>Example") -> 0 | N18: =COUNTIFS(Findings!$C$6:$C$156,$C18,Findings!$I$6:$I$156,N$16,Findings!$A$6:$A$156,"<>Example") -> 0 | O18: =COUNTIFS(Findings!$C$6:$C$156,$C18,Findings!$I$6:$I$156,O$16,Findings!$A$6:$A$156,"<>Example") -> 0 | P18: =COUNTIFS(Findings!$C$6:$C$156,$C18,Findings!$I$6:$I$156,P$16,Findings!$A$6:$A$156,"<>Example") -> 0 | Q18: =COUNTIFS(Recommendations!$B$6:$B$86,$C18,Recommendations!$A$6:$A$86,"<>Example") -> 0
B19: D03 | C19: Products & Services | D19: Products & Services | E19: =COUNTIFS(Assessment!$B$6:$B$179,$C19) -> 8 | F19: =COUNTIFS(Assessment!$B$6:$B$179,$C19,Assessment!$G$6:$G$179,">=1")+COUNTIFS(Assessment!$B$6:$B$179,$C19,Assessment!$G$6:$G$179,"N/A") -> 0 | G19: =IFERROR(F19/E19,0) -> 0 | H19: =IFERROR(AVERAGEIFS(Assessment!$G$6:$G$179,Assessment!$B$6:$B$179,$C19),"") | I19: =IFERROR(AVERAGEIFS(Assessment!$H$6:$H$179,Assessment!$B$6:$B$179,$C19,Assessment!$G$6:$G$179,">=1"),"") | J19: =IFERROR(AVERAGEIFS(Assessment!$I$6:$I$179,Assessment!$B$6:$B$179,$C19),"") | K19: =IFERROR(AVERAGEIFS(Assessment!$J$6:$J$179,Assessment!$B$6:$B$179,$C19),"") | L19: =IF(ISNUMBER(J19),IF(J19>=Engagement!$C$40,"Red",IF(J19>=Engagement!$C$41,"Amber","Green")),"") | M19: =COUNTIFS(Findings!$C$6:$C$156,$C19,Findings!$I$6:$I$156,M$16,Findings!$A$6:$A$156,"<>Example") -> 0 | N19: =COUNTIFS(Findings!$C$6:$C$156,$C19,Findings!$I$6:$I$156,N$16,Findings!$A$6:$A$156,"<>Example") -> 0 | O19: =COUNTIFS(Findings!$C$6:$C$156,$C19,Findings!$I$6:$I$156,O$16,Findings!$A$6:$A$156,"<>Example") -> 0 | P19: =COUNTIFS(Findings!$C$6:$C$156,$C19,Findings!$I$6:$I$156,P$16,Findings!$A$6:$A$156,"<>Example") -> 0 | Q19: =COUNTIFS(Recommendations!$B$6:$B$86,$C19,Recommendations!$A$6:$A$86,"<>Example") -> 0
B20: D04 | C20: Value Streams & Processes | D20: Processes | E20: =COUNTIFS(Assessment!$B$6:$B$179,$C20) -> 10 | F20: =COUNTIFS(Assessment!$B$6:$B$179,$C20,Assessment!$G$6:$G$179,">=1")+COUNTIFS(Assessment!$B$6:$B$179,$C20,Assessment!$G$6:$G$179,"N/A") -> 0 | G20: =IFERROR(F20/E20,0) -> 0 | H20: =IFERROR(AVERAGEIFS(Assessment!$G$6:$G$179,Assessment!$B$6:$B$179,$C20),"") | I20: =IFERROR(AVERAGEIFS(Assessment!$H$6:$H$179,Assessment!$B$6:$B$179,$C20,Assessment!$G$6:$G$179,">=1"),"") | J20: =IFERROR(AVERAGEIFS(Assessment!$I$6:$I$179,Assessment!$B$6:$B$179,$C20),"") | K20: =IFERROR(AVERAGEIFS(Assessment!$J$6:$J$179,Assessment!$B$6:$B$179,$C20),"") | L20: =IF(ISNUMBER(J20),IF(J20>=Engagement!$C$40,"Red",IF(J20>=Engagement!$C$41,"Amber","Green")),"") | M20: =COUNTIFS(Findings!$C$6:$C$156,$C20,Findings!$I$6:$I$156,M$16,Findings!$A$6:$A$156,"<>Example") -> 0 | N20: =COUNTIFS(Findings!$C$6:$C$156,$C20,Findings!$I$6:$I$156,N$16,Findings!$A$6:$A$156,"<>Example") -> 0 | O20: =COUNTIFS(Findings!$C$6:$C$156,$C20,Findings!$I$6:$I$156,O$16,Findings!$A$6:$A$156,"<>Example") -> 0 | P20: =COUNTIFS(Findings!$C$6:$C$156,$C20,Findings!$I$6:$I$156,P$16,Findings!$A$6:$A$156,"<>Example") -> 0 | Q20: =COUNTIFS(Recommendations!$B$6:$B$86,$C20,Recommendations!$A$6:$A$86,"<>Example") -> 0
B21: D05 | C21: Business Capabilities | D21: Capabilities | E21: =COUNTIFS(Assessment!$B$6:$B$179,$C21) -> 8 | F21: =COUNTIFS(Assessment!$B$6:$B$179,$C21,Assessment!$G$6:$G$179,">=1")+COUNTIFS(Assessment!$B$6:$B$179,$C21,Assessment!$G$6:$G$179,"N/A") -> 0 | G21: =IFERROR(F21/E21,0) -> 0 | H21: =IFERROR(AVERAGEIFS(Assessment!$G$6:$G$179,Assessment!$B$6:$B$179,$C21),"") | I21: =IFERROR(AVERAGEIFS(Assessment!$H$6:$H$179,Assessment!$B$6:$B$179,$C21,Assessment!$G$6:$G$179,">=1"),"") | J21: =IFERROR(AVERAGEIFS(Assessment!$I$6:$I$179,Assessment!$B$6:$B$179,$C21),"") | K21: =IFERROR(AVERAGEIFS(Assessment!$J$6:$J$179,Assessment!$B$6:$B$179,$C21),"") | L21: =IF(ISNUMBER(J21),IF(J21>=Engagement!$C$40,"Red",IF(J21>=Engagement!$C$41,"Amber","Green")),"") | M21: =COUNTIFS(Findings!$C$6:$C$156,$C21,Findings!$I$6:$I$156,M$16,Findings!$A$6:$A$156,"<>Example") -> 0 | N21: =COUNTIFS(Findings!$C$6:$C$156,$C21,Findings!$I$6:$I$156,N$16,Findings!$A$6:$A$156,"<>Example") -> 0 | O21: =COUNTIFS(Findings!$C$6:$C$156,$C21,Findings!$I$6:$I$156,O$16,Findings!$A$6:$A$156,"<>Example") -> 0 | P21: =COUNTIFS(Findings!$C$6:$C$156,$C21,Findings!$I$6:$I$156,P$16,Findings!$A$6:$A$156,"<>Example") -> 0 | Q21: =COUNTIFS(Recommendations!$B$6:$B$86,$C21,Recommendations!$A$6:$A$86,"<>Example") -> 0
B22: D06 | C22: Organisation Structure & Roles | D22: Structure | E22: =COUNTIFS(Assessment!$B$6:$B$179,$C22) -> 9 | F22: =COUNTIFS(Assessment!$B$6:$B$179,$C22,Assessment!$G$6:$G$179,">=1")+COUNTIFS(Assessment!$B$6:$B$179,$C22,Assessment!$G$6:$G$179,"N/A") -> 0 | G22: =IFERROR(F22/E22,0) -> 0 | H22: =IFERROR(AVERAGEIFS(Assessment!$G$6:$G$179,Assessment!$B$6:$B$179,$C22),"") | I22: =IFERROR(AVERAGEIFS(Assessment!$H$6:$H$179,Assessment!$B$6:$B$179,$C22,Assessment!$G$6:$G$179,">=1"),"") | J22: =IFERROR(AVERAGEIFS(Assessment!$I$6:$I$179,Assessment!$B$6:$B$179,$C22),"") | K22: =IFERROR(AVERAGEIFS(Assessment!$J$6:$J$179,Assessment!$B$6:$B$179,$C22),"") | L22: =IF(ISNUMBER(J22),IF(J22>=Engagement!$C$40,"Red",IF(J22>=Engagement!$C$41,"Amber","Green")),"") | M22: =COUNTIFS(Findings!$C$6:$C$156,$C22,Findings!$I$6:$I$156,M$16,Findings!$A$6:$A$156,"<>Example") -> 0 | N22: =COUNTIFS(Findings!$C$6:$C$156,$C22,Findings!$I$6:$I$156,N$16,Findings!$A$6:$A$156,"<>Example") -> 0 | O22: =COUNTIFS(Findings!$C$6:$C$156,$C22,Findings!$I$6:$I$156,O$16,Findings!$A$6:$A$156,"<>Example") -> 0 | P22: =COUNTIFS(Findings!$C$6:$C$156,$C22,Findings!$I$6:$I$156,P$16,Findings!$A$6:$A$156,"<>Example") -> 0 | Q22: =COUNTIFS(Recommendations!$B$6:$B$86,$C22,Recommendations!$A$6:$A$86,"<>Example") -> 0
B23: D07 | C23: Governance & Decision Rights | D23: Governance | E23: =COUNTIFS(Assessment!$B$6:$B$179,$C23) -> 9 | F23: =COUNTIFS(Assessment!$B$6:$B$179,$C23,Assessment!$G$6:$G$179,">=1")+COUNTIFS(Assessment!$B$6:$B$179,$C23,Assessment!$G$6:$G$179,"N/A") -> 0 | G23: =IFERROR(F23/E23,0) -> 0 | H23: =IFERROR(AVERAGEIFS(Assessment!$G$6:$G$179,Assessment!$B$6:$B$179,$C23),"") | I23: =IFERROR(AVERAGEIFS(Assessment!$H$6:$H$179,Assessment!$B$6:$B$179,$C23,Assessment!$G$6:$G$179,">=1"),"") | J23: =IFERROR(AVERAGEIFS(Assessment!$I$6:$I$179,Assessment!$B$6:$B$179,$C23),"") | K23: =IFERROR(AVERAGEIFS(Assessment!$J$6:$J$179,Assessment!$B$6:$B$179,$C23),"") | L23: =IF(ISNUMBER(J23),IF(J23>=Engagement!$C$40,"Red",IF(J23>=Engagement!$C$41,"Amber","Green")),"") | M23: =COUNTIFS(Findings!$C$6:$C$156,$C23,Findings!$I$6:$I$156,M$16,Findings!$A$6:$A$156,"<>Example") -> 0 | N23: =COUNTIFS(Findings!$C$6:$C$156,$C23,Findings!$I$6:$I$156,N$16,Findings!$A$6:$A$156,"<>Example") -> 0 | O23: =COUNTIFS(Findings!$C$6:$C$156,$C23,Findings!$I$6:$I$156,O$16,Findings!$A$6:$A$156,"<>Example") -> 0 | P23: =COUNTIFS(Findings!$C$6:$C$156,$C23,Findings!$I$6:$I$156,P$16,Findings!$A$6:$A$156,"<>Example") -> 0 | Q23: =COUNTIFS(Recommendations!$B$6:$B$86,$C23,Recommendations!$A$6:$A$86,"<>Example") -> 0
B24: D08 | C24: People, Workforce & Skills | D24: People | E24: =COUNTIFS(Assessment!$B$6:$B$179,$C24) -> 10 | F24: =COUNTIFS(Assessment!$B$6:$B$179,$C24,Assessment!$G$6:$G$179,">=1")+COUNTIFS(Assessment!$B$6:$B$179,$C24,Assessment!$G$6:$G$179,"N/A") -> 0 | G24: =IFERROR(F24/E24,0) -> 0 | H24: =IFERROR(AVERAGEIFS(Assessment!$G$6:$G$179,Assessment!$B$6:$B$179,$C24),"") | I24: =IFERROR(AVERAGEIFS(Assessment!$H$6:$H$179,Assessment!$B$6:$B$179,$C24,Assessment!$G$6:$G$179,">=1"),"") | J24: =IFERROR(AVERAGEIFS(Assessment!$I$6:$I$179,Assessment!$B$6:$B$179,$C24),"") | K24: =IFERROR(AVERAGEIFS(Assessment!$J$6:$J$179,Assessment!$B$6:$B$179,$C24),"") | L24: =IF(ISNUMBER(J24),IF(J24>=Engagement!$C$40,"Red",IF(J24>=Engagement!$C$41,"Amber","Green")),"") | M24: =COUNTIFS(Findings!$C$6:$C$156,$C24,Findings!$I$6:$I$156,M$16,Findings!$A$6:$A$156,"<>Example") -> 0 | N24: =COUNTIFS(Findings!$C$6:$C$156,$C24,Findings!$I$6:$I$156,N$16,Findings!$A$6:$A$156,"<>Example") -> 0 | O24: =COUNTIFS(Findings!$C$6:$C$156,$C24,Findings!$I$6:$I$156,O$16,Findings!$A$6:$A$156,"<>Example") -> 0 | P24: =COUNTIFS(Findings!$C$6:$C$156,$C24,Findings!$I$6:$I$156,P$16,Findings!$A$6:$A$156,"<>Example") -> 0 | Q24: =COUNTIFS(Recommendations!$B$6:$B$86,$C24,Recommendations!$A$6:$A$86,"<>Example") -> 0
B25: D09 | C25: Culture, Leadership & Behaviours | D25: Culture | E25: =COUNTIFS(Assessment!$B$6:$B$179,$C25) -> 9 | F25: =COUNTIFS(Assessment!$B$6:$B$179,$C25,Assessment!$G$6:$G$179,">=1")+COUNTIFS(Assessment!$B$6:$B$179,$C25,Assessment!$G$6:$G$179,"N/A") -> 0 | G25: =IFERROR(F25/E25,0) -> 0 | H25: =IFERROR(AVERAGEIFS(Assessment!$G$6:$G$179,Assessment!$B$6:$B$179,$C25),"") | I25: =IFERROR(AVERAGEIFS(Assessment!$H$6:$H$179,Assessment!$B$6:$B$179,$C25,Assessment!$G$6:$G$179,">=1"),"") | J25: =IFERROR(AVERAGEIFS(Assessment!$I$6:$I$179,Assessment!$B$6:$B$179,$C25),"") | K25: =IFERROR(AVERAGEIFS(Assessment!$J$6:$J$179,Assessment!$B$6:$B$179,$C25),"") | L25: =IF(ISNUMBER(J25),IF(J25>=Engagement!$C$40,"Red",IF(J25>=Engagement!$C$41,"Amber","Green")),"") | M25: =COUNTIFS(Findings!$C$6:$C$156,$C25,Findings!$I$6:$I$156,M$16,Findings!$A$6:$A$156,"<>Example") -> 0 | N25: =COUNTIFS(Findings!$C$6:$C$156,$C25,Findings!$I$6:$I$156,N$16,Findings!$A$6:$A$156,"<>Example") -> 0 | O25: =COUNTIFS(Findings!$C$6:$C$156,$C25,Findings!$I$6:$I$156,O$16,Findings!$A$6:$A$156,"<>Example") -> 0 | P25: =COUNTIFS(Findings!$C$6:$C$156,$C25,Findings!$I$6:$I$156,P$16,Findings!$A$6:$A$156,"<>Example") -> 0 | Q25: =COUNTIFS(Recommendations!$B$6:$B$86,$C25,Recommendations!$A$6:$A$86,"<>Example") -> 0
B26: D10 | C26: Performance Management & Planning | D26: Performance | E26: =COUNTIFS(Assessment!$B$6:$B$179,$C26) -> 9 | F26: =COUNTIFS(Assessment!$B$6:$B$179,$C26,Assessment!$G$6:$G$179,">=1")+COUNTIFS(Assessment!$B$6:$B$179,$C26,Assessment!$G$6:$G$179,"N/A") -> 0 | G26: =IFERROR(F26/E26,0) -> 0 | H26: =IFERROR(AVERAGEIFS(Assessment!$G$6:$G$179,Assessment!$B$6:$B$179,$C26),"") | I26: =IFERROR(AVERAGEIFS(Assessment!$H$6:$H$179,Assessment!$B$6:$B$179,$C26,Assessment!$G$6:$G$179,">=1"),"") | J26: =IFERROR(AVERAGEIFS(Assessment!$I$6:$I$179,Assessment!$B$6:$B$179,$C26),"") | K26: =IFERROR(AVERAGEIFS(Assessment!$J$6:$J$179,Assessment!$B$6:$B$179,$C26),"") | L26: =IF(ISNUMBER(J26),IF(J26>=Engagement!$C$40,"Red",IF(J26>=Engagement!$C$41,"Amber","Green")),"") | M26: =COUNTIFS(Findings!$C$6:$C$156,$C26,Findings!$I$6:$I$156,M$16,Findings!$A$6:$A$156,"<>Example") -> 0 | N26: =COUNTIFS(Findings!$C$6:$C$156,$C26,Findings!$I$6:$I$156,N$16,Findings!$A$6:$A$156,"<>Example") -> 0 | O26: =COUNTIFS(Findings!$C$6:$C$156,$C26,Findings!$I$6:$I$156,O$16,Findings!$A$6:$A$156,"<>Example") -> 0 | P26: =COUNTIFS(Findings!$C$6:$C$156,$C26,Findings!$I$6:$I$156,P$16,Findings!$A$6:$A$156,"<>Example") -> 0 | Q26: =COUNTIFS(Recommendations!$B$6:$B$86,$C26,Recommendations!$A$6:$A$86,"<>Example") -> 0
B27: D11 | C27: Technology & Applications | D27: Technology | E27: =COUNTIFS(Assessment!$B$6:$B$179,$C27) -> 11 | F27: =COUNTIFS(Assessment!$B$6:$B$179,$C27,Assessment!$G$6:$G$179,">=1")+COUNTIFS(Assessment!$B$6:$B$179,$C27,Assessment!$G$6:$G$179,"N/A") -> 0 | G27: =IFERROR(F27/E27,0) -> 0 | H27: =IFERROR(AVERAGEIFS(Assessment!$G$6:$G$179,Assessment!$B$6:$B$179,$C27),"") | I27: =IFERROR(AVERAGEIFS(Assessment!$H$6:$H$179,Assessment!$B$6:$B$179,$C27,Assessment!$G$6:$G$179,">=1"),"") | J27: =IFERROR(AVERAGEIFS(Assessment!$I$6:$I$179,Assessment!$B$6:$B$179,$C27),"") | K27: =IFERROR(AVERAGEIFS(Assessment!$J$6:$J$179,Assessment!$B$6:$B$179,$C27),"") | L27: =IF(ISNUMBER(J27),IF(J27>=Engagement!$C$40,"Red",IF(J27>=Engagement!$C$41,"Amber","Green")),"") | M27: =COUNTIFS(Findings!$C$6:$C$156,$C27,Findings!$I$6:$I$156,M$16,Findings!$A$6:$A$156,"<>Example") -> 0 | N27: =COUNTIFS(Findings!$C$6:$C$156,$C27,Findings!$I$6:$I$156,N$16,Findings!$A$6:$A$156,"<>Example") -> 0 | O27: =COUNTIFS(Findings!$C$6:$C$156,$C27,Findings!$I$6:$I$156,O$16,Findings!$A$6:$A$156,"<>Example") -> 0 | P27: =COUNTIFS(Findings!$C$6:$C$156,$C27,Findings!$I$6:$I$156,P$16,Findings!$A$6:$A$156,"<>Example") -> 0 | Q27: =COUNTIFS(Recommendations!$B$6:$B$86,$C27,Recommendations!$A$6:$A$86,"<>Example") -> 0
B28: D12 | C28: Data, Information & Analytics | D28: Data | E28: =COUNTIFS(Assessment!$B$6:$B$179,$C28) -> 9 | F28: =COUNTIFS(Assessment!$B$6:$B$179,$C28,Assessment!$G$6:$G$179,">=1")+COUNTIFS(Assessment!$B$6:$B$179,$C28,Assessment!$G$6:$G$179,"N/A") -> 0 | G28: =IFERROR(F28/E28,0) -> 0 | H28: =IFERROR(AVERAGEIFS(Assessment!$G$6:$G$179,Assessment!$B$6:$B$179,$C28),"") | I28: =IFERROR(AVERAGEIFS(Assessment!$H$6:$H$179,Assessment!$B$6:$B$179,$C28,Assessment!$G$6:$G$179,">=1"),"") | J28: =IFERROR(AVERAGEIFS(Assessment!$I$6:$I$179,Assessment!$B$6:$B$179,$C28),"") | K28: =IFERROR(AVERAGEIFS(Assessment!$J$6:$J$179,Assessment!$B$6:$B$179,$C28),"") | L28: =IF(ISNUMBER(J28),IF(J28>=Engagement!$C$40,"Red",IF(J28>=Engagement!$C$41,"Amber","Green")),"") | M28: =COUNTIFS(Findings!$C$6:$C$156,$C28,Findings!$I$6:$I$156,M$16,Findings!$A$6:$A$156,"<>Example") -> 0 | N28: =COUNTIFS(Findings!$C$6:$C$156,$C28,Findings!$I$6:$I$156,N$16,Findings!$A$6:$A$156,"<>Example") -> 0 | O28: =COUNTIFS(Findings!$C$6:$C$156,$C28,Findings!$I$6:$I$156,O$16,Findings!$A$6:$A$156,"<>Example") -> 0 | P28: =COUNTIFS(Findings!$C$6:$C$156,$C28,Findings!$I$6:$I$156,P$16,Findings!$A$6:$A$156,"<>Example") -> 0 | Q28: =COUNTIFS(Recommendations!$B$6:$B$86,$C28,Recommendations!$A$6:$A$86,"<>Example") -> 0
... B33: D17 | C33: Change, Transformation & Continuous Improvement | D33: Change | E33: =COUNTIFS(Assessment!$B$6:$B$179,$C33) -> 10 | F33: =COUNTIFS(Assessment!$B$6:$B$179,$C33,Assessment!$G$6:$G$179,">=1")+COUNTIFS(Assessment!$B$6:$B$179,$C33,Assessment!$G$6:$G$179,"N/A") -> 0 | G33: =IFERROR(F33/E33,0) -> 0 | H33: =IFERROR(AVERAGEIFS(Assessment!$G$6:$G$179,Assessment!$B$6:$B$179,$C33),"") | I33: =IFERROR(AVERAGEIFS(Assessment!$H$6:$H$179,Assessment!$B$6:$B$179,$C33,Assessment!$G$6:$G$179,">=1"),"") | J33: =IFERROR(AVERAGEIFS(Assessment!$I$6:$I$179,Assessment!$B$6:$B$179,$C33),"") | K33: =IFERROR(AVERAGEIFS(Assessment!$J$6:$J$179,Assessment!$B$6:$B$179,$C33),"") | L33: =IF(ISNUMBER(J33),IF(J33>=Engagement!$C$40,"Red",IF(J33>=Engagement!$C$41,"Amber","Green")),"") | M33: =COUNTIFS(Findings!$C$6:$C$156,$C33,Findings!$I$6:$I$156,M$16,Findings!$A$6:$A$156,"<>Example") -> 0 | N33: =COUNTIFS(Findings!$C$6:$C$156,$C33,Findings!$I$6:$I$156,N$16,Findings!$A$6:$A$156,"<>Example") -> 0 | O33: =COUNTIFS(Findings!$C$6:$C$156,$C33,Findings!$I$6:$I$156,O$16,Findings!$A$6:$A$156,"<>Example") -> 0 | P33: =COUNTIFS(Findings!$C$6:$C$156,$C33,Findings!$I$6:$I$156,P$16,Findings!$A$6:$A$156,"<>Example") -> 0 | Q33: =COUNTIFS(Recommendations!$B$6:$B$86,$C33,Recommendations!$A$6:$A$86,"<>Example") -> 0
B34: All | C34: Overall | E34: =SUM(E17:E33) -> 157 | F34: =SUM(F17:F33) -> 0 | G34: =IFERROR(F34/E34,0) -> 0 | H34: =D6 | I34: =D7 | J34: =D8 | K34: =IFERROR(AVERAGE(Assessment!$J$6:$J$179),"") | L34: =D9 | M34: =SUM(M17:M33) -> 0 | N34: =SUM(N17:N33) -> 0 | O34: =SUM(O17:O33) -> 0 | P34: =SUM(P17:P33) -> 0 | Q34: =SUM(Q17:Q33) -> 0
B36: Charts

Sheet Current vs Target
A1: Current vs Target Operating Model
A2: Summarise the current state, target state and key shifts for each dimension. Maturity figures link to the Dashboard.
A3: Legend: yellow cells = inputs | grey cells = calculated (do not overwrite) | green text = linked from another tab | grey italic row = example (overwrite or delete)
A5: Code | B5: Dimension | C5: Current maturity | D5: Target maturity | E5: Gap | F5: RAG | G5: Current state summary | H5: Target state description | I5: Key shifts (from → to) | J5: Design principles applied | K5: Key enablers & dependencies | L5: Linked recommendations
A6: D01 | B6: Strategy & Direction | C6: =Dashboard!H17 | D6: =Dashboard!I17 | E6: =Dashboard!J17 | F6: =Dashboard!L17
A7: D02 | B7: Customers, Channels & Value Proposition | C7: =Dashboard!H18 | D7: =Dashboard!I18 | E7: =Dashboard!J18 | F7: =Dashboard!L18
A8: D03 | B8: Products & Services | C8: =Dashboard!H19 | D8: =Dashboard!I19 | E8: =Dashboard!J19 | F8: =Dashboard!L19
A9: D04 | B9: Value Streams & Processes | C9: =Dashboard!H20 | D9: =Dashboard!I20 | E9: =Dashboard!J20 | F9: =Dashboard!L20
A10: D05 | B10: Business Capabilities | C10: =Dashboard!H21 | D10: =Dashboard!I21 | E10: =Dashboard!J21 | F10: =Dashboard!L21
A11: D06 | B11: Organisation Structure & Roles | C11: =Dashboard!H22 | D11: =Dashboard!I22 | E11: =Dashboard!J22 | F11: =Dashboard!L22
A12: D07 | B12: Governance & Decision Rights | C12: =Dashboard!H23 | D12: =Dashboard!I23 | E12: =Dashboard!J23 | F12: =Dashboard!L23
A13: D08 | B13: People, Workforce & Skills | C13: =Dashboard!H24 | D13: =Dashboard!I24 | E13: =Dashboard!J24 | F13: =Dashboard!L24
A14: D09 | B14: Culture, Leadership & Behaviours | C14: =Dashboard!H25 | D14: =Dashboard!I25 | E14: =Dashboard!J25 | F14: =Dashboard!L25
A15: D10 | B15: Performance Management & Planning | C15: =Dashboard!H26 | D15: =Dashboard!I26 | E15: =Dashboard!J26 | F15: =Dashboard!L26
A16: D11 | B16: Technology & Applications | C16: =Dashboard!H27 | D16: =Dashboard!I27 | E16: =Dashboard!J27 | F16: =Dashboard!L27
A17: D12 | B17: Data, Information & Analytics | C17: =Dashboard!H28 | D17: =Dashboard!I28 | E17: =Dashboard!J28 | F17: =Dashboard!L28
... A22: D17 | B22: Change, Transformation & Continuous Improvement | C22: =Dashboard!H33 | D22: =Dashboard!I33 | E22: =Dashboard!J33 | F22: =Dashboard!L33

Sheet Recommendations
A1: Recommendations & Roadmap
A2: Score Value (benefit and strategic impact) and Ease (cost, complexity, risk, time; 5 = easiest) from 1 to 5. Category is derived from the prioritisation threshold on the Engagement tab.
A3: Legend: yellow cells = inputs | grey cells = calculated (do not overwrite) | green text = linked from another tab | grey italic row = example (overwrite or delete)
A5: ID | B5: Dimension | C5: Recommendation | D5: Linked finding(s) | E5: Expected benefits | F5: Value (1–5) | G5: Ease (1–5) | H5: Priority score | I5: Category | J5: Horizon | K5: Indicative cost ($) | L5: Accountable owner | M5: Dependencies | N5: Key risks | O5: Status
A6: Example | B6: Governance & Decision Rights | C6: Refresh delegations of authority to align with the current structure and risk appetite, devolving investment decisions below $250k to business unit heads. | D6: Example finding | E6: Faster delivery of minor change; executive time refocused on strategic decisions | F6: 4 | G6: 4 | H6: =IF(AND(ISNUMBER(F6),ISNUMBER(G6)),F6*G6,"") -> 16 | I6: =IF(AND(ISNUMBER(F6),ISNUMBER(G6)),IF(F6>=Engagement!$C$42,IF(G6>=Engagement!$C$42,"Quick win","Strategic initiative"),IF(G6>=Engagement!$C$42,"Fill-in","Deprioritise")),"") -> Quick win | J6: 0–3 months | K6: 40000 | L6: CFO | M6: Refresh of risk appetite statement | N6: Weaker control if delegations are not system-enforced | O6: Proposed
A7: R001 | H7: =IF(AND(ISNUMBER(F7),ISNUMBER(G7)),F7*G7,"") | I7: =IF(AND(ISNUMBER(F7),ISNUMBER(G7)),IF(F7>=Engagement!$C$42,IF(G7>=Engagement!$C$42,"Quick win","Strategic initiative"),IF(G7>=Engagement!$C$42,"Fill-in","Deprioritise")),"")
A8: R002 | H8: =IF(AND(ISNUMBER(F8),ISNUMBER(G8)),F8*G8,"") | I8: =IF(AND(ISNUMBER(F8),ISNUMBER(G8)),IF(F8>=Engagement!$C$42,IF(G8>=Engagement!$C$42,"Quick win","Strategic initiative"),IF(G8>=Engagement!$C$42,"Fill-in","Deprioritise")),"")
A9: R003 | H9: =IF(AND(ISNUMBER(F9),ISNUMBER(G9)),F9*G9,"") | I9: =IF(AND(ISNUMBER(F9),ISNUMBER(G9)),IF(F9>=Engagement!$C$42,IF(G9>=Engagement!$C$42,"Quick win","Strategic initiative"),IF(G9>=Engagement!$C$42,"Fill-in","Deprioritise")),"")
A10: R004 | H10: =IF(AND(ISNUMBER(F10),ISNUMBER(G10)),F10*G10,"") | I10: =IF(AND(ISNUMBER(F10),ISNUMBER(G10)),IF(F10>=Engagement!$C$42,IF(G10>=Engagement!$C$42,"Quick win","Strategic initiative"),IF(G10>=Engagement!$C$42,"Fill-in","Deprioritise")),"")
A11: R005 | H11: =IF(AND(ISNUMBER(F11),ISNUMBER(G11)),F11*G11,"") | I11: =IF(AND(ISNUMBER(F11),ISNUMBER(G11)),IF(F11>=Engagement!$C$42,IF(G11>=Engagement!$C$42,"Quick win","Strategic initiative"),IF(G11>=Engagement!$C$42,"Fill-in","Deprioritise")),"")
A12: R006 | H12: =IF(AND(ISNUMBER(F12),ISNUMBER(G12)),F12*G12,"") | I12: =IF(AND(ISNUMBER(F12),ISNUMBER(G12)),IF(F12>=Engagement!$C$42,IF(G12>=Engagement!$C$42,"Quick win","Strategic initiative"),IF(G12>=Engagement!$C$42,"Fill-in","Deprioritise")),"")
A13: R007 | H13: =IF(AND(ISNUMBER(F13),ISNUMBER(G13)),F13*G13,"") | I13: =IF(AND(ISNUMBER(F13),ISNUMBER(G13)),IF(F13>=Engagement!$C$42,IF(G13>=Engagement!$C$42,"Quick win","Strategic initiative"),IF(G13>=Engagement!$C$42,"Fill-in","Deprioritise")),"")
A14: R008 | H14: =IF(AND(ISNUMBER(F14),ISNUMBER(G14)),F14*G14,"") | I14: =IF(AND(ISNUMBER(F14),ISNUMBER(G14)),IF(F14>=Engagement!$C$42,IF(G14>=Engagement!$C$42,"Quick win","Strategic initiative"),IF(G14>=Engagement!$C$42,"Fill-in","Deprioritise")),"")
A15: R009 | H15: =IF(AND(ISNUMBER(F15),ISNUMBER(G15)),F15*G15,"") | I15: =IF(AND(ISNUMBER(F15),ISNUMBER(G15)),IF(F15>=Engagement!$C$42,IF(G15>=Engagement!$C$42,"Quick win","Strategic initiative"),IF(G15>=Engagement!$C$42,"Fill-in","Deprioritise")),"")
A16: R010 | H16: =IF(AND(ISNUMBER(F16),ISNUMBER(G16)),F16*G16,"") | I16: =IF(AND(ISNUMBER(F16),ISNUMBER(G16)),IF(F16>=Engagement!$C$42,IF(G16>=Engagement!$C$42,"Quick win","Strategic initiative"),IF(G16>=Engagement!$C$42,"Fill-in","Deprioritise")),"")
A17: R011 | H17: =IF(AND(ISNUMBER(F17),ISNUMBER(G17)),F17*G17,"") | I17: =IF(AND(ISNUMBER(F17),ISNUMBER(G17)),IF(F17>=Engagement!$C$42,IF(G17>=Engagement!$C$42,"Quick win","Strategic initiative"),IF(G17>=Engagement!$C$42,"Fill-in","Deprioritise")),"")
A18: R012 | H18: =IF(AND(ISNUMBER(F18),ISNUMBER(G18)),F18*G18,"") | I18: =IF(AND(ISNUMBER(F18),ISNUMBER(G18)),IF(F18>=Engagement!$C$42,IF(G18>=Engagement!$C$42,"Quick win","Strategic initiative"),IF(G18>=Engagement!$C$42,"Fill-in","Deprioritise")),"")
... A86: R080 | H86: =IF(AND(ISNUMBER(F86),ISNUMBER(G86)),F86*G86,"") | I86: =IF(AND(ISNUMBER(F86),ISNUMBER(G86)),IF(F86>=Engagement!$C$42,IF(G86>=Engagement!$C$42,"Quick win","Strategic initiative"),IF(G86>=Engagement!$C$42,"Fill-in","Deprioritise")),"")
B87: Total indicative cost (excluding example) | K87: =SUMIF($A$6:$A$86,"<>Example",K6:K86) -> 0

Sheet Lists
A1: Dimensions | B1: Maturity score | C1: Importance weight | D1: High / Medium / Low | E1: RAG | F1: Severity / criticality | G1: Yes / No / Partial | H1: Yes / No | I1: Validation | J1: Finding status | K1: Recommendation status | L1: Horizon | M1: Recommendation category | N1: Stakeholder group | O1: Interview status | P1: Document status | Q1: Differentiation | R1: Sourcing model | S1: Automation level | T1: Hosting model | U1: Support status | V1: Data classification | W1: Supplier segment (Kraljic) | X1: Security assurance | Y1: Site type | Z1: Tenure | AA1: RAPID code | AB1: Engagement status | AC1: Principle status | AE1: Nature of work | AF1: Span min | AG1: Span max | AI1: Importance | AJ1: Weight
A2: Strategy & Direction | B2: 1 | C2: 1 | D2: High | E2: Red | F2: Critical | G2: Yes | H2: Yes | I2: Yes | J2: Open | K2: Proposed | L2: 0–3 months | M2: Quick win | N2: Board / Chair | O2: Not scheduled | P2: Not requested | Q2: Differentiating | R2: In-house | S2: Manual | T2: On-premises | U2: Supported | V2: Public | W2: Strategic | X2: ISO/IEC 27001 certified | Y2: Head office | Z2: Owned | AA2: R | AB2: Mobilising | AC2: Proposed | AE2: Specialist / complex | AF2: 5 | AG2: 7 | AI2: High | AJ2: 3
A3: Customers, Channels & Value Proposition | B3: 2 | C3: 2 | D3: Medium | E3: Amber | F3: High | G3: No | H3: No | I3: No | J3: Validated | K3: Endorsed | L3: 3–12 months | M3: Strategic initiative | N3: CEO & Executive Leadership | O3: Scheduled | P3: Requested | Q3: Competitive parity | R3: Shared service | S3: Partially automated | T3: Private cloud | U3: Extended support | V3: Internal | W3: Leverage | X3: SOC 2 Type II report | Y3: Regional office | Z3: Leased | AA3: A | AB3: Discovery | AC3: Agreed | AE3: Mixed / professional | AF3: 8 | AG3: 10 | AI3: Medium | AJ3: 2
A4: Products & Services | B4: 3 | C4: 3 | D4: Low | E4: Green | F4: Medium | G4: Partial | I4: Pending | J4: Closed | K4: In progress | L4: 12–24 months | M4: Fill-in | N4: Business Unit & Operations Leaders | O4: Completed | P4: Received | Q4: Commodity | R4: Outsourced | S4: Highly automated | T4: Public cloud (IaaS / PaaS) | U4: End of life | V4: Confidential | W4: Bottleneck | X4: Assessed by client | Y4: Service centre | Z4: Shared / co-located | AA4: P | AB4: Analysis | AC4: Retired | AE4: Standardised / operational | AF4: 11 | AG4: 15 | AI4: Low | AJ4: 1
A5: Value Streams & Processes | B5: 4 | F5: Low | K5: Complete | L5: 24+ months | M5: Deprioritise | N5: Team Leaders & Frontline Staff | O5: Cancelled | P5: Partially received | R5: Partnered | T5: SaaS | U5: Unknown | V5: Restricted | W5: Non-critical | X5: Not assessed | Y5: Contact centre | Z5: Serviced office | AA5: I | AB5: Recommendations | AE5: Highly routine / transactional | AF5: 15 | AG5: 20
A6: Business Capabilities | B6: 5 | K6: Rejected | N6: CFO & Finance | P6: Not available | R6: Hybrid | T6: Hybrid | Y6: Operations site | AA6: D | AB6: Complete
A7: Organisation Structure & Roles | B7: N/A | N7: CHRO & People | Y7: Data centre | AE7: Indicative practitioner benchmarks for average span of control by nature of work. Adjust to the client context and any benchmark data available.
A8: Governance & Decision Rights | N8: CIO, Technology & Data | Y8: Warehouse / logistics
A9: People, Workforce & Skills | N9: CRO, Risk, Compliance & Audit | Y9: Retail / shopfront
A10: Culture, Leadership & Behaviours | N10: Procurement & Supplier Management
A11: Performance Management & Planning | N11: Customers & External Partners
A12: Technology & Applications
A13: Data, Information & Analytics
A14: Suppliers, Partners & Sourcing
A15: Locations & Physical Assets
A16: Risk, Compliance, Security & Resilience
A17: Finance, Funding & Cost Model
A18: Change, Transformation & Continuous Improvement
